Workbook

Sheet CONSOLIDADO 2026
A1: WEEK | B1: MXT/MXG | C1: ITEM | D1: SUPPLIER | E1: TYPE | F1: NO TOCAR | G1: REFERENCIA | H1: INVOICE # | I1: MOUTH | J1: INVOICE DATE | K1: PEDIMENTO | L1: PRO NUMBER/ TRACKING # | M1: IMPO/ EXPO MOOD | N1: TRAILER/ CONTAINER | O1: PAGO DE IMPUESTOS | P1: PAGO A TERCEROS | Q1: SUB-TOTAL | R1: IVA | S1: RETENTION | T1: TOTAL | U1: CURRENCY | V1: USD AMOUNT | W1: SHIP DATE | X1: SHIPPER | Y1: ORIGIN | Z1: DESTINATION | AA1: CONSIGNEE | AB1: BU | AC1: I/O | AD1: TYPE | AE1: ACCOUNT | AF1: COMMENTS | AG1: ACCOUNT | AH1: MXN AMOUNT | AI1: W | AJ1: CHARGE BACK | AK1: AMOUNT USD | AL1: INVOICED | AM1: PFA | AN1: PFA2 | AO1: PFA3
A2: 01 | B2: MXG | C2: 1 | D2: AERO WORLDWIDE GmbH | E2: Freight | F2: =E2&G2 -> FreightRM-A-0383AI25-M19 | G2: RM-A-0383AI25-M19 | H2: INV-1097 | I2: ENERO | J2: 46054 | L2: OTRO | M2: IMPO | N2: OTRO | O2: 0 | P2: 0 | Q2: 3121 | R2: 0 | S2: 0 | T2: 3121 | U2: USD | V2: =T2 -> 3121 | W2: VARIAS | X2: VARIOUS | Y2: VARIOUS | Z2: ZAC | AA2: JEG | AB2: M19 | AC2: I | AD2: AIR IMPO | AE2: 67130000 | AF2: NO COMMENTS | AI2: 01 | AJ2: NO | AK2: 0 | AL2: NO
A3: 01 | B3: MXG | C3: 2 | D3: DHL EXPRESS MEXICO, S.A. DE C.V. | E3: Freight | F3: =E3&G3 -> FreightPAQUETERIA | G3: PAQUETERIA | H3: ZCLIR00826898 | I3: ENERO | J3: 46054 | K3: OTRO | L3: 3636567771 | M3: AIR IMPO | N3: OTRO | O3: 0 | P3: 0 | Q3: 31467.62 | R3: 0 | S3: 0 | T3: 31467.62 | U3: MXN | V3: =T3/17.9075 -> 1757.2313 | W3: VARIAS | X3: JE_CHN | Y3: CHN | Z3: ZAC | AA3: JEG | AB3: M19 | AC3: I | AD3: AIR IMPO | AE3: 67130000 | AF3: NO COMMENTS | AI3: 01 | AJ3: NO | AK3: 0 | AL3: NO
A4: 01 | B4: MXG | C4: 3 | D4: DHL EXPRESS MEXICO, S.A. DE C.V. | E4: Freight | F4: =E4&G4 -> FreightRM-I-0970-AI25-M19 | G4: RM-I-0970-AI25-M19 | H4: ZCLIR00829111 | I4: ENERO | J4: 46266 | K4: OTRO | L4: VARIAS | M4: AIR IMPO | N4: OTRO | O4: 0 | P4: 0 | Q4: 35461.76 | R4: 1418.47 | S4: 0 | T4: 36880.23 | U4: MXN | V4: =T4/17.9075 -> 2059.4851 | W4: VARIAS | X4: VARIOUS | Y4: VARIOUS | Z4: ZAC | AA4: JEG | AB4: M19 | AC4: I | AD4: AIR IMPO | AE4: 67130000 | AF4: NO COMMENTS | AI4: 01 | AJ4: NO | AK4: 0 | AL4: NO
A5: 01 | B5: MXG | C5: 4 | D5: DHL EXPRESS MEXICO, S.A. DE C.V. | E5: Freight | F5: =E5&G5 -> FreightRM-I-0983-AI25-M19 | G5: RM-I-0983-AI25-M19 | H5: ZCLR006211093 | I5: ENERO | J5: 46054 | K5: OTRO | L5: 6201039272 | M5: AIR IMPO | N5: OTRO | O5: 0 | P5: 0 | Q5: 339.74 | R5: 54.36 | S5: 0 | T5: 394.1 | U5: MXN | V5: =T5/17.9075 -> 22.007539 | W5: VARIAS | X5: VARIOUS | Y5: VARIOUS | Z5: ZAC | AA5: JEG | AB5: M19 | AC5: I | AD5: AIR IMPO | AE5: 67130000 | AF5: NO COMMENTS | AI5: 01 | AJ5: NO | AK5: 0 | AL5: NO
A6: 01 | B6: MXG | C6: 5 | D6: DHL EXPRESS MEXICO, S.A. DE C.V. | E6: Freight | F6: =E6&G6 -> FreightFG-I-0422-AE26-M19 | G6: FG-I-0422-AE26-M19 | H6: ZCLR006221593 | I6: ENERO | J6: 46266 | K6: OTRO | L6: VARIAS | M6: AIR EXPO | N6: OTRO | O6: 0 | P6: 0 | Q6: 519.6 | R6: 83.14 | S6: 0 | T6: 602.74 | U6: MXN | V6: =T6/17.9075 -> 33.658523 | W6: VARIAS | X6: JEG | Y6: ZAC | Z6: VARIOUS | AA6: VARIOUS | AB6: M19 | AC6: O | AD6: AIR EXPO | AE6: 59230000 | AF6: NO COMMENTS | AI6: 01 | AJ6: NO | AK6: 0 | AL6: NO
A7: 01 | B7: MXG | C7: 6 | D7: DICEX S.A DE C.V. | E7: Broker | F7: =E7&G7 -> BrokerRM-M-195-SI25-M19-L-B | G7: RM-M-195-SI25-M19-L-B | H7: ALT81399 | I7: ENERO | J7: 46025 | K7: 25-810-3699-5005731 | L7: 721099314 | M7: IMPO | N7: TCKU7405737 | O7: 0 | P7: 3300.2 | Q7: 2553.99 | R7: 408.64 | S7: 0 | T7: 6262.83 | U7: MXN | V7: =T7/17.9075 -> 349.73224 | W7: 45989 | X7: SACO SHIPPING GMBH | Y7: GERMANY | Z7: MEX | AA7: INTERTEAM, S.A. DE C.V. | AB7: M19 | AC7: I | AD7: SEA IMPO | AE7: 67120000 | AF7: NO COMMENTS | AI7: 01 | AJ7: NO | AK7: 0 | AL7: NO
A8: 01 | B8: MXG | C8: 7 | D8: DICEX S.A DE C.V. | E8: Broker | F8: =E8&G8 -> BrokerRM-I-0934-AI24-M19 | G8: RM-I-0934-AI24-M19 | H8: GDL47609 | I8: ENERO | J8: 46013 | K8: 25-480-3993-5001694 | L8: 886495711575 | M8: AIR IMPO | N8: OTRO | O8: 0 | P8: 3991.85 | Q8: 806.86 | R8: 129.1 | S8: 0 | T8: 4927.81 | U8: MXN | V8: =T8/17.9075 -> 275.18135 | W8: 08-Dec-25 | X8: DICEX SA DE CV | Y8: USA | Z8: ZCL | AA8: JEG | AB8: M19 | AC8: I | AD8: AIR IMPO | AE8: 67130000 | AF8: NO COMMENTS | AI8: 01 | AJ8: NO | AK8: 0 | AL8: NO
A9: 01 | B9: MXG | C9: 8 | D9: DICEX S.A DE C.V. | E9: Broker | F9: =E9&G9 -> BrokerRM-I-0935-AI24-M19 | G9: RM-I-0935-AI24-M19 | H9: GDL47610 | I9: ENERO | J9: 46013 | K9: 25-480-3993-5001695 | L9: 886395798563 | M9: AIR IMPO | N9: OTRO | O9: 0 | P9: 2838.88 | Q9: 809.91 | R9: 129.59 | S9: 0 | T9: 3778.38 | U9: MXN | V9: =T9/17.9075 -> 210.99428 | W9: 03-Dec-25 | X9: DICEX SA DE CV | Y9: USA | Z9: ZCL | AA9: JEG | AB9: M19 | AC9: I | AD9: AIR IMPO | AE9: 67130000 | AF9: NO COMMENTS | AI9: 01 | AJ9: NO | AK9: 0 | AL9: NO
A10: 01 | B10: MXG | C10: 9 | D10: DICEX S.A DE C.V. | E10: Broker | F10: =E10&G10 -> BrokerRM-I-0940-AI24-M19 | G10: RM-I-0940-AI24-M19 | H10: GDL47611 | I10: ENERO | J10: 46013 | K10: 25-480-3993-5001696 | L10: 886778414045 | M10: AIR IMPO | N10: OTRO | O10: 0 | P10: 2763.96 | Q10: 804.86 | R10: 128.78 | S10: 0 | T10: 3697.6 | U10: MXN | V10: =T10/17.9075 -> 206.48332 | W10: 03-Dec-25 | X10: DICEX SA DE CV | Y10: USA | Z10: ZCL | AA10: JEG | AB10: M19 | AC10: I | AD10: AIR IMPO | AE10: 67130000 | AF10: NO COMMENTS | AI10: 01 | AJ10: NO | AK10: 0 | AL10: NO
A11: 01 | B11: MXG | C11: 10 | D11: DICEX S.A DE C.V. | E11: Broker | F11: =E11&G11 -> BrokerRM-I-0945-AI24-M19 | G11: RM-I-0945-AI24-M19 | H11: GDL47612 | I11: ENERO | J11: 46013 | K11: 25-480-3993-5001710 | L11: 886848925377 | M11: AIR IMPO | N11: OTRO | O11: 0 | P11: 2759.73 | Q11: 803 | R11: 128.48 | S11: 0 | T11: 3691.21 | U11: MXN | V11: =T11/17.9075 -> 206.12648 | W11: 03-Dec-25 | X11: DICEX SA DE CV | Y11: USA | Z11: ZCL | AA11: JEG | AB11: M19 | AC11: I | AD11: AIR IMPO | AE11: 67130000 | AF11: NO COMMENTS | AI11: 01 | AJ11: NO | AK11: 0 | AL11: NO
A12: 01 | B12: MXG | C12: 11 | D12: DICEX S.A DE C.V. | E12: Broker | F12: =E12&G12 -> BrokerRM-I-0946-AI24-M19 | G12: RM-I-0946-AI24-M19 | H12: GDL47613 | I12: ENERO | J12: 46013 | K12: 25-480-3993-5001711 | L12: 886695033050 | M12: AIR IMPO | N12: OTRO | O12: 0 | P12: 2759.73 | Q12: 805.18 | R12: 128.83 | S12: 0 | T12: 3693.74 | U12: MXN | V12: =T12/17.9075 -> 206.26776 | W12: 04-Dec-25 | X12: DICEX SA DE CV | Y12: CHN | Z12: ZCL | AA12: JEG | AB12: M19 | AC12: I | AD12: AIR IMPO | AE12: 67130000 | AF12: NO COMMENTS | AI12: 01 | AJ12: NO | AK12: 0 | AL12: NO
A13: 01 | B13: MXG | C13: 12 | D13: DICEX S.A DE C.V. | E13: Broker | F13: =E13&G13 -> BrokerRM-I-0947-AI24-M19 | G13: RM-I-0947-AI24-M19 | H13: GDL47614 | I13: ENERO | J13: 46013 | K13: 25-480-3993-5001712 | L13: 886647776083 | M13: AIR IMPO | N13: OTRO | O13: 0 | P13: 2759.73 | Q13: 805.18 | R13: 128.83 | S13: 0 | T13: 3693.74 | U13: MXN | V13: =T13/17.9075 -> 206.26776 | W13: 05-Dec-25 | X13: DICEX SA DE CV | Y13: USA | Z13: ZCL | AA13: JEG | AB13: M19 | AC13: I | AD13: AIR IMPO | AE13: 67130000 | AF13: NO COMMENTS | AI13: 01 | AJ13: NO | AK13: 0 | AL13: NO
A14: 01 | B14: MXG | C14: 13 | D14: DICEX S.A DE C.V. | E14: Broker | F14: =E14&G14 -> BrokerRM-I-0953-AI24-M19 | G14: RM-I-0953-AI24-M19 | H14: GDL47615 | I14: ENERO | J14: 46013 | K14: 25-480-3993-5001717 | L14: 886937395946 | M14: AIR IMPO | N14: OTRO | O14: 0 | P14: 3181.38 | Q14: 803.34 | R14: 128.53 | S14: 0 | T14: 4113.25 | U14: MXN | V14: =T14/17.9075 -> 229.69426 | W14: 10-Dec-25 | X14: DICEX SA DE CV | Y14: CHN | Z14: ZCL | AA14: JEG | AB14: M19 | AC14: I | AD14: AIR IMPO | AE14: 67130000 | AF14: NO COMMENTS | AI14: 01 | AJ14: NO | AK14: 0 | AL14: NO
A15: 01 | B15: MXG | C15: 14 | D15: DICEX S.A DE C.V. | E15: Broker | F15: =E15&G15 -> BrokerRM-I-0952-AI24-M19 | G15: RM-I-0952-AI24-M19 | H15: GDL47616 | I15: ENERO | J15: 46013 | K15: 25-480-3993-5001718 | L15: 886630817791 | M15: AIR IMPO | N15: OTRO | O15: 0 | P15: 3181.38 | Q15: 805.18 | R15: 128.83 | S15: 0 | T15: 4115.39 | U15: MXN | V15: =T15/17.9075 -> 229.81377 | W15: 10-Dec-25 | X15: DICEX SA DE CV | Y15: CHN | Z15: ZCL | AA15: JEG | AB15: M19 | AC15: I | AD15: AIR IMPO | AE15: 67130000 | AF15: NO COMMENTS | AI15: 01 | AJ15: NO | AK15: 0 | AL15: NO
A16: 01 | B16: MXG | C16: 15 | D16: DICEX S.A DE C.V. | E16: Broker | F16: =E16&G16 -> BrokerRM-I-0960-AI24-M19 | G16: RM-I-0960-AI24-M19 | H16: GDL47617 | I16: ENERO | J16: 46013 | K16: 25-480-3993-5001730 | L16: 886972205991 | M16: AIR IMPO | N16: OTRO | O16: 0 | P16: 3892.34 | Q16: 803.97 | R16: 128.64 | S16: 0 | T16: 4824.95 | U16: MXN | V16: =T16/17.9075 -> 269.43739 | W16: 10-Dec-25 | X16: DICEX SA DE CV | Y16: CHN | Z16: ZCL | AA16: JEG | AB16: M19 | AC16: I | AD16: AIR IMPO | AE16: 67130000 | AF16: NO COMMENTS | AI16: 01 | AJ16: NO | AK16: 0 | AL16: NO
A17: 01 | B17: MXG | C17: 16 | D17: DICEX S.A DE C.V. | E17: Broker | F17: =E17&G17 -> BrokerRM-I-0961-AI24-M19 | G17: RM-I-0961-AI24-M19 | H17: GDL47618 | I17: ENERO | J17: 46013 | K17: 25-480-3993-5001731 | L17: 887018804665 | M17: AIR IMPO | N17: OTRO | O17: 0 | P17: 3892.34 | Q17: 803.97 | R17: 128.64 | S17: 0 | T17: 4824.95 | U17: MXN | V17: =T17/17.9075 -> 269.43739 | W17: 10-Dec-25 | X17: DICEX SA DE CV | Y17: CHN | Z17: ZCL | AA17: JEG | AB17: M19 | AC17: I | AD17: AIR IMPO | AE17: 67130000 | AF17: NO COMMENTS | AI17: 01 | AJ17: NO | AK17: 0 | AL17: NO
A18: 01 | B18: MXG | C18: 17 | D18: DICEX S.A DE C.V. | E18: Broker | F18: =E18&G18 -> BrokerRM-I-0962-AI24-M19 | G18: RM-I-0962-AI24-M19 | H18: GDL47619 | I18: ENERO | J18: 46013 | K18: 25-480-3993-5001732 | L18: 887092934199 | M18: AIR IMPO | N18: OTRO | O18: 0 | P18: 2742.99 | Q18: 797.33 | R18: 127.57 | S18: 0 | T18: 3667.89 | U18: MXN | V18: =T18/17.9075 -> 204.82424 | W18: 10-Dec-25 | X18: DICEX SA DE CV | Y18: CHN | Z18: ZCL | AA18: JEG | AB18: M19 | AC18: I | AD18: AIR IMPO | AE18: 67130000 | AF18: NO COMMENTS | AI18: 01 | AJ18: NO | AK18: 0 | AL18: NO
A19: 01 | B19: MXG | C19: 18 | D19: DICEX S.A DE C.V. | E19: Broker | F19: =E19&G19 -> BrokerFG-A-0382AI25-M19-C8714.D | G19: FG-A-0382AI25-M19-C8714.D | H19: MEX124375 | I19: ENERO | J19: 46014 | K19: 25-85-34165018080 | L19: 2025/11/24-01 | M19: AIR IMPO | N19: OTRO | O19: 0 | P19: 33385.87 | Q19: 1893.24 | R19: 302.92 | S19: 0 | T19: 35582.03 | U19: MXN | V19: =T19/17.9075 -> 1986.9904 | W19: 46014 | X19: JOHNSON ELECTRIC INDUSTRIAL MANUFACTORY LIMITED | Y19: USA | Z19: ZAC | AA19: JEG | AB19: M19 | AC19: I | AD19: AIR IMPO | AE19: 67180000 | AF19: NO COMMENTS | AI19: 01 | AJ19: NO | AK19: 0 | AL19: NO | AM19: CS000008714
A20: 01 | B20: MXG | C20: 19 | D20: DICEX S.A DE C.V. | E20: Broker | F20: =E20&G20 -> BrokerRM-M-466-SI25-M19-B | G20: RM-M-466-SI25-M19-B | H20: MZO185520 | I20: ENERO | J20: 46003 | K20: 25 16 1690 5038712 | L20: OOLU2038118971 | M20: IMPO | N20: TLLU7511375 | O20: 0 | P20: 7134 | Q20: 0 | R20: 0 | S20: 0 | T20: 7134 | U20: MXN | V20: =T20/17.9075 -> 398.38057 | W20: 12-Dec-25 | X20: JOHNSON ELECTRIC INDUSTRIAL MANUFACTORY LIMITED | Y20: CHN | Z20: ZCL | AA20: JEG | AB20: M19 | AC20: I | AD20: SEA IMPO | AE20: 67120000 | AF20: COMPLEMENTARIA DE LA CUENTA MZO185283 | AI20: 01 | AJ20: NO | AK20: 0 | AL20: NO
A21: 01 | B21: MXG | C21: 20 | D21: DICEX S.A DE C.V. | E21: Broker | F21: =E21&G21 -> BrokerRM-M-487-SI25-M19-B | G21: RM-M-487-SI25-M19-B | H21: MZO185524 | I21: ENERO | J21: 46003 | K21: 25 16 1690 5042158 | L21: COSU6433823132 | M21: IMPO | N21: OOLU9447086 | O21: 0 | P21: 11671.42 | Q21: 3631.63 | R21: 581.07 | S21: 0 | T21: 15884.12 | U21: MXN | V21: =T21/17.9075 -> 887.00935 | W21: 12-Dec-25 | X21: JOHNSON ELECTRIC INDUSTRIAL MANUFACTORY LIMITED | Y21: CHN | Z21: ZCL | AA21: JEG | AB21: M19 | AC21: I | AD21: SEA IMPO | AE21: 67120000 | AF21: NO COMMENTS | AI21: 01 | AJ21: NO | AK21: 0 | AL21: NO
A22: 01 | B22: MXG | C22: 21 | D22: DICEX S.A DE C.V. | E22: Broker | F22: =E22&G22 -> BrokerRM-M-485-SI25-M19-B | G22: RM-M-485-SI25-M19-B | H22: MZO185525 | I22: ENERO | J22: 46003 | K22: 25 16 1690 5042160 | L22: COSU6433823130 | M22: IMPO | N22: TRHU4721473 | O22: 0 | P22: 14542.42 | Q22: 5014.41 | R22: 802.31 | S22: 0 | T22: 20359.14 | U22: MXN | V22: =T22/17.9075 -> 1136.9058 | W22: 12-Dec-25 | X22: JOHNSON ELECTRIC INDUSTRIAL MANUFACTORY LIMITED | Y22: CHN | Z22: ZCL | AA22: JEG | AB22: M19 | AC22: I | AD22: SEA IMPO | AE22: 67120000 | AF22: NO COMMENTS | AI22: 01 | AJ22: NO | AK22: 0 | AL22: NO
A23: 01 | B23: MXG | C23: 22 | D23: DICEX S.A DE C.V. | E23: Broker | F23: =E23&G23 -> BrokerRM-M-489-SI25-M19-B | G23: RM-M-489-SI25-M19-B | H23: MZO185526 | I23: ENERO | J23: 46003 | K23: 25 16 1690 5042102 | L23: MEDURH066769 | M23: IMPO | N23: TCNU2464881 | O23: 0 | P23: 13874.37 | Q23: 6110.48 | R23: 977.68 | S23: 0 | T23: 20962.53 | U23: MXN | V23: =T23/17.9075 -> 1170.6006 | W23: 12-Dec-25 | X23: OHNSON ELECTRIC INDUSTRIAL MANUFACTORY LIMITED | Y23: CHN | Z23: ZCL | AA23: JEG | AB23: M19 | AC23: I | AD23: SEA IMPO | AE23: 67120000 | AF23: NO COMMENTS | AI23: 01 | AJ23: NO | AK23: 0 | AL23: NO
A24: 01 | B24: MXG | C24: 23 | D24: DICEX S.A DE C.V. | E24: Broker | F24: =E24&G24 -> BrokerRM-M-479-SI25-M19-B | G24: RM-M-479-SI25-M19-B | H24: MZO185532 | I24: ENERO | J24: 46003 | K24: 25 16 1690 5038784 | L24: OOLU2038131940 | M24: IMPO | N24: OOCU7349926 | O24: 0 | P24: 23759.85 | Q24: 3169.12 | R24: 507.05 | S24: 0 | T24: 27436.02 | U24: MXN | V24: =T24/17.9075 -> 1532.0966 | W24: 12-Dec-25 | X24: OHNSON ELECTRIC INDUSTRIAL MANUFACTORY LIMITED | Y24: CHN | Z24: ZCL | AA24: JEG | AB24: M19 | AC24: I | AD24: SEA IMPO | AE24: 67120000 | AF24: NO COMMENTS | AI24: 01 | AJ24: NO | AK24: 0 | AL24: NO
A25: 01 | B25: MXG | C25: 24 | D25: DICEX S.A DE C.V. | E25: Broker | F25: =E25&G25 -> BrokerRM-M-480-SI25-M19-B | G25: RM-M-480-SI25-M19-B | H25: MZO185533 | I25: ENERO | J25: 46003 | K25: 25 16 1690 5038783 | L25: OOLU2038131941 | M25: IMPO | N25: OOCU7818659 | O25: 0 | P25: 23165.93 | Q25: 3664.47 | R25: 586.31 | S25: 0 | T25: 27416.71 | U25: MXN | V25: =T25/17.9075 -> 1531.0183 | W25: 12-Dec-25 | X25: JOHNSON ELECTRIC INDUSTRIAL MANUFACTORY LIMITED | Y25: CHN | Z25: ZCL | AA25: JEG | AB25: M19 | AC25: I | AD25: SEA IMPO | AE25: 67120000 | AF25: NO COMMENTS | AI25: 01 | AJ25: NO | AK25: 0 | AL25: NO
A26: 01 | B26: MXG | C26: 25 | D26: DICEX S.A DE C.V. | E26: Broker | F26: =E26&G26 -> BrokerRM-M-492-SI25-M19-B | G26: RM-M-492-SI25-M19-B | H26: MZO185614 | I26: ENERO | J26: 46003 | K26: 25 16 1690 5038773 | L26: OOLU2038157981 | M26: IMPO | N26: TGBU7698706 | O26: 0 | P26: 15672.47 | Q26: 3544.16 | R26: 567.06 | S26: 0 | T26: 19783.69 | U26: MXN | V26: =T26/17.9075 -> 1104.7712 | W26: 12-Dec-25 | X26: JOHNSON ELECTRIC INDUSTRIAL MANUFACTORY LIMITED | Y26: CHN | Z26: ZCL | AA26: JEG | AB26: M19 | AC26: I | AD26: SEA IMPO | AE26: 67120000 | AF26: NO COMMENTS | AI26: 01 | AJ26: NO | AK26: 0 | AL26: NO
A27: 01 | B27: MXG | C27: 26 | D27: DICEX S.A DE C.V. | E27: Broker | F27: =E27&G27 -> BrokerRM-M-491-SI25-M19-B | G27: RM-M-491-SI25-M19-B | H27: MZO185619 | I27: ENERO | J27: 46003 | K27: 25 16 1690 5038774 | L27: OOLU2038157980 | M27: IMPO | N27: OOCU8377500 | O27: 0 | P27: 15375.51 | Q27: 3248.84 | R27: 519.81 | S27: 0 | T27: 19144.16 | U27: MXN | V27: =T27/17.9075 -> 1069.0582 | W27: 12-Dec-25 | X27: JOHNSON ELECTRIC INDUSTRIAL MANUFACTORY LIMITE | Y27: CHN | Z27: ZCL | AA27: JEG | AB27: M19 | AC27: I | AD27: SEA IMPO | AE27: 67120000 | AF27: NO COMMENTS | AI27: 01 | AJ27: NO | AK27: 0 | AL27: NO
A28: 01 | B28: MXG | C28: 27 | D28: DICEX S.A DE C.V. | E28: Broker | F28: =E28&G28 -> BrokerRM-M-478-SI25-M19-B | G28: RM-M-478-SI25-M19-B | H28: MZO185626 | I28: ENERO | J28: 46003 | K28: 25 16 1690 5038780 | L28: OOLU2038131950 | M28: IMPO | N28: FBIU5272988 | O28: 0 | P28: 33390.57 | Q28: 5128.66 | R28: 820.58 | S28: 0 | T28: 39339.81 | U28: MXN | V28: =T28/17.9075 -> 2196.8343 | W28: 12-Dec-25 | X28: JOHNSON ELECTRIC INDUSTRIAL MANUFACTORY LIMITE | Y28: CHN | Z28: ZCL | AA28: JEG | AB28: M19 | AC28: I | AD28: SEA IMPO | AE28: 67120000 | AF28: NO COMMENTS | AI28: 01 | AJ28: NO | AK28: 0 | AL28: NO
A29: 01 | B29: MXG | C29: 28 | D29: DICEX S.A DE C.V. | E29: Broker | F29: =E29&G29 -> BrokerRM-M-488-SI25-M19-B | G29: RM-M-488-SI25-M19-B | H29: MZO185640 | I29: ENERO | J29: 46003 | K29: 25 16 1690 5042157 | L29: COSU6433823133 | M29: IMPO | N29: CSNU7797874 | O29: 0 | P29: 11671.42 | Q29: 6693.5 | R29: 1070.96 | S29: 0 | T29: 19435.88 | U29: MXN | V29: =T29/17.9075 -> 1085.3486 | W29: 12-Dec-25 | X29: JOHNSON ELECTRIC INDUSTRIAL MANUFACTORY LIMITED | Y29: CHN | Z29: ZCL | AA29: JEG | AB29: M19 | AC29: I | AD29: SEA IMPO | AE29: 67120000 | AF29: NO COMMENTS | AI29: 01 | AJ29: NO | AK29: 0 | AL29: NO
A30: 01 | B30: MXG | C30: 29 | D30: DICEX S.A DE C.V. | E30: Broker | F30: =E30&G30 -> BrokerRM-M-490-SI25-M19-B | G30: RM-M-490-SI25-M19-B | H30: MZO185644 | I30: ENERO | J30: 46003 | K30: 25 16 1690 5042156 | L30: OOLU2038174630 | M30: IMPO | N30: CSNU6882837 | O30: 0 | P30: 12430.27 | Q30: 4920.08 | R30: 787.21 | S30: 0 | T30: 18137.56 | U30: MXN | V30: =T30/17.9075 -> 1012.8471 | W30: 12-Dec-25 | X30: JOHNSON ELECTRIC INDUSTRIAL MANUFACTORY LIMITED | Y30: CHN | Z30: ZCL | AA30: JEG | AB30: M19 | AC30: I | AD30: SEA IMPO | AE30: 67120000 | AF30: NO COMMENTS | AI30: 01 | AJ30: NO | AK30: 0 | AL30: NO
A31: 01 | B31: MXG | C31: 30 | D31: DICEX S.A DE C.V. | E31: Broker | F31: =E31&G31 -> BrokerRM-M-488-SI25-M19-B | G31: RM-M-488-SI25-M19-B | H31: MZO185726 | I31: ENERO | J31: 46006 | K31: 25 16 1690 5042161 | L31: COSU6433823133 | M31: IMPO | N31: CSNU7797874 | O31: 0 | P31: 0 | Q31: 1498.91 | R31: 239.83 | S31: 0 | T31: 1738.74 | U31: MXN | V31: =T31/17.9075 -> 97.09563 | W31: 15-Dec-25 | X31: JOHNSON ELECTRIC INDUSTRIAL MANUFACTORY LIMITED | Y31: CHN | Z31: ZCL | AA31: JEG | AB31: M19 | AC31: I | AD31: SEA IMPO | AE31: 67120000 | AF31: NO COMMENTS | AI31: 01 | AJ31: NO | AK31: 0 | AL31: NO
... A52: 01 | B52: MXG | C52: 51 | D52: DICEX S.A DE C.V. | E52: Broker | F52: =E52&G52 -> BrokerRM-M-511-SI25-M19-B | G52: RM-M-511-SI25-M19-B | H52: MZO186262 | I52: ENERO | J52: 46010 | K52: 25 16 1690 5042748 | L52: COSU6435196943 | M52: IMPO | N52: SEGU6880793 | O52: 0 | P52: 11657.02 | Q52: 6368.64 | R52: 1018.98 | S52: 0 | T52: 19044.64 | U52: MXN | V52: =T52/17.9075 -> 1063.5008 | W52: 19-Dec-25 | X52: JOHNSON ELECTRIC INDUSTRIAL MANUFACTORY LIMITED | Y52: CHN | Z52: ZCL | AA52: JEG | AB52: M19 | AC52: I | AD52: SEA IMPO | AE52: 67120000 | AF52: NO COMMENTS | AI52: 01 | AJ52: NO | AK52: 0 | AL52: NO
A53: 01 | B53: MXG | C53: 52 | D53: DICEX S.A DE C.V. | E53: Broker | F53: =E53&G53 -> BrokerRM-M-208-SI25-M19-L-B | G53: RM-M-208-SI25-M19-L-B | H53: MZO186743 | I53: ENERO | J53: 46024 | K53: 25 16 1690 5043460 | L53: COSU6435332521 | M53: IMPO | N53: COSU6435332521 | O53: 0 | P53: 9066.56 | Q53: 2632.1 | R53: 421.13 | S53: 0 | T53: 12119.79 | U53: MXN | V53: =T53/17.9075 -> 676.79966 | W53: 46024 | X53: HONGKONG LIPIN INT'L LIMITED | Y53: CHN | Z53: ZCL | AA53: JEG | AB53: M19 | AC53: I | AD53: SEA IMPO | AE53: 67120000 | AF53: NO COMMENTS | AI53: 01 | AJ53: NO | AK53: 0 | AL53: NO
A54: 01 | B54: MXG | C54: 53 | D54: DICEX S.A DE C.V. | E54: Broker | F54: =E54&G54 -> BrokerRM-M-192-SI25-M19-L-B | G54: RM-M-192-SI25-M19-L-B | H54: MZO186744 | I54: ENERO | J54: 46024 | K54: 25 16 1690 5042735 | L54: HLCUSEL251127440 | M54: IMPO | N54: HLCUSEL251127440 | O54: 0 | P54: 9101.54 | Q54: 2728.27 | R54: 436.52 | S54: 0 | T54: 12266.33 | U54: MXN | V54: =T54/17.9075 -> 684.98283 | W54: 46024 | X54: JOHNSON ELECTRIC PVT LTD | Y54: CHN | Z54: ZCL | AA54: JEG | AB54: M19 | AC54: I | AD54: SEA IMPO | AE54: 67120000 | AF54: NO COMMENTS | AI54: 01 | AJ54: NO | AK54: 0 | AL54: NO
A55: 01 | B55: MXG | C55: 54 | D55: DICEX S.A DE C.V. | E55: Broker | F55: =E55&G55 -> BrokerRM-M-201-SI25-M19-L-B | G55: RM-M-201-SI25-M19-L-B | H55: MZO186746 | I55: ENERO | J55: 46024 | K55: 25 16 1690 5043457 | L55: HLCUSEL251156604 | M55: IMPO | N55: HLCUSEL251156604 | O55: 0 | P55: 7674.56 | Q55: 2696.31 | R55: 431.41 | S55: 0 | T55: 10802.28 | U55: MXN | V55: =T55/17.9075 -> 603.22658 | W55: 46024 | X55: ELNA AMERICA, INC | Y55: CHN | Z55: ZCL | AA55: JEG | AB55: M19 | AC55: I | AD55: SEA IMPO | AE55: 67120000 | AF55: NO COMMENTS | AI55: 01 | AJ55: NO | AK55: 0 | AL55: NO
A56: 01 | B56: MXG | C56: 55 | D56: DICEX S.A DE C.V. | E56: Broker | F56: =E56&G56 -> BrokerRM-M-214-SI25-M19-L-B | G56: RM-M-214-SI25-M19-L-B | H56: MZO186748 | I56: ENERO | J56: 46024 | K56: 25 16 1690 5042751 | L56: 264868494 | M56: IMPO | N56: 264868494 | O56: 0 | P56: 8891.4 | Q56: 2605.07 | R56: 416.81 | S56: 0 | T56: 11913.28 | U56: MXN | V56: =T56/17.9075 -> 665.26763 | W56: 46024 | X56: SHANGHAI KRAH ELECTRONICS CO; LTD | Y56: CHN | Z56: ZCL | AA56: JEG | AB56: M19 | AC56: I | AD56: SEA IMPO | AE56: 67120000 | AF56: NO COMMENTS | AI56: 01 | AJ56: NO | AK56: 0 | AL56: NO
A57: 01 | B57: MXG | C57: 56 | D57: DICEX S.A DE C.V. | E57: Broker | F57: =E57&G57 -> BrokerRM-M-204-SI25-M19-L-B | G57: RM-M-204-SI25-M19-L-B | H57: MZO186749 | I57: ENERO | J57: 46024 | K57: 25 16 1690 5043456 | L57: HLCUSEL251156604 | M57: IMPO | N57: HLCUSEL251156604 | O57: 0 | P57: 7674.56 | Q57: 2599.22 | R57: 415.87 | S57: 0 | T57: 10689.65 | U57: MXN | V57: =T57/17.9075 -> 596.93704 | W57: 46024 | X57: ELNA AMERICA, INC | Y57: CHN | Z57: ZCL | AA57: JEG | AB57: M19 | AC57: I | AD57: SEA IMPO | AE57: 67120000 | AF57: NO COMMENTS | AI57: 01 | AJ57: NO | AK57: 0 | AL57: NO
A58: 01 | B58: MXG | C58: 57 | D58: DICEX S.A DE C.V. | E58: Broker | F58: =E58&G58 -> BrokerRM-M-189-SI25-M19-L-B | G58: RM-M-189-SI25-M19-L-B | H58: MZO186920 | I58: ENERO | J58: 46024 | K58: 25 16 1690 5042734 | L58: HLCUSEL251017563 | M58: IMPO | N58: HLCUSEL251017563 | O58: 0 | P58: 9101.54 | Q58: 2531.77 | R58: 405.08 | S58: 0 | T58: 12038.39 | U58: MXN | V58: =T58/17.9075 -> 672.25408 | W58: 46024 | X58: JOHNSON ELECTRIC PVT LTD | Y58: CHN | Z58: ZCL | AA58: JEG | AB58: M19 | AC58: I | AD58: SEA IMPO | AE58: 67120000 | AF58: NO COMMENTS | AI58: 01 | AJ58: NO | AK58: 0 | AL58: NO
A59: 01 | B59: MXG | C59: 58 | D59: DICEX S.A DE C.V. | E59: Broker | F59: =E59&G59 -> BrokerRM-M-483-SI25-M19-B | G59: RM-M-483-SI25-M19-B | H59: MZO186996 | I59: ENERO | J59: 46024 | K59: 25 16 1690 5038775 | L59: MEDUKH433089 | M59: EXPO | N59: BMOU6550304 | O59: 0 | P59: 0 | Q59: 1990 | R59: 318.4 | S59: 0 | T59: 2308.4 | U59: MXN | V59: =T59/17.9075 -> 128.90688 | W59: 46024 | X59: JOHNSON ELECTRIC INDUSTRIAL MANUFACTORY LIMITED | Y59: CHN | Z59: ZCL | AA59: JEG | AB59: M19 | AC59: I | AD59: SEA IMPO | AE59: 67120000 | AF59: COMPLEMENTARIA DE LA CUENTA MZO184599 | AI59: 01 | AJ59: NO | AK59: 0 | AL59: NO
A60: 01 | B60: MXG | C60: 59 | D60: DICEX S.A DE C.V. | E60: Broker | F60: =E60&G60 -> BrokerRM-M-523-SI25-M19-B | G60: RM-M-523-SI25-M19-B | H60: MZO187006 | I60: ENERO | J60: 46024 | K60: 25 16 1690 5043760 | L60: OOLU2038223200 | M60: IMPO | N60: CSNU6814540 | O60: 0 | P60: 0 | Q60: 2438.4 | R60: 390.14 | S60: 0 | T60: 2828.54 | U60: MXN | V60: =T60/17.9075 -> 157.95281 | W60: 46024 | X60: JOHNSON ELECTRIC INDUSTRIAL MANUFACTORY LIMITE | Y60: CHN | Z60: ZCL | AA60: JEG | AB60: M19 | AC60: I | AD60: SEA IMPO | AE60: 67120000 | AF60: NO COMMENTS | AI60: 01 | AJ60: NO | AK60: 0 | AL60: NO
A61: 01 | B61: MXG | C61: 60 | D61: DICEX S.A DE C.V. | E61: Broker | F61: =E61&G61 -> BrokerRM-M-504-SI25-M19-B | G61: RM-M-504-SI25-M19-B | H61: MZO187018 | I61: ENERO | J61: 46024 | K61: 25 16 1690 5042740 | L61: OOLU2038188200 | M61: IMPO | N61: OOCU7164584 | O61: 0 | P61: 6148 | Q61: 0 | R61: 0 | S61: 0 | T61: 6148 | U61: MXN | V61: =T61/17.9075 -> 343.31984 | W61: 46024 | X61: JOHNSON ELECTRIC INDUSTRIAL MANUFACTORY LIMITE | Y61: CHN | Z61: ZCL | AA61: JEG | AB61: M19 | AC61: I | AD61: SEA IMPO | AE61: 67120000 | AF61: NO COMMENTS | AI61: 01 | AJ61: NO | AK61: 0 | AL61: NO
A62: 01 | B62: MXG | C62: 61 | D62: DICEX S.A DE C.V. | E62: Broker | F62: =E62&G62 -> BrokerRM-M-505-SI25-M19-B | G62: RM-M-505-SI25-M19-B | H62: MZO187205 | I62: ENERO | J62: 46024 | K62: 25 16 1690 5042741 | L62: OOLU2038188201 | M62: IMPO | N62: TXGU4115032 | O62: 0 | P62: 6844 | Q62: 0 | R62: 0 | S62: 0 | T62: 6844 | U62: MXN | V62: =T62/17.9075 -> 382.18623 | W62: 46024 | X62: JOHNSON ELECTRIC INDUSTRIAL MANUFACTORY LIMITED | Y62: CHN | Z62: ZCL | AA62: JEG | AB62: M19 | AC62: I | AD62: SEA IMPO | AE62: 67120000 | AF62: NO COMMENTS | AI62: 01 | AJ62: NO | AK62: 0 | AL62: NO
A63: 01 | B63: MXG | C63: 62 | D63: DICEX S.A DE C.V. | E63: Broker | F63: =E63&G63 -> BrokerRM-M-512-SI25-M19-B | G63: RM-M-512-SI25-M19-B | H63: MZO187238 | I63: ENERO | J63: 46024 | K63: 25 16 1690 5042742 | L63: MEDURH301760 | M63: IMPO | N63: MSCU4979064 | O63: 0 | P63: 14034.57 | Q63: 4453.96 | R63: 712.63 | S63: 0 | T63: 19201.16 | U63: MXN | V63: =T63/17.9075 -> 1072.2412 | W63: 46024 | X63: JOHNSON ELECTRIC INDUSTRIAL MANUFACTORY LIMITED | Y63: CHN | Z63: ZCL | AA63: JEG | AB63: M19 | AC63: I | AD63: SEA IMPO | AE63: 67120000 | AF63: NO COMMENTS | AI63: 01 | AJ63: NO | AK63: 0 | AL63: NO
A64: 01 | B64: MXG | C64: 63 | D64: DICEX S.A DE C.V. | E64: Broker | F64: =E64&G64 -> BrokerRM-M-513-SI25-M19-B | G64: RM-M-513-SI25-M19-B | H64: MZO187240 | I64: ENERO | J64: 46024 | K64: 25 16 1690 5042743 | L64: MEDURH301778 | M64: IMPO | N64: MSDU7952857 | O64: 0 | P64: 14034.57 | Q64: 4453.96 | R64: 712.63 | S64: 0 | T64: 19201.16 | U64: MXN | V64: =T64/17.9075 -> 1072.2412 | W64: 46024 | X64: JOHNSON ELECTRIC INDUSTRIAL MANUFACTORY LIMITED | Y64: CHN | Z64: ZCL | AA64: JEG | AB64: M19 | AC64: I | AD64: SEA IMPO | AE64: 67120000 | AF64: NO COMMENTS | AI64: 01 | AJ64: NO | AK64: 0 | AL64: NO
A65: 01 | B65: MXG | C65: 64 | D65: DICEX S.A DE C.V. | E65: Broker | F65: =E65&G65 -> BrokerRM-M-524-SI25-M19-B | G65: RM-M-524-SI25-M19-B | H65: MZO187326 | I65: ENERO | J65: 46025 | K65: 25 16 1690 5043466 | L65: MEDURH398261 | M65: IMPO | N65: MSMU4917490 | O65: 0 | P65: 14034.57 | Q65: 5439.18 | R65: 870.26 | S65: 0 | T65: 20344.01 | U65: MXN | V65: =T65/17.9075 -> 1136.0609 | W65: 46025 | X65: JOHNSON ELECTRIC INDUSTRIAL MANUFACTORY LIMITED | Y65: CHN | Z65: ZCL | AA65: JEG | AB65: M19 | AC65: I | AD65: SEA IMPO | AE65: 67120000 | AF65: NO COMMENTS | AI65: 01 | AJ65: NO | AK65: 0 | AL65: NO
A66: 01 | B66: MXG | C66: 65 | D66: DICEX S.A DE C.V. | E66: Broker | F66: =E66&G66 -> BrokerFG-R-2069LR25.M19//FG-R-2068LR25.M19//FG-R-2067LR25.M01 | G66: FG-R-2069LR25.M19//FG-R-2068LR25.M19//FG-R-2067LR25.M01 | H66: NL239198 | I66: ENERO | J66: 46008 | K66: 5085044 | L66: OTRO | M66: LAND EXPO | N66: OTRO | O66: 0 | P66: 0 | Q66: 16959.34 | R66: 2713.49 | S66: 0 | T66: 19672.83 | U66: MXN | V66: =T66/17.9075 -> 1098.5805 | W66: VARIAS | X66: JEG | Y66: ZAC | Z66: USA | AA66: JENA | AB66: M19 | AC66: O | AD66: LAND EXPO | AE66: 59210003 | AF66: NO COMMENTS | AI66: 01 | AJ66: NO | AK66: 0 | AL66: NO
A67: 01 | B67: MXG | C67: 66 | D67: DICEX S.A DE C.V. | E67: Broker | F67: =E67&G67 -> BrokerFG-R-2075LE25.M01//FG-R-2076LE25.M19//FG-R-2078LE25.M19 | G67: FG-R-2075LE25.M01//FG-R-2076LE25.M19//FG-R-2078LE25.M19 | H67: NL239399 | I67: ENERO | J67: 46010 | K67: 5085885 | L67: OTRO | M67: LAND EXPO | N67: OTRO | O67: 0 | P67: 0 | Q67: 10611.44 | R67: 1697.83 | S67: 0 | T67: 12309.27 | U67: MXN | V67: =T67/17.9075 -> 687.38071 | W67: VARIAS | X67: JEG | Y67: ZAC | Z67: USA | AA67: JENA | AB67: M01 | AC67: O | AD67: LAND EXPO | AE67: 59210003 | AF67: NO COMMENTS | AI67: 01 | AJ67: NO | AK67: 0 | AL67: NO
A68: 01 | B68: MXG | C68: 67 | D68: Europartners Mexico, S.A. DE C.V. | E68: Freight | F68: =E68&G68 -> FreightRM-J-1093LI25-M19 | G68: RM-J-1093LI25-M19 | H68: 618994 | I68: ENERO | J68: 46024 | L68: OTRO | M68: LAND IMPO | N68: OTRO | O68: 0 | P68: 0 | Q68: 420 | R68: 0 | S68: 0 | T68: 420 | U68: USD | V68: =T68 -> 420 | W68: 45997 | X68: COMPAL USA // 1 Technology Way Logansport Indiana 46947 United States | Y68: COMPAL USA //. United States | Z68: TDS. United States | AA68: TDS 14213 Transportation Avenue Laredo Texas 78045 United States | AB68: M19 | AC68: I | AD68: LAND IMPO | AE68: 67110002 | AF68: NO COMMENTS | AI68: 01 | AJ68: NO | AK68: 0 | AL68: NO
A69: 01 | B69: MXG | C69: 68 | D69: Europartners Mexico, S.A. DE C.V. | E69: Freight | F69: =E69&G69 -> FreightRM-J-1096LI25-M19.1 | G69: RM-J-1096LI25-M19.1 | H69: 618995 | I69: ENERO | J69: 46024 | L69: OTRO | M69: LAND IMPO | N69: OTRO | O69: 0 | P69: 0 | Q69: 320 | R69: 0 | S69: 0 | T69: 320 | U69: USD | V69: =T69 -> 320 | W69: 45997 | X69: T&C STAMPING // 1403 Freeman Avenue Athens Alabama 35613 United States | Y69: T&C Stamping. United States | Z69: TDS. United States | AA69: TDS 14213 Transportation Avenue Laredo Texas 78045 United States | AB69: M19 | AC69: I | AD69: LAND IMPO | AE69: 67110002 | AF69: NO COMMENTS | AI69: 01 | AJ69: NO | AK69: 0 | AL69: NO
A70: 01 | B70: MXG | C70: 69 | D70: Europartners Mexico, S.A. DE C.V. | E70: Freight | F70: =E70&G70 -> FreightRM-M-203-SI25-M19-L | G70: RM-M-203-SI25-M19-L | H70: 618997 | I70: ENERO | J70: 46024 | L70: OTRO | M70: SEA IMPO | N70: OTRO | O70: 0 | P70: 0 | Q70: 644 | R70: 0 | S70: 0 | T70: 644 | U70: MXN | V70: =T70/17.9075 -> 35.962586 | W70: 45993 | X70: EJOT SE & CO. KG // Herrenwiese 8 Bad Berleburg Ratingen 57319 Germany XEXX010101000 | Y70: Hamburg Port. Germany | Z70: Altamira Port. Mexico | AA70: JOHNSON ELECTRIC GROUP DE MEXICO Boulevard Morelos No. 1109 Mega Parque Industrial Aeropuerto de Calera Calera Zacatecas 98519 Mexico JEG120120DD4 | AB70: M19 | AC70: I | AD70: SEA IMPO | AE70: 67120000 | AF70: NO COMMENTS | AI70: 01 | AJ70: NO | AK70: 0 | AL70: NO
A71: 01 | B71: MXG | C71: 70 | D71: Europartners Mexico, S.A. DE C.V. | E71: Freight | F71: =E71&G71 -> FreightRM-M-202-SI25-M19-L | G71: RM-M-202-SI25-M19-L | H71: 618998 | I71: ENERO | J71: 46024 | L71: OTRO | M71: SEA IMPO | N71: OTRO | O71: 0 | P71: 0 | Q71: 922.4 | R71: 0 | S71: 0 | T71: 922.4 | U71: USD | V71: =T71 -> 922.4 | W71: 45986 | X71: EJOT SE & CO. KG // Herrenwiese 8 Bad Berleburg Ratingen 57319 Germany XEXX010101000 | Y71: Hamburg Port. Germany | Z71: Altamira Port. Mexico | AA71: JOHNSON ELECTRIC GROUP DE MEXICO Boulevard Morelos No. 1109 Mega Parque Industrial Aeropuerto de Calera Calera Zacatecas 98519 Mexico JEG120120DD4 | AB71: M19 | AC71: I | AD71: SEA IMPO | AE71: 67120000 | AF71: NO COMMENTS | AI71: 01 | AJ71: NO | AK71: 0 | AL71: NO
A72: 01 | B72: MXG | C72: 71 | D72: Europartners Mexico, S.A. DE C.V. | E72: Freight | F72: =E72&G72 -> FreightRM-J-1097LI25-M19 | G72: RM-J-1097LI25-M19 | H72: 619025 | I72: ENERO | J72: 46024 | L72: OTRO | M72: LAND IMPO | N72: OTRO | O72: 0 | P72: 0 | Q72: 420 | R72: 0 | S72: 0 | T72: 420 | U72: USD | V72: =T72 -> 420 | W72: 45998 | X72: AUTOMATION SYSTEMS LLC 2001 North 17th Avenue Melrose Park Illinois 60160 United States | Y72: AUTOMATION SYSTEMS LLC. United States | Z72: TDS. United States | AA72: TDS 14213 Transportation Avenue Laredo Texas 78045 United States | AB72: M19 | AC72: I | AD72: LAND IMPO | AE72: 67110002 | AF72: NO COMMENTS | AI72: 01 | AJ72: NO | AK72: 0 | AL72: NO
A73: 01 | B73: MXG | C73: 72 | D73: Europartners Mexico, S.A. DE C.V. | E73: Freight | F73: =E73&G73 -> FreightRM-J-1088LI25-M19 | G73: RM-J-1088LI25-M19 | H73: 619082 | I73: ENERO | J73: 46026 | L73: OTRO | M73: LAND IMPO | N73: OTRO | O73: 0 | P73: 0 | Q73: 420 | R73: 0 | S73: 0 | T73: 420 | U73: USD | V73: =T73 -> 420 | W73: 45997 | X73: NAGASE CHEMTEX AMERICA 100 Innovation Court Delaware Ohio 43015 United States | Y73: NAGASE CHEMTEX AMERICA. United States | Z73: TDS. United States | AA73: TDS 14213 Transportation Avenue Laredo Texas 78045 United States | AB73: M19 | AC73: I | AD73: LAND IMPO | AE73: 67110002 | AF73: NO COMMENTS | AI73: 01 | AJ73: NO | AK73: 0 | AL73: NO
A74: 01 | B74: MXG | C74: 73 | D74: Europartners Mexico, S.A. DE C.V. | E74: Freight | F74: =E74&G74 -> FreightRM-M-206-SI25-M19-L | G74: RM-M-206-SI25-M19-L | H74: 619180 | I74: ENERO | J74: 46027 | L74: OTRO | M74: SEA IMPO | N74: OTRO | O74: 0 | P74: 0 | Q74: 642.4 | R74: 0 | S74: 0 | T74: 642.4 | U74: USD | V74: =T74 -> 642.4 | W74: 46001 | X74: EJOT SE & CO. KG // Herrenwiese 8 Bad Berleburg Ratingen 57319 Germany XEXX010101000 | Y74: Hamburg Port. Germany | Z74: Altamira Port. Mexico | AA74: JOHNSON ELECTRIC GROUP DE MEXICO Boulevard Morelos No. 1109 Mega Parque Industrial Aeropuerto de Calera Calera Zacatecas 98519 Mexico JEG120120DD4 | AB74: M19 | AC74: I | AD74: SEA IMPO | AE74: 67120000 | AF74: NO COMMENTS | AI74: 01 | AJ74: NO | AK74: 0 | AL74: NO
A75: 01 | B75: MXG | C75: 74 | D75: Europartners Mexico, S.A. DE C.V. | E75: Freight | F75: =E75&G75 -> FreightRM-M-208-SI25-M19-L | G75: RM-M-208-SI25-M19-L | H75: 619181 | I75: ENERO | J75: 46027 | L75: OTRO | M75: SEA IMPO | N75: OTRO | O75: 0 | P75: 0 | Q75: 692.4 | R75: 0 | S75: 0 | T75: 692.4 | U75: USD | V75: =T75 -> 692.4 | W75: 46006 | X75: HONGKONG LIPIN INT&aposL LIMITED // ROOM 1613. 16F. TAIYAU BUILDING. 181 JOHNSTON HONG KONG Wan Chai 999077 Hong Kong XEXX010101000 | Y75: Hong Kong Port. Hong Kong | Z75: Manzanillo (MX) Port. Mexico | AA75: JOHNSON ELECTRIC GROUP DE MEXICO Boulevard Morelos No. 1109 Mega Parque Industrial Aeropuerto de Calera Calera Zacatecas 98519 Mexico JEG120120DD4 | AB75: M19 | AC75: I | AD75: SEA IMPO | AE75: 67120000 | AF75: NO COMMENTS | AI75: 01 | AJ75: NO | AK75: 0 | AL75: NO
A76: 01 | B76: MXG | C76: 75 | D76: Europartners Mexico, S.A. DE C.V. | E76: Freight | F76: =E76&G76 -> FreightRM-M-213-SI25-M19-L | G76: RM-M-213-SI25-M19-L | H76: 619182 | I76: ENERO | J76: 46027 | L76: OTRO | M76: SEA IMPO | N76: OTRO | O76: 0 | P76: 0 | Q76: 742.4 | R76: 0 | S76: 0 | T76: 742.4 | U76: USD | V76: =T76 -> 742.4 | W76: 46001 | X76: EJOT SE & CO. KG // Herrenwiese 8 Bad Berleburg Ratingen 57319 Germany XEXX010101000 | Y76: Hamburg Port. Germany | Z76: Altamira Port. Mexico | AA76: JOHNSON ELECTRIC GROUP MEXICO // Boulevard Morelos 1109. Mega Parque Industrial Aeropuerto de Calera Calera Zacatecas 98519 Mexico JEG120120DD4 | AB76: M19 | AC76: I | AD76: SEA IMPO | AE76: 67120000 | AF76: NO COMMENTS | AI76: 01 | AJ76: NO | AK76: 0 | AL76: NO
A77: 01 | B77: MXG | C77: 76 | D77: Europartners Mexico, S.A. DE C.V. | E77: Freight | F77: =E77&G77 -> FreightRM-J-1099LI25-M19 | G77: RM-J-1099LI25-M19 | H77: 619204 | I77: ENERO | J77: 46027 | L77: OTRO | M77: LAND IMPO | N77: OTRO | O77: 0 | P77: 0 | Q77: 450 | R77: 0 | S77: 0 | T77: 450 | U77: USD | V77: =T77 -> 450 | W77: 46000 | X77: ALKEGEN FULTON // 2885 State Route 481. Fulton. NY 13069 Fulton New York 13069 United States | Y77: Alkegen FULTON //. United States | Z77: TDS. United States | AA77: TDS 14213 Transportation Avenue Laredo Texas 78045 United States | AB77: M19 | AC77: I | AD77: LAND IMPO | AE77: 67110002 | AF77: NO COMMENTS | AI77: 01 | AJ77: NO | AK77: 0 | AL77: NO
A78: 01 | B78: MXG | C78: 77 | D78: Europartners Mexico, S.A. DE C.V. | E78: Freight | F78: =E78&G78 -> FreightRM-J-1102LI25-M19 | G78: RM-J-1102LI25-M19 | H78: 619205 | I78: ENERO | J78: 46027 | L78: OTRO | M78: LAND IMPO | N78: OTRO | O78: 0 | P78: 0 | Q78: 580 | R78: 0 | S78: 0 | T78: 580 | U78: USD | V78: =T78 -> 580 | W78: 46000 | X78: COMPAL USA // 1 Technology Way Logansport Indiana 46947 United States | Y78: COMPAL USA //. United States | Z78: TDS. United States | AA78: TDS 14213 Transportation Avenue Laredo Texas 78045 United States | AB78: M19 | AC78: I | AD78: LAND IMPO | AE78: 67110002 | AF78: NO COMMENTS | AI78: 01 | AJ78: NO | AK78: 0 | AL78: NO
A79: 01 | B79: MXG | C79: 78 | D79: Europartners Mexico, S.A. DE C.V. | E79: Freight | F79: =E79&G79 -> FreightRM-J-1103LI25-M19 | G79: RM-J-1103LI25-M19 | H79: 619206 | I79: ENERO | J79: 46027 | L79: OTRO | M79: LAND IMPO | N79: OTRO | O79: 0 | P79: 0 | Q79: 330 | R79: 0 | S79: 0 | T79: 330 | U79: USD | V79: =T79 -> 330 | W79: 46006 | X79: ULTRACHEM INC 900 Centerpoint Boulevard New Castle Delaware 19720 United States | Y79: Ultrachem Inc. United States | Z79: TDS. United States | AA79: TDS 14213 Transportation Avenue Laredo Texas 78045 United States | AB79: M19 | AC79: I | AD79: LAND IMPO | AE79: 67110002 | AF79: NO COMMENTS | AI79: 01 | AJ79: NO | AK79: 0 | AL79: NO
A80: 01 | B80: MXG | C80: 79 | D80: Europartners Mexico, S.A. DE C.V. | E80: Freight | F80: =E80&G80 -> FreightRM-J-1101LI25-M19 | G80: RM-J-1101LI25-M19 | H80: 619207 | I80: ENERO | J80: 46027 | L80: OTRO | M80: LAND IMPO | N80: OTRO | O80: 0 | P80: 0 | Q80: 400 | R80: 0 | S80: 0 | T80: 400 | U80: USD | V80: =T80 -> 400 | W80: 46003 | X80: NAGASE CHEMTEX AMERICA 100 Innovation Court Delaware Ohio 43015 United States | Y80: NAGASE CHEMTEX AMERICA. United States | Z80: TDS. United States | AA80: TDS 14213 Transportation Avenue Laredo Texas 78045 United States | AB80: M19 | AC80: I | AD80: LAND IMPO | AE80: 67110002 | AF80: NO COMMENTS | AI80: 01 | AJ80: NO | AK80: 0 | AL80: NO
A81: 01 | B81: MXG | C81: 80 | D81: Europartners Mexico, S.A. DE C.V. | E81: Freight | F81: =E81&G81 -> FreightRM-J-1113LI25-M19 | G81: RM-J-1113LI25-M19 | H81: 619238 | I81: ENERO | J81: 46027 | L81: OTRO | M81: LAND IMPO | N81: OTRO | O81: 0 | P81: 0 | Q81: 350 | R81: 0 | S81: 0 | T81: 350 | U81: USD | V81: =T81 -> 350 | W81: 46006 | X81: MARCOLE ENTERPRISES 1108 Oakdale Street Manchester Tennessee 37355 United States | Y81: MARCOLE ENTERPRISES. United States | Z81: TDS. United States | AA81: TDS 14213 Transportation Avenue Laredo Texas 78045 United States | AB81: M19 | AC81: I | AD81: LAND IMPO | AE81: 67110002 | AF81: NO COMMENTS | AI81: 01 | AJ81: NO | AK81: 0 | AL81: NO
A82: 01 | B82: MXG | C82: 81 | D82: Europartners Mexico, S.A. DE C.V. | E82: Freight | F82: =E82&G82 -> FreightRM-M-183-SI25-M19-L | G82: RM-M-183-SI25-M19-L | H82: 619351 | I82: ENERO | J82: 46027 | L82: OTRO | M82: SEA IMPO | N82: OTRO | O82: 0 | P82: 0 | Q82: 1092.4 | R82: 0 | S82: 0 | T82: 1092.4 | U82: USD | V82: =T82 -> 1092.4 | W82: 45968 | X82: JOHNSON ELECTRIC INTERNATIONAL AG // Freiburgstraase 33 Murten jeton shkodra 7681 Suiza shkodra Freiburg / Fribourg 7681 Switzerland | Y82: Antwerpen Port. Belgium | Z82: Altamira Port. Mexico | AA82: JOHNSON ELECTRIC GROUP MEXICO // Boulevard Morelos 1109. Mega Parque Industrial Aeropuerto de Calera Calera Zacatecas 98519 Mexico JEG120120DD4 | AB82: M19 | AC82: I | AD82: SEA IMPO | AE82: 67120000 | AF82: NO COMMENTS | AI82: 01 | AJ82: NO | AK82: 0 | AL82: NO
A83: 01 | B83: MXG | C83: 82 | D83: FEDERAL EXPRESS HOLDINGS MEXICO Y COMPAÑIA, S.N.C. DE C.V. | E83: Freight | F83: =E83&G83 -> FreightPAQUETERIA | G83: PAQUETERIA | H83: 5-464-45045 | I83: ENERO | J83: 46027 | L83: 887382406891 | M83: AIR IMPO | N83: OTRO | O83: 0 | P83: 0 | Q83: 1743.2 | R83: 0 | S83: 0 | T83: 1743.2 | U83: MXN | V83: =T83/17.9075 -> 97.344688 | W83: 23/12/2025 | X83: SAM LEVINE | Y83: USA | Z83: ZAC | AA83: JEG | AB83: M19 | AC83: I | AD83: AIR IMPO | AE83: 67130000 | AF83: NO COMMENTS | AI83: 01 | AJ83: NO | AK83: 0 | AL83: NO
A84: 01 | B84: MXG | C84: 83 | D84: FEDERAL EXPRESS HOLDINGS MEXICO Y COMPAÑIA, S.N.C. DE C.V. | E84: Freight | F84: =E84&G84 -> FreightPAQUETERIA | G84: PAQUETERIA | H84: 5-464-82939 | I84: ENERO | J84: 45992 | L84: VARIAS | M84: AIR IMPO | N84: OTRO | O84: 0 | P84: 0 | Q84: 12457.56 | R84: 0 | S84: 0 | T84: 12457.56 | U84: MXN | V84: =T84/17.9075 -> 695.66159 | W84: VARIAS | X84: VARIOUS | Y84: VARIOUS | Z84: ZAC | AA84: JEG | AB84: M19 | AC84: I | AD84: AIR IMPO | AE84: 67130000 | AF84: NO COMMENTS | AI84: 01 | AJ84: NO | AK84: 0 | AL84: NO
A85: 01 | B85: MXG | C85: 84 | D85: FEDERAL EXPRESS HOLDINGS MEXICO Y COMPAÑIA, S.N.C. DE C.V. | E85: Freight | F85: =E85&G85 -> FreightPAQUETERIA | G85: PAQUETERIA | H85: EXRGDL021530 | I85: ENERO | J85: 46204 | L85: 887264151850 | M85: AIR EXPO | N85: OTRO | O85: 0 | P85: 0 | Q85: 336 | R85: 0 | S85: 0 | T85: 336 | U85: MXN | V85: =T85/17.9075 -> 18.763088 | W85: VARIAS | X85: JEG | Y85: ZAC | Z85: VARIOUS | AA85: VARIOUS | AB85: M19 | AC85: O | AD85: AIR EXPO | AE85: 59230000 | AF85: NO COMMENTS | AI85: 01 | AJ85: NO | AK85: 0 | AL85: NO
A86: 01 | B86: MXG | C86: 85 | D86: FEDERAL EXPRESS HOLDINGS MEXICO Y COMPAÑIA, S.N.C. DE C.V. | E86: Freight | F86: =E86&G86 -> FreightPAQUETERIA | G86: PAQUETERIA | H86: FAGDLE16662 | I86: ENERO | J86: 46235 | L86: 887264151850 | M86: AIR EXPO | N86: OTRO | O86: 0 | P86: 0 | Q86: 1195.75 | R86: 191.32 | S86: 0 | T86: 1387.07 | U86: MXN | V86: =T86/17.9075 -> 77.45749 | W86: VARIAS | X86: JEG | Y86: ZAC | Z86: VARIOUS | AA86: VARIOUS | AB86: M19 | AC86: O | AD86: AIR EXPO | AE86: 59230000 | AF86: NO COMMENTS | AI86: 01 | AJ86: NO | AK86: 0 | AL86: NO
A87: 01 | B87: MXG | C87: 86 | D87: MEMPHIS DISTRIBUTION SERVICES | E87: STORAGE | F87: =E87&G87 -> STORAGEINVENTARIO | G87: INVENTARIO | H87: R02492 | I87: ENERO | J87: 45689 | L87: OTRO | M87: LAND EXPO | N87: OTRO | O87: 0 | P87: 0 | Q87: 146 | R87: 0 | S87: 0 | T87: 146 | U87: USD | V87: =T87 -> 146 | W87: VARIAS | X87: JEG | Y87: ZAC | Z87: USA | AA87: MDS | AB87: M19 | AC87: O | AD87: LAND EXPO | AE87: 75640000 | AF87: NO COMMENTS | AI87: 01 | AJ87: NO | AK87: 0 | AL87: NO
A88: 01 | B88: MXG | C88: 87 | D88: MEMPHIS DISTRIBUTION SERVICES | E88: STORAGE | F88: =E88&G88 -> STORAGEINVENTARIO | G88: INVENTARIO | H88: R02521 | I88: ENERO | J88: 45689 | L88: OTRO | M88: LAND EXPO | N88: OTRO | O88: 0 | P88: 0 | Q88: 36 | R88: 0 | S88: 0 | T88: 36 | U88: USD | V88: =T88 -> 36 | W88: VARIAS | X88: JEG | Y88: ZAC | Z88: USA | AA88: MDS | AB88: M19 | AC88: O | AD88: LAND EXPO | AE88: 75640000 | AF88: NO COMMENTS | AI88: 01 | AJ88: NO | AK88: 0 | AL88: NO
A89: 01 | B89: MXG | C89: 88 | D89: MEMPHIS DISTRIBUTION SERVICES | E89: STORAGE | F89: =E89&G89 -> STORAGEINVENTARIO | G89: INVENTARIO | H89: R02549 | I89: ENERO | J89: 45689 | L89: OTRO | M89: LAND EXPO | N89: OTRO | O89: 0 | P89: 0 | Q89: 120 | R89: 0 | S89: 0 | T89: 120 | U89: USD | V89: =T89 -> 120 | W89: VARIAS | X89: JEG | Y89: ZAC | Z89: USA | AA89: MDS | AB89: M19 | AC89: O | AD89: LAND EXPO | AE89: 75640000 | AF89: NO COMMENTS | AI89: 01 | AJ89: NO | AK89: 0 | AL89: NO
A90: 01 | B90: MXG | C90: 89 | D90: MEMPHIS DISTRIBUTION SERVICES | E90: STORAGE | F90: =E90&G90 -> STORAGEINVENTARIO | G90: INVENTARIO | H90: R02541 | I90: ENERO | J90: 45689 | L90: OTRO | M90: LAND EXPO | N90: OTRO | O90: 0 | P90: 0 | Q90: 60 | R90: 0 | S90: 0 | T90: 60 | U90: USD | V90: =T90 -> 60 | W90: VARIAS | X90: JEG | Y90: ZAC | Z90: USA | AA90: MDS | AB90: M19 | AC90: O | AD90: LAND EXPO | AE90: 75640000 | AF90: NO COMMENTS | AI90: 01 | AJ90: NO | AK90: 0 | AL90: NO
A91: 01 | B91: MXG | C91: 90 | D91: MEMPHIS DISTRIBUTION SERVICES | E91: STORAGE | F91: =E91&G91 -> STORAGEINVENTARIO | G91: INVENTARIO | H91: R02523 | I91: ENERO | J91: 45689 | L91: OTRO | M91: LAND EXPO | N91: OTRO | O91: 0 | P91: 0 | Q91: 432 | R91: 0 | S91: 0 | T91: 432 | U91: USD | V91: =T91 -> 432 | W91: VARIAS | X91: JEG | Y91: ZAC | Z91: USA | AA91: MDS | AB91: M19 | AC91: O | AD91: LAND EXPO | AE91: 75640000 | AF91: NO COMMENTS | AI91: 01 | AJ91: NO | AK91: 0 | AL91: NO
A92: 01 | B92: MXG | C92: 91 | D92: MEMPHIS DISTRIBUTION SERVICES | E92: STORAGE | F92: =E92&G92 -> STORAGEINVENTARIO | G92: INVENTARIO | H92: R02502 | I92: ENERO | J92: 45689 | L92: OTRO | M92: LAND EXPO | N92: OTRO | O92: 0 | P92: 0 | Q92: 108 | R92: 0 | S92: 0 | T92: 108 | U92: USD | V92: =T92 -> 108 | W92: VARIAS | X92: JEG | Y92: ZAC | Z92: USA | AA92: MDS | AB92: M19 | AC92: O | AD92: LAND EXPO | AE92: 75640000 | AF92: NO COMMENTS | AI92: 01 | AJ92: NO | AK92: 0 | AL92: NO
A93: 01 | B93: MXG | C93: 92 | D93: MEMPHIS DISTRIBUTION SERVICES | E93: STORAGE | F93: =E93&G93 -> STORAGEINVENTARIO | G93: INVENTARIO | H93: R02550 | I93: ENERO | J93: 45689 | L93: OTRO | M93: LAND EXPO | N93: OTRO | O93: 0 | P93: 0 | Q93: 84 | R93: 0 | S93: 0 | T93: 84 | U93: USD | V93: =T93 -> 84 | W93: VARIAS | X93: JEG | Y93: ZAC | Z93: USA | AA93: MDS | AB93: M19 | AC93: O | AD93: LAND EXPO | AE93: 75640000 | AF93: NO COMMENTS | AI93: 01 | AJ93: NO | AK93: 0 | AL93: NO
A94: 01 | B94: MXG | C94: 93 | D94: MEMPHIS DISTRIBUTION SERVICES | E94: STORAGE | F94: =E94&G94 -> STORAGEINVENTARIO | G94: INVENTARIO | H94: R02510 | I94: ENERO | J94: 45689 | L94: OTRO | M94: LAND EXPO | N94: OTRO | O94: 0 | P94: 0 | Q94: 120 | R94: 0 | S94: 0 | T94: 120 | U94: USD | V94: =T94 -> 120 | W94: VARIAS | X94: JEG | Y94: ZAC | Z94: USA | AA94: MDS | AB94: M19 | AC94: O | AD94: LAND EXPO | AE94: 75640000 | AF94: NO COMMENTS | AI94: 01 | AJ94: NO | AK94: 0 | AL94: NO
A95: 01 | B95: MXG | C95: 94 | D95: MEMPHIS DISTRIBUTION SERVICES | E95: STORAGE | F95: =E95&G95 -> STORAGEINVENTARIO | G95: INVENTARIO | H95: R02535 | I95: ENERO | J95: 45689 | L95: OTRO | M95: LAND EXPO | N95: OTRO | O95: 0 | P95: 0 | Q95: 72 | R95: 0 | S95: 0 | T95: 72 | U95: USD | V95: =T95 -> 72 | W95: VARIAS | X95: JEG | Y95: ZAC | Z95: USA | AA95: MDS | AB95: M19 | AC95: O | AD95: LAND EXPO | AE95: 75640000 | AF95: NO COMMENTS | AI95: 01 | AJ95: NO | AK95: 0 | AL95: NO
A96: 01 | B96: MXG | C96: 95 | D96: MEMPHIS DISTRIBUTION SERVICES | E96: STORAGE | F96: =E96&G96 -> STORAGEINVENTARIO | G96: INVENTARIO | H96: R02500 | I96: ENERO | J96: 45689 | L96: OTRO | M96: LAND EXPO | N96: OTRO | O96: 0 | P96: 0 | Q96: 132 | R96: 0 | S96: 0 | T96: 132 | U96: USD | V96: =T96 -> 132 | W96: VARIAS | X96: JEG | Y96: ZAC | Z96: USA | AA96: MDS | AB96: M19 | AC96: O | AD96: LAND EXPO | AE96: 75640000 | AF96: NO COMMENTS | AI96: 01 | AJ96: NO | AK96: 0 | AL96: NO
A97: 01 | B97: MXG | C97: 96 | D97: P&P GLOBAL LOGISTICS, LLC. | E97: Freight | F97: =E97&G97 -> FreightFG-R-2064LE25.M19 | G97: FG-R-2064LE25.M19 | H97: 53748 | I97: ENERO | J97: 46024 | K97: 3323-5085044 | L97: OTRO | M97: LAND EXPO | N97: 553902 | O97: 0 | P97: 0 | Q97: 5175 | R97: 0 | S97: 0 | T97: 5175 | U97: USD | V97: =T97 -> 5175 | W97: 45992 | X97: JOHNSON ELECTRIC GROUP MEXICO, S. DE R.L.C.V. | Y97: USA | Z97: USA | AA97: SAIA-BURGESS AUTOMOTIVE ACTUATORS | AB97: M19 | AC97: O | AD97: LAND EXPO | AE97: 59210003 | AF97: NO COMMENTS | AI97: 01 | AJ97: NO | AK97: 0 | AL97: NO
A98: 01 | B98: MXG | C98: 97 | D98: P&P GLOBAL LOGISTICS, LLC. | E98: Freight | F98: =E98&G98 -> FreightFG-R-2065LE25.M19 | G98: FG-R-2065LE25.M19 | H98: 53749 | I98: ENERO | J98: 46024 | K98: 3323-5085044 | L98: OTRO | M98: LAND EXPO | N98: PG27120 | O98: 0 | P98: 0 | Q98: 5645 | R98: 0 | S98: 0 | T98: 5645 | U98: USD | V98: =T98 -> 5645 | W98: 45993 | X98: JOHNSON ELECTRIC GROUP MEXICO, S. DE R.L.C.V. | Y98: USA | Z98: USA | AA98: APX WAREHOUSE | AB98: M19 | AC98: O | AD98: LAND EXPO | AE98: 59210003 | AF98: NO COMMENTS | AI98: 01 | AJ98: NO | AK98: 0 | AL98: NO
A99: 01 | B99: MXG | C99: 98 | D99: P&P GLOBAL LOGISTICS, LLC. | E99: Freight | F99: =E99&G99 -> FreightFG-R-2070LE25.M19 | G99: FG-R-2070LE25.M19 | H99: 53750 | I99: ENERO | J99: 46024 | K99: 3323-5085044 | L99: OTRO | M99: LAND EXPO | N99: 5307955 | O99: 0 | P99: 0 | Q99: 4997 | R99: 0 | S99: 0 | T99: 4997 | U99: USD | V99: =T99 -> 4997 | W99: 45994 | X99: JOHNSON ELECTRIC GROUP MEXICO, S. DE R.L.C.V. | Y99: USA | Z99: USA | AA99: SAIA-BURGESS AUTOMOTIVE ACTUATORS | AB99: M19 | AC99: O | AD99: LAND EXPO | AE99: 59210003 | AF99: NO COMMENTS | AI99: 01 | AJ99: NO | AK99: 0 | AL99: NO
A100: 01 | B100: MXG | C100: 99 | D100: P&P GLOBAL LOGISTICS, LLC. | E100: Freight | F100: =E100&G100 -> FreightFG-R-2066LE25.M19 | G100: FG-R-2066LE25.M19 | H100: 53751 | I100: ENERO | J100: 46024 | K100: 3323-5085044 | L100: OTRO | M100: LAND EXPO | N100: 4WU7990 | O100: 0 | P100: 0 | Q100: 7945 | R100: 0 | S100: 0 | T100: 7945 | U100: USD | V100: =T100 -> 7945 | W100: 45994 | X100: JOHNSON ELECTRIC GROUP MEXICO, S. DE R.L.C.V. | Y100: USA | Z100: USA | AA100: APX WAREHOUSE | AB100: M19 | AC100: O | AD100: LAND EXPO | AE100: 59210003 | AF100: NO COMMENTS | AI100: 01 | AJ100: NO | AK100: 0 | AL100: NO
A101: 01 | B101: MXG | C101: 100 | D101: P&P GLOBAL LOGISTICS, LLC. | E101: Freight | F101: =E101&G101 -> FreightFG-R-2067LE25.M01 | G101: FG-R-2067LE25.M01 | H101: 53752 | I101: ENERO | J101: 46024 | K101: 3323-5085044 | L101: OTRO | M101: LAND EXPO | N101: 553899 | O101: 0 | P101: 0 | Q101: 4345 | R101: 0 | S101: 0 | T101: 4345 | U101: USD | V101: =T101 -> 4345 | W101: 45997 | X101: JOHNSON ELECTRIC GROUP MEXICO, S. DE R.L.C.V. | Y101: USA | Z101: USA | AA101: MEMPHIS DISTRIBUTION SERVICES | AB101: M01 | AC101: O | AD101: LAND EXPO | AE101: 59210003 | AF101: NO COMMENTS | AI101: 01 | AJ101: NO | AK101: 0 | AL101: NO
A102: 01 | B102: MXG | C102: 101 | D102: P&P GLOBAL LOGISTICS, LLC. | E102: Freight | F102: =E102&G102 -> FreightFG-R-2068LE25.M19 | G102: FG-R-2068LE25.M19 | H102: 53753 | I102: ENERO | J102: 46024 | K102: 3323-5085044 | L102: OTRO | M102: LAND EXPO | N102: 5182950 | O102: 0 | P102: 0 | Q102: 8245 | R102: 0 | S102: 0 | T102: 8245 | U102: USD | V102: =T102 -> 8245 | W102: 45997 | X102: JOHNSON ELECTRIC GROUP MEXICO, S. DE R.L.C.V. | Y102: USA | Z102: USA | AA102: APX WAREHOUSE | AB102: M19 | AC102: O | AD102: LAND EXPO | AE102: 59210003 | AF102: NO COMMENTS | AI102: 01 | AJ102: NO | AK102: 0 | AL102: NO
A103: 01 | B103: MXG | C103: 102 | D103: P&P GLOBAL LOGISTICS, LLC. | E103: Freight | F103: =E103&G103 -> FreightFG-R-2069LE25.M19 | G103: FG-R-2069LE25.M19 | H103: 53754 | I103: ENERO | J103: 46024 | K103: 3323-5085044 | L103: OTRO | M103: LAND EXPO | N103: 5182221 | O103: 0 | P103: 0 | Q103: 4997 | R103: 0 | S103: 0 | T103: 4997 | U103: USD | V103: =T103 -> 4997 | W103: 45997 | X103: JOHNSON ELECTRIC GROUP MEXICO, S. DE R.L.C.V. | Y103: USA | Z103: USA | AA103: SAIA-BURGESS AUTOMOTIVE ACTUATORS | AB103: M19 | AC103: O | AD103: LAND EXPO | AE103: 59210003 | AF103: NO COMMENTS | AI103: 01 | AJ103: NO | AK103: 0 | AL103: NO
A104: 01 | B104: MXG | C104: 103 | D104: P&P GLOBAL LOGISTICS, LLC. | E104: Freight | F104: =E104&G104 -> FreightFG-R-2073LE25.M19 | G104: FG-R-2073LE25.M19 | H104: 54034 | I104: ENERO | J104: 46024 | K104: 3323-5085885 | L104: OTRO | M104: LAND EXPO | N104: 553888 | O104: 0 | P104: 0 | Q104: 7650 | R104: 0 | S104: 0 | T104: 7650 | U104: USD | V104: =T104 -> 7650 | W104: 46000 | X104: JOHNSON ELECTRIC GROUP MEXICO, S. DE R.L.C.V. | Y104: USA | Z104: USA | AA104: APX WAREHOUSE | AB104: M19 | AC104: O | AD104: LAND EXPO | AE104: 59210003 | AF104: NO COMMENTS | AI104: 01 | AJ104: NO | AK104: 0 | AL104: NO
A105: 01 | B105: MXG | C105: 104 | D105: P&P GLOBAL LOGISTICS, LLC. | E105: Freight | F105: =E105&G105 -> FreightFG-R-2079LE25.M19 | G105: FG-R-2079LE25.M19 | H105: 54035 | I105: ENERO | J105: 46024 | K105: 3323-5085885 | L105: OTRO | M105: LAND EXPO | N105: 5182314 | O105: 0 | P105: 0 | Q105: 5175 | R105: 0 | S105: 0 | T105: 5175 | U105: USD | V105: =T105 -> 5175 | W105: 46001 | X105: JOHNSON ELECTRIC GROUP MEXICO, S. DE R.L.C.V. | Y105: USA | Z105: USA | AA105: SAIA-BURGESS AUTOMOTIVE ACTUATORS | AB105: M19 | AC105: O | AD105: LAND EXPO | AE105: 59210003 | AF105: NO COMMENTS | AI105: 01 | AJ105: NO | AK105: 0 | AL105: NO
A106: 01 | B106: MXG | C106: 105 | D106: P&P GLOBAL LOGISTICS, LLC. | E106: Freight | F106: =E106&G106 -> FreightFG-R-2078LE25.M19 | G106: FG-R-2078LE25.M19 | H106: 54036 | I106: ENERO | J106: 46024 | K106: 3323-5085885 | L106: OTRO | M106: LAND EXPO | N106: 4WX9866 | O106: 0 | P106: 0 | Q106: 4745 | R106: 0 | S106: 0 | T106: 4745 | U106: USD | V106: =T106 -> 4745 | W106: 46002 | X106: JOHNSON ELECTRIC GROUP MEXICO, S. DE R.L.C.V. | Y106: USA | Z106: USA | AA106: MEMPHIS DISTRIBUTION SERVICES | AB106: M19 | AC106: O | AD106: LAND EXPO | AE106: 59210003 | AF106: NO COMMENTS | AI106: 01 | AJ106: NO | AK106: 0 | AL106: NO
A107: 01 | B107: MXG | C107: 106 | D107: P&P GLOBAL LOGISTICS, LLC. | E107: Freight | F107: =E107&G107 -> FreightFG-R-2075LE25.M01 | G107: FG-R-2075LE25.M01 | H107: 54037 | I107: ENERO | J107: 46024 | K107: 3323-5085885 | L107: OTRO | M107: LAND EXPO | N107: 5182221 | O107: 0 | P107: 0 | Q107: 4345 | R107: 0 | S107: 0 | T107: 4345 | U107: USD | V107: =T107 -> 4345 | W107: 46003 | X107: JOHNSON ELECTRIC GROUP MEXICO, S. DE R.L.C.V. | Y107: USA | Z107: USA | AA107: MEMPHIS DISTRIBUTION SERVICES | AB107: M01 | AC107: O | AD107: LAND EXPO | AE107: 59210003 | AF107: NO COMMENTS | AI107: 01 | AJ107: NO | AK107: 0 | AL107: NO
A108: 01 | B108: MXG | C108: 107 | D108: P&P GLOBAL LOGISTICS, LLC. | E108: Freight | F108: =E108&G108 -> FreightFG-R-2076LE25.M19 | G108: FG-R-2076LE25.M19 | H108: 54038 | I108: ENERO | J108: 46024 | K108: 3323-5085885 | L108: OTRO | M108: LAND EXPO | N108: 548054 | O108: 0 | P108: 0 | Q108: 5825 | R108: 0 | S108: 0 | T108: 5825 | U108: USD | V108: =T108 -> 5825 | W108: 46003 | X108: JOHNSON ELECTRIC GROUP MEXICO, S. DE R.L.C.V. | Y108: USA | Z108: USA | AA108: APX WAREHOUSE | AB108: M19 | AC108: O | AD108: LAND EXPO | AE108: 59210003 | AF108: NO COMMENTS | AI108: 01 | AJ108: NO | AK108: 0 | AL108: NO
A109: 01 | B109: MXG | C109: 108 | D109: P&P GLOBAL LOGISTICS, LLC. | E109: Freight | F109: =E109&G109 -> FreightFG-R-2077LE25.M19 | G109: FG-R-2077LE25.M19 | H109: 54039 | I109: ENERO | J109: 46024 | K109: 3323-5085885 | L109: OTRO | M109: LAND EXPO | N109: 4WU7961 | O109: 0 | P109: 0 | Q109: 4997 | R109: 0 | S109: 0 | T109: 4997 | U109: USD | V109: =T109 -> 4997 | W109: 46004 | X109: JOHNSON ELECTRIC GROUP MEXICO, S. DE R.L.C.V. | Y109: USA | Z109: USA | AA109: SAIA-BURGESS AUTOMOTIVE ACTUATORS | AB109: M19 | AC109: O | AD109: LAND EXPO | AE109: 59210003 | AF109: NO COMMENTS | AI109: 01 | AJ109: NO | AK109: 0 | AL109: NO
A110: 01 | B110: MXG | C110: 109 | D110: P&P GLOBAL LOGISTICS, LLC. | E110: Freight | F110: =E110&G110 -> FreightRM-J-1111LI25-M19 | G110: RM-J-1111LI25-M19 | H110: 54061 | I110: ENERO | J110: 46024 | K110: 3323-5085885 | L110: OTRO | M110: LOCAL MOV | N110: OTRO | O110: 0 | P110: 0 | Q110: 150 | R110: 0 | S110: 0 | T110: 150 | U110: USD | V110: =T110 -> 150 | W110: VARIAS | X110: JOHNSON ELECTRIC GROUP MEXICO, S. DE R.L.C.V. | Y110: USA | Z110: USA | AA110: OTRO | AB110: M19 | AC110: I | AD110: LAND IMPO | AE110: 67110002 | AF110: NO COMMENTS | AI110: 01 | AJ110: NO | AK110: 0 | AL110: NO
A111: 01 | B111: MXG | C111: 110 | D111: P&P GLOBAL LOGISTICS, LLC. | E111: Freight | F111: =E111&G111 -> FreightFG-R-2084LE25.M19 | G111: FG-R-2084LE25.M19 | H111: 54241 | I111: ENERO | J111: 46024 | K111: 3323-5086630 | L111: OTRO | M111: LAND EXPO | N111: 55656 | O111: 0 | P111: 0 | Q111: 4997 | R111: 0 | S111: 0 | T111: 4997 | U111: USD | V111: =T111 -> 4997 | W111: 46006 | X111: JOHNSON ELECTRIC GROUP MEXICO, S. DE R.L.C.V. | Y111: USA | Z111: USA | AA111: SAIA-BURGESS AUTOMOTIVE ACTUATORS | AB111: M19 | AC111: O | AD111: LAND EXPO | AE111: 59210003 | AF111: NO COMMENTS | AI111: 01 | AJ111: NO | AK111: 0 | AL111: NO
A112: 01 | B112: MXG | C112: 111 | D112: P&P GLOBAL LOGISTICS, LLC. | E112: Freight | F112: =E112&G112 -> FreightFG-R-2080LE25.M19 | G112: FG-R-2080LE25.M19 | H112: 54242 | I112: ENERO | J112: 46024 | K112: 3323-5086630 | L112: OTRO | M112: LAND EXPO | N112: 553893 | O112: 0 | P112: 0 | Q112: 5645 | R112: 0 | S112: 0 | T112: 5645 | U112: USD | V112: =T112 -> 5645 | W112: 46008 | X112: JOHNSON ELECTRIC GROUP MEXICO, S. DE R.L.C.V. | Y112: USA | Z112: USA | AA112: APX WAREHOUSE | AB112: M19 | AC112: O | AD112: LAND EXPO | AE112: 59210003 | AF112: NO COMMENTS | AI112: 01 | AJ112: NO | AK112: 0 | AL112: NO
A113: 01 | B113: MXG | C113: 112 | D113: P&P GLOBAL LOGISTICS, LLC. | E113: Freight | F113: =E113&G113 -> FreightFG-R-2081LE25.M19 | G113: FG-R-2081LE25.M19 | H113: 54248 | I113: ENERO | J113: 46024 | K113: 3323-5086630 | L113: OTRO | M113: LAND EXPO | N113: 4WX9857 | O113: 0 | P113: 0 | Q113: 4345 | R113: 0 | S113: 0 | T113: 4345 | U113: USD | V113: =T113 -> 4345 | W113: 46010 | X113: JOHNSON ELECTRIC GROUP MEXICO, S. DE R.L.C.V. | Y113: USA | Z113: USA | AA113: MEMPHIS DISTRIBUTION SERVICES | AB113: M19 | AC113: O | AD113: LAND EXPO | AE113: 59210003 | AF113: NO COMMENTS | AI113: 01 | AJ113: NO | AK113: 0 | AL113: NO
A114: 01 | B114: MXG | C114: 113 | D114: P&P GLOBAL LOGISTICS, LLC. | E114: Freight | F114: =E114&G114 -> FreightFG-R-2082LE25.M19 | G114: FG-R-2082LE25.M19 | H114: 54243 | I114: ENERO | J114: 46024 | K114: 3323-5086630 | L114: OTRO | M114: LAND EXPO | N114: 5184533 | O114: 0 | P114: 0 | Q114: 5895 | R114: 0 | S114: 0 | T114: 5895 | U114: USD | V114: =T114 -> 5895 | W114: 46011 | X114: JOHNSON ELECTRIC GROUP MEXICO, S. DE R.L.C.V. | Y114: USA | Z114: USA | AA114: APX WAREHOUSE | AB114: M19 | AC114: O | AD114: LAND EXPO | AE114: 59210003 | AF114: NO COMMENTS | AI114: 01 | AJ114: NO | AK114: 0 | AL114: NO
A115: 01 | B115: MXG | C115: 114 | D115: P&P GLOBAL LOGISTICS, LLC. | E115: Freight | F115: =E115&G115 -> FreightFG-R-2083LE25.M01 | G115: FG-R-2083LE25.M01 | H115: 54249 | I115: ENERO | J115: 46024 | K115: 3323-5086630 | L115: OTRO | M115: LAND EXPO | N115: 553889 | O115: 0 | P115: 0 | Q115: 4997 | R115: 0 | S115: 0 | T115: 4997 | U115: USD | V115: =T115 -> 4997 | W115: 46011 | X115: JOHNSON ELECTRIC GROUP MEXICO, S. DE R.L.C.V. | Y115: USA | Z115: USA | AA115: SAIA-BURGESS AUTOMOTIVE ACTUATORS | AB115: M01 | AC115: O | AD115: LAND EXPO | AE115: 59210003 | AF115: NO COMMENTS | AI115: 01 | AJ115: NO | AK115: 0 | AL115: NO
A116: 01 | B116: MXG | C116: 115 | D116: P&P GLOBAL LOGISTICS, LLC. | E116: Freight | F116: =E116&G116 -> FreightFG-R-2085LE25.M19 | G116: FG-R-2085LE25.M19 | H116: 54244 | I116: ENERO | J116: 46024 | K116: 3323-5086630 | L116: OTRO | M116: LAND EXPO | N116: 4WX9857 | O116: 0 | P116: 0 | Q116: 6125 | R116: 0 | S116: 0 | T116: 6125 | U116: USD | V116: =T116 -> 6125 | W116: 46011 | X116: JOHNSON ELECTRIC GROUP MEXICO, S. DE R.L.C.V. | Y116: USA | Z116: USA | AA116: SAIA-BURGESS AUTOMOTIVE ACTUATORS | AB116: M19 | AC116: O | AD116: LAND EXPO | AE116: 59210003 | AF116: NO COMMENTS | AI116: 01 | AJ116: NO | AK116: 0 | AL116: NO
A117: 01 | B117: MXG | C117: 116 | D117: P&P GLOBAL LOGISTICS, LLC. | E117: Freight | F117: =E117&G117 -> FreightFG-R-2086LE25.M19 | G117: FG-R-2086LE25.M19 | H117: 54442 | I117: ENERO | J117: 46024 | K117: 3323-5087389 | L117: OTRO | M117: LAND EXPO | N117: 5182941 | O117: 0 | P117: 0 | Q117: 5425 | R117: 0 | S117: 0 | T117: 5425 | U117: USD | V117: =T117 -> 5425 | W117: 46014 | X117: JOHNSON ELECTRIC GROUP MEXICO, S. DE R.L.C.V. | Y117: USA | Z117: USA | AA117: APX WAREHOUSE | AB117: M19 | AC117: O | AD117: LAND EXPO | AE117: 59210003 | AF117: NO COMMENTS | AI117: 01 | AJ117: NO | AK117: 0 | AL117: NO
A118: 01 | B118: MXG | C118: 117 | D118: P&P GLOBAL LOGISTICS, LLC. | E118: Freight | F118: =E118&G118 -> FreightFG-R-2087LE25.M19 | G118: FG-R-2087LE25.M19 | H118: 54443 | I118: ENERO | J118: 46024 | K118: 3323-5087389 | L118: OTRO | M118: LAND EXPO | N118: 4WU8002 | O118: 0 | P118: 0 | Q118: 5495 | R118: 0 | S118: 0 | T118: 5495 | U118: USD | V118: =T118 -> 5495 | W118: 46017 | X118: JOHNSON ELECTRIC GROUP MEXICO, S. DE R.L.C.V. | Y118: USA | Z118: USA | AA118: APX WAREHOUSE | AB118: M19 | AC118: O | AD118: LAND EXPO | AE118: 59210003 | AF118: NO COMMENTS | AI118: 01 | AJ118: NO | AK118: 0 | AL118: NO
A119: 01 | B119: MXG | C119: 118 | D119: TRANSCONTINENTAL DIST. SERVICES | E119: STORAGE | F119: =E119&G119 -> STORAGERM-J-1069LI25-M19.1 | G119: RM-J-1069LI25-M19.1 | H119: 145454 | I119: ENERO | J119: 45659 | K119: 240-3483-5035800 | L119: 12 GUIAS | M119: LAND IMPO | N119: CAJA: CB-072 | O119: 0 | P119: 0 | Q119: 420.75 | R119: 0 | S119: 0 | T119: 420.75 | U119: USD | V119: =T119 -> 420.75 | W119: 45975 | X119: DICEX | Y119: LDO | Z119: ZCL | AA119: JOHNSON MX | AB119: M19 | AC119: I | AD119: LAND IMPO | AE119: 67115005 | AF119: NO COMMENTS | AI119: 01 | AJ119: NO | AK119: 0 | AL119: NO
A120: 01 | B120: MXG | C120: 119 | D120: TRANSCONTINENTAL DIST. SERVICES | E120: STORAGE | F120: =E120&G120 -> STORAGEFG-R-2033LE25.M19 | G120: FG-R-2033LE25.M19 | H120: 145455 | I120: ENERO | J120: 45659 | L120: 487248 | M120: LAND IMPO | N120: OTRO | O120: 0 | P120: 0 | Q120: 29.7 | R120: 0 | S120: 0 | T120: 29.7 | U120: USD | V120: =T120 -> 29.7 | W120: VARIAS | X120: LDO | Y120: LDO | Z120: ZCL | AA120: JOHNSON MX | AB120: M19 | AC120: O | AD120: LAND EXPO | AE120: 75640000 | AF120: NO COMMENTS | AI120: 01 | AJ120: NO | AK120: 0 | AL120: NO
...

Sheet HT
A1: FG-R-2069LR25.M19 | B1: NL239198 | O1: FECHA FACTURA | P1: FOLIO FACTURA | Q1: TRANSPORT ORDER | R1: FECHA VENCIMIENTO | S1: MONEDA | T1: DIAS DE VENCIMIENTO | U1: IMPORTE | V1: ESTATUS FACT | W1: REFERENCIA
A2: FG-R-2068LR25.M19 | B2: NL239198 | O2: 45811 | P2: 542336 | Q2: XPD/MX/AI/24120046775 | R2: 20/04/2025 | S2: USD | T2: 274 | U2: $ 1,405.60 | V2: VENCIDA | W2: RM-A-0169AI24-M19 | X2: 1405.6 | Y2: 1340
A3: FG-R-2067LR25.M01 | B3: NL239198 | O3: 45811 | P3: 542489 | Q3: LOD1300354 | R3: 20/04/2025 | S3: USD | T3: 274 | U3: $ 575.00 | V3: VENCIDA | W3: RM-R-0239LI24-M19 | X3: 575
A4: FG-R-2075LE25.M01 | B4: NL239399 | O4: 45811 | P4: 542492 | Q4: LOD1333794 | R4: 20/04/2025 | S4: USD | T4: 274 | U4: $ 320.00 | V4: VENCIDA | W4: RM-J-0065LI24-M19 | X4: 320 | Y4: N/E
A5: FG-R-2076LE25.M19 | B5: NL239399 | O5: 45964 | P5: 543444 | Q5: XPD/MX/RI/24120046891 | R5: 25/04/2025 | S5: USD | T5: 269 | U5: $ 924.00 | V5: VENCIDA | W5: RM-J-0275LI24-M19 | X5: 924 | Y5: N/E
A6: FG-R-2078LE25.M19 | B6: NL239399 | O6: 24/03/2025 | P6: 546784 | Q6: EP/AGU/SI/S/2024/013921 | R6: 45874 | S6: USD | T6: 256 | U6: $ 907.20 | V6: VENCIDA | W6: RM-M-017-SI24-M19-L SUSTITUTYE 521607 | X6: 907.2 | Y6: E/D EUR/XPD
A7: RM-A-0003AI26-M19-C9038.D | B7: MEX125301 | O7: 28/03/2025 | P7: 548215 | Q7: XPD/MX/SI/24110030461 | R7: 45996 | S7: USD | T7: 252 | U7: $ 2,701.60 | V7: VENCIDA | W7: RM-M-135-SI24-M19-L | X7: 2701.6 | Y7: DSV
A8: RM-A-0011AI26-M19.PFA.D | B8: MEX125301 | O8: 28/03/2025 | P8: 548218 | Q8: XPD/MX/SI/24090016489 | R8: 45996 | S8: USD | T8: 252 | U8: $ 1,468.40 | V8: VENCIDA | W8: RM-M-111-SI24-M19-L | X8: 1468.4 | Y8: DSV
A9: RM-A-0012AI26-M19.PFA.D | B9: MEX125301 | O9: 31/03/2025 | P9: 548526 | Q9: XPD/MX/SI/24110029932 | R9: 15/05/2025 | S9: USD | T9: 249 | U9: $ 1,168.80 | V9: VENCIDA | W9: RM-M-137-SI24-M19-L | X9: 1168.8 | Y9: E
A10: FG-R-2077LE25.M19 | B10: NL240119 | X10: =SUM(X2:X9) -> 9470.6
A11: FG-R-2084LE25.M19 | B11: NL240119
A12: FG-R-2087LE25.M19 | B12: NL240126
A13: FG-R-2086LE25.M19 | B13: NL240126 | F13: 67110002 | G13: LAND IMPO | H13: 67110002
A14: RM-M-540-SI25-M19 | B14: CAL-3958 | F14: 67115005 | G14: STORAGE | H14: 67115005
A15: RM-M-541-SI25-M19 | B15: CAL-3958 | F15: 67120000 | G15: SEA IMPO | H15: 67120000 | I15: 67110003
A16: RM-M-516-SI25-M19 | B16: CAL-3959 | F16: 67130000 | G16: AIR IMPO | H16: 67130000
A17: RM-M-525-SI25-M19 | B17: CAL-3959 | F17: 67155001 | G17: DUTY | H17: 67155001
A18: RM-M-535-SI25-M19 | B18: CAL-3961 | F18: 67170000 | G18: DUTY | H18: 67170000
A19: RM-M-538-SI25-M19 | B19: CAL-3961 | F19: 67180000 | G19: PREMIUM | H19: 67180000
A20: RM-M-532-SI25-M19 | B20: CAL-3975 | F20: 59210003 | G20: LAND EXPO | H20: 59210003
A21: RM-M-533-SI25-M19 | B21: CAL-3975 | F21: 59220000 | G21: SEA EXPO | H21: 59220000
A22: AF-M-493-SI25-M23 | B22: CAL-3960 | F22: 59230000 | G22: AIR EXPO | H22: 59230000
A23: AF-M-496-SI25-M23 | B23: CAL-3960 | F23: 59234005 | G23: PREMIUM | H23: 59234005
A24: RM-M-491-SI25-M19 | B24: CAL-3970 | F24: 59210002 | G24: LAND EXPO | H24: 59210002
A25: RM-M-492-SI25-M19 | B25: CAL-3970
A26: RM-M-498-SI25-M19 | B26: CAL-3973 | G26: 75640000
A27: RM-M-500-SI25-M19 | B27: CAL-3973 | G27: 67110003
A28: RM-M-505-SI25-M19 | B28: CAL-3977
A29: RM-M-504-SI25-M19 | B29: CAL-3977
A30: RM-M-508-SI25-M19 | B30: CAL-3978
A31: RM-M-510-SI25-M19 | B31: CAL-3978
A32: RM-M-502-SI25-M19 | B32: CAL-3983
A33: RM-M-503-SI25-M19 | B33: CAL-3983
A34: RM-M-526-SI25-M19 | B34: CAL-3988
A35: RM-M-527-SI25-M19 | B35: CAL-3988
A36: RM-M-519-SI25-M19 | B36: CAL-3987
A37: RM-M-520-SI25-M19 | B37: CAL-3987
A38: RM-J1094LI25-M19.1 | B38: A268029
A39: RM-J-1108LI25-M19.2 | B39: A268029
... A88: RM-M-584-SI25-M19 | B88: CAL-4081
A89: RM-A-0019AI26-M19-C9049 | B89: 3358
A90: RM-A-0020AI26-M19-C9049 | B90: 3358
A91: FG-R2117LE25.M19 | B91: NL242496
A92: FG-R2118LE25.M01 | B92: NL242496
A93: FG-R2111LE25.M19 | B93: NL242496
A94: FG-R-2124LE25.M01 | B94: NL242573
A95: FG-R-2125LE25.M19 | B95: NL242573
A96: FG-R-2126LE25.M19 | B96: NL242573
A97: RM-M-011-SI26-M19 | B97: CAL-4094
A98: RM-M-005-SI26-M19 | B98: CAL-4094
A99: MARZO
A100: RM-J-1201LI26-M19 | B100: A270398
A101: RM-J-1211LI26-M19 | B101: A270398
A102: RM-I-1076-AI26-M19 | B102: GDL48144
A103: RM-I-1077-AI26-M19 | B103: GDL48144
A104: RM-A-0023AI26-M19-C9270.D | B104: MEX126896
A105: RM-A-0022AI26-M19-C9338.D | B105: MEX126896
A106: RM-A-0025AI26-M19-C9270.D | B106: MEX126896
A107: RM-M-014-SI26-M19 | B107: CAL-4108
A108: RM-M-010-SI26-M19 | B108: CAL-4108
A109: RM-M-580-SI25-M19 | B109: CAL-4098
A110: RM-M-577-SI25-M19 | B110: CAL-4098
A111: AF-M-059-SI26-M46 | B111: CAL-4112
... A172: RM-M-044-SI26-M19 | B172: CAL.4149
A173: RM-A-0027AI26-M19-C9388 | B173: 3454
A174: RM-A-0028AI26 M19-C9048 | B174: 3454
A175: RM-A-0033AI26-M19-C9505 | B175: 3456
A176: RM-A-0035AI26 M19-C9506 | B176: 3456
A177: AF-A-0030AI26-M19-C9482 | B177: 3456
A178: RM-J-1222LI26-M19 | B178: A271753
A179: RM-J-1230LI26-M19 | B179: A271753
A180: RM-A-0037AI26-M19-C9529.D | B180: MEX128060
A181: RM-A-0041AI26-M19-C9529.D | B181: MEX128060
A182: RM-M-045-SI26-M19 | B182: CAL-4152
A183: RM-M-041-SI26-M19 | B183: CAL-4152
A184: RM-M-076-SI26-M19 | B184: CAL-4150
A185: RM-M-047-SI26-M19 | B185: CAL-4150

Sheet CANCELADAS
A1: MEX125323 | B1: =VLOOKUP(A1,'CONSOLIDADO 2026'!H:H,1,0) -> #N/A
A2: MX-1070 | B2: =VLOOKUP(A2,'CONSOLIDADO 2026'!H:H,1,0) -> #N/A | J2: =J3/17.2988 -> 231.22991 | O2: 17.2988
A3: C7975 | B3: =VLOOKUP(A3,'CONSOLIDADO 2026'!H:H,1,0) -> #N/A | J3: 4000 | K3: 1101.44 | L3: 68.28 | M3: 147.54
A4: CAL-3748 | B4: =VLOOKUP(A4,'CONSOLIDADO 2026'!H:H,1,0) -> #N/A | E4: 540470091 | H4: POSITION | I4: NAME | J4: STANDING DESK | K4: COMPUTER | L4: KEYBOARD & MOUSE | M4: COMPUTER MONITOR
A5: MZO190087 | B5: =VLOOKUP(A5,'CONSOLIDADO 2026'!H:H,1,0) -> #N/A | H5: Compliance lead | I5: Alejandro Ocampo | J5: 1 | K5: 1 | L5: 1 | M5: 1
A6: MZO187863 | B6: =VLOOKUP(A6,'CONSOLIDADO 2026'!H:H,1,0) -> MZO187863 | H6: Compliance analyst | I6: Mayra García | J6: 1 | K6: 1 | L6: 1 | M6: 1
A7: MX-1088 | B7: =VLOOKUP(A7,'CONSOLIDADO 2026'!H:H,1,0) -> #N/A | H7: Compliance analyst | I7: TBD | J7: 1 | K7: 1 | L7: 1 | M7: 1
A8: CAL-4042 | B8: =VLOOKUP(A8,'CONSOLIDADO 2026'!H:H,1,0) -> #N/A | H8: Logistics Analyst | I8: Andrea Reyes | J8: 1 | K8: - | L8: 1 | M8: 1
A9: CAL-4056 | B9: =VLOOKUP(A9,'CONSOLIDADO 2026'!H:H,1,0) -> #N/A | H9: Logistics lead | I9: Magnolia Valle | J9: - | K9: - | L9: - | M9: 1
A10: CAL-4055 | B10: =VLOOKUP(A10,'CONSOLIDADO 2026'!H:H,1,0) -> #N/A | I10: TOTAL | J10: 4 | K10: 3 | L10: 4 | M10: 5
A11: CAL-4051 | B11: =VLOOKUP(A11,'CONSOLIDADO 2026'!H:H,1,0) -> #N/A | I11: TOTAL USD | J11: =J10*J2 -> 924.91965 | K11: =1101.44*3 -> 3304.32 | L11: =68.28*4 -> 273.12 | M11: =147.54*5 -> 737.7 | N11: =J11+K11+L11+M11 -> 5240.0596
A12: CAL-4048 | B12: =VLOOKUP(A12,'CONSOLIDADO 2026'!H:H,1,0) -> #N/A | K12: 21SYS5SW0J | L12: 4X31R64337 | M12: 63DEKAR3LA
A13: CAL-3983 | B13: CAL-4086 | K13: ThinkPad E14 G7, Intel® Core™ Ultra 5 235U vPro® (E-cores up to 4.10GHz, 12MB), 14" WUXGA Non-Touch, W11P64 US/UK_ENG, 32.0GB, 1x512GB SSD M.2 2242 PCIe Gen4 TLC Opal, Intel® Graphics, BT 5.3,Intel®AX211vPro, FPR, 1080PFHD Hybrid, 3 Cell Li-ion 48Wh, 65W, 3YR Premier NBD,1CourierCarryin, CO2 Offset,Keep your Drive, Black-Spanish (LA) | L13: Lenovo Professional Wireless Rechargeable Combo Keyboard and Mouse-LA Spanish | M13: ThinkVision S24i-30 23.8 inch Monitor
A14: CAL-4143
A15: CAL-4059
A16: 4996 | L16: SAGS 33306 | O16: INVOICE | P16: INVOICE | Q16: INVOICE | R16: INVOICE | S16: INVOICE | T16: INVOICE | U16: INVOICE
A17: CAL-4176 | I17: BU | J17: COM | K17: Sum of % | L17: 1266.32 | M17: 100 | N17: BU | O17: SAGS 33306 | P17: SAGS 33321 | Q17: SAGS 33310 | R17: SAGS 33322 | S17: SAGS 33323 | T17: SAGS 33251 | U17: SAGS 33267 | V17: TOTAL/MXN
A18: CAL-4172 | I18: 1 | J18: 2762703.6 | K18: 0.12331747 | L18: =(L17*M18)/M17 -> 156.13726 | M18: 12.33 | N18: 01 | O18: 202.06034 | P18: 202.06034 | Q18: 202.06034 | R18: 202.06034 | S18: 202.06034 | T18: 194.38738 | U18: 194.38738 | V18: =SUM(O18:U18) -> 1399.0765
A19: CAL-4174 | I19: 19 | J19: 14619078 | K19: 0.65254478 | L19: =(L18*M19)/M18 -> 826.2738 | M19: 65.25 | N19: 19 | O19: 1069.2974 | P19: 1069.2974 | Q19: 1069.2974 | R19: 1069.2974 | S19: 1069.2974 | T19: 1028.6924 | U19: 1028.6924 | V19: =SUM(O19:U19) -> 7403.8718
A20: CAL-4158 | I20: 23 | J20: 953212.61 | K20: 0.042548094 | L20: =(L19*M20)/M19 -> 53.8186 | M20: 4.25 | N20: 23 | O20: 69.647725 | P20: 69.647725 | Q20: 69.647725 | R20: 69.647725 | S20: 69.647725 | T20: 67.00295 | U20: 67.00295 | V20: =SUM(O20:U20) -> 482.24452
A21: FACTURA | B21: SEMANA | I21: 46 | J21: 1614005.6 | K21: 0.072043593 | L21: =(L20*M21)/M20 -> 91.301672 | M21: 7.21 | N21: 46 | O21: 118.15532 | P21: 118.15532 | Q21: 118.15532 | R21: 118.15532 | S21: 118.15532 | T21: 113.66853 | U21: 113.66853 | V21: =SUM(O21:U21) -> 818.11365
A22: CAL-4160 | B22: SEM 12 | C22: =VLOOKUP(A22,'CONSOLIDADO 2026'!H:H,1,0) -> CAL-4160 | I22: 61 | J22: 2118438.2 | K22: 0.094559711 | L22: =(L21*M22)/M21 -> 119.79387 | M22: 9.46 | N22: 61 | O22: 155.02764 | P22: 155.02764 | Q22: 155.02764 | R22: 155.02764 | S22: 155.02764 | T22: 149.14068 | U22: 149.14068 | V22: =SUM(O22:U22) -> 1073.4196
A23: CAL-4158 | B23: SEM 12 | C23: =VLOOKUP(A23,'CONSOLIDADO 2026'!H:H,1,0) -> CAL-4158 | I23: 62 | J23: 335741.98 | K23: 0.014986354 | L23: =(L22*M23)/M22 -> 18.9948 | M23: 1.5 | N23: 62 | O23: 24.58155 | P23: 24.58155 | Q23: 24.58155 | R23: 24.58155 | S23: 24.58155 | T23: 23.6481 | U23: 23.6481 | V23: =SUM(O23:U23) -> 170.20395
A24: CAL-4185 | B24: SEM 13 | C24: =VLOOKUP(A24,'CONSOLIDADO 2026'!H:H,1,0) -> CAL-4185 | I24: Grand Total | J24: 22403180 | K24: 1 | L24: =SUM(L18:L23) -> 1266.32 | M24: =SUM(M18:M23) -> 100 | O24: =SUM(O18:O23) -> 1638.77 | P24: =SUM(P18:P23) -> 1638.77 | Q24: =SUM(Q18:Q23) -> 1638.77 | R24: =SUM(R18:R23) -> 1638.77 | S24: =SUM(S18:S23) -> 1638.77 | T24: =SUM(T18:T23) -> 1576.54 | U24: =SUM(U18:U23) -> 1576.54 | V24: =SUM(V18:V23) -> 11346.93
A25: CAL-4169 | C25: =VLOOKUP(A25,'CONSOLIDADO 2026'!H:H,1,0) -> #N/A
A26: CAL-4170 | C26: =VLOOKUP(A26,'CONSOLIDADO 2026'!H:H,1,0) -> #N/A | O26: INVOICE | P26: INVOICE | Q26: INVOICE | R26: INVOICE | S26: INVOICE | T26: INVOICE | U26: INVOICE | V26: INVOICE | W26: INVOICE | X26: INVOICE | Y26: INVOICE | Z26: INVOICE | AA26: INVOICE | AB26: INVOICE | AC26: INVOICE | AD26: INVOICE | AE26: INVOICE | AF26: INVOICE | AG26: INVOICE | AH26: INVOICE
A27: CAL-4171 | C27: =VLOOKUP(A27,'CONSOLIDADO 2026'!H:H,1,0) -> #N/A | N27: BU | O27: SAGS 33614 | P27: SAGS 33605 | Q27: SAGS 33592 | R27: SAGS 33600 | S27: SAGS 33604 | T27: SAGS 33603 | U27: SAGS 33598 | V27: SAGS 33588 | W27: SAGS 33587 | X27: SAGS 33597 | Y27: SAGS 33595 | Z27: SAGS 33591 | AA27: SAGS 33594 | AB27: SAGS 33613 | AC27: SAGS 33606 | AD27: SAGS 33586 | AE27: SAGS 33593 | AF27: SAGS 33590 | AG27: SAGS 33607 | AH27: SAGS 33589 | AI27: TOTAL/MXN
A28: CAL-4172 | C28: =VLOOKUP(A28,'CONSOLIDADO 2026'!H:H,1,0) -> #N/A | N28: 01 | O28: 214.39034 | P28: 214.39034 | Q28: 276.04034 | R28: 276.04034 | S28: 276.04034 | T28: 265.84713 | U28: 276.04034 | V28: 214.39034 | W28: 276.04034 | X28: 276.04034 | Y28: 276.04034 | Z28: 276.04034 | AA28: 276.04034 | AB28: 276.04034 | AC28: 276.04034 | AD28: 276.04034 | AE28: 276.04034 | AF28: 276.04034 | AG28: 2959.2 | AH28: 276.04034 | AI28: =SUM(O28:AH28) -> 8008.8233
A29: CAL-4174 | C29: =VLOOKUP(A29,'CONSOLIDADO 2026'!H:H,1,0) -> #N/A | N29: 19 | O29: 1134.5474 | P29: 1134.5474 | Q29: 1460.7974 | R29: 1460.7974 | S29: 1460.7974 | T29: 1406.8553 | U29: 1460.7974 | V29: 1134.5474 | W29: 1460.7974 | X29: 1460.7974 | Y29: 1460.7974 | Z29: 1460.7974 | AA29: 1460.7974 | AB29: 1460.7974 | AC29: 1460.7974 | AD29: 1460.7974 | AE29: 1460.7974 | AF29: 1460.7974 | AG29: 15660 | AH29: 1460.7974 | AI29: =SUM(O29:AH29) -> 42382.459
A30: CAL-4175 | C30: =VLOOKUP(A30,'CONSOLIDADO 2026'!H:H,1,0) -> #N/A | N30: 23 | O30: 73.897725 | P30: 73.897725 | Q30: 95.147725 | R30: 95.147725 | S30: 95.147725 | T30: 91.63425 | U30: 95.147725 | V30: 73.897725 | W30: 95.147725 | X30: 95.147725 | Y30: 95.147725 | Z30: 95.147725 | AA30: 95.147725 | AB30: 95.147725 | AC30: 95.147725 | AD30: 95.147725 | AE30: 95.147725 | AF30: 95.147725 | AG30: 1020 | AH30: 95.147725 | AI30: =SUM(O30:AH30) -> 2760.5433
A31: CAL-4176 | C31: =VLOOKUP(A31,'CONSOLIDADO 2026'!H:H,1,0) -> #N/A | N31: 46 | O31: 125.36532 | P31: 125.36532 | Q31: 161.41532 | R31: 161.41532 | S31: 161.41532 | T31: 155.45481 | U31: 161.41532 | V31: 125.36532 | W31: 161.41532 | X31: 161.41532 | Y31: 161.41532 | Z31: 161.41532 | AA31: 161.41532 | AB31: 161.41532 | AC31: 161.41532 | AD31: 161.41532 | AE31: 161.41532 | AF31: 161.41532 | AG31: 1730.4 | AH31: 161.41532 | AI31: =SUM(O31:AH31) -> 4683.1805
A32: CAL-4146 | C32: =VLOOKUP(A32,'CONSOLIDADO 2026'!H:H,1,0) -> #N/A | N32: 61 | O32: 164.48764 | P32: 164.48764 | Q32: 211.78764 | R32: 211.78764 | S32: 211.78764 | T32: 203.96706 | U32: 211.78764 | V32: 164.48764 | W32: 211.78764 | X32: 211.78764 | Y32: 211.78764 | Z32: 211.78764 | AA32: 211.78764 | AB32: 211.78764 | AC32: 211.78764 | AD32: 211.78764 | AE32: 211.78764 | AF32: 211.78764 | AG32: 2270.4 | AH32: 211.78764 | AI32: =SUM(O32:AH32) -> 6144.6446
A33: MX-1110 | C33: =VLOOKUP(A33,'CONSOLIDADO 2026'!H:H,1,0) -> #N/A | N33: 62 | O33: 26.08155 | P33: 26.08155 | Q33: 33.58155 | R33: 33.58155 | S33: 33.58155 | T33: 32.3415 | U33: 33.58155 | V33: 26.08155 | W33: 33.58155 | X33: 33.58155 | Y33: 33.58155 | Z33: 33.58155 | AA33: 33.58155 | AB33: 33.58155 | AC33: 33.58155 | AD33: 33.58155 | AE33: 33.58155 | AF33: 33.58155 | AG33: 360 | AH33: 33.58155 | AI33: =SUM(O33:AH33) -> 974.3094
O34: =SUM(O28:O33) -> 1738.77 | P34: =SUM(P28:P33) -> 1738.77 | Q34: =SUM(Q28:Q33) -> 2238.77 | R34: =SUM(R28:R33) -> 2238.77 | S34: =SUM(S28:S33) -> 2238.77 | T34: =SUM(T28:T33) -> 2156.1 | U34: =SUM(U28:U33) -> 2238.77 | V34: =SUM(V28:V33) -> 1738.77 | ... AH34: =SUM(AH28:AH33) -> 2238.77 | AI34: =SUM(O34:AH34) -> 64953.96
A35: CAL-4185 Sustituye CAL 4190
B36: Trading | O36: INVOICE | P36: INVOICE | Q36: INVOICE | R36: INVOICE | S36: INVOICE | T36: INVOICE | U36: INVOICE | V36: INVOICE
A37: F 66896 | B37: F 65719 | N37: BU | O37: SAGS 33654 | P37: SAGS 33652 | Q37: 214.39034 | R37: SAGS 33650 | S37: SAGS 33649 | T37: SAGS 33648 | U37: SAGS 33647 | V37: SAGS 33661
A38: F 66897 | B38: F 65295 | N38: 01 | O38: 265.84713 | P38: 265.84713 | Q38: 214.39034 | R38: 276.04034 | S38: 276.04034 | T38: 276.04034 | U38: 265.84713 | V38: 508.19451 | W38: =SUM(O38:V38) -> 2348.2473
A39: F 66898 | B39: F 65296 | N39: 19 | O39: 1406.8553 | P39: 1406.8553 | Q39: 1134.5474 | R39: 1460.7974 | S39: 1460.7974 | T39: 1460.7974 | U39: 1406.8553 | V39: 2689.3505 | W39: =SUM(O39:V39) -> 12426.856
A40: F 66899 | B40: F 65297 | N40: 23 | O40: 91.63425 | P40: 91.63425 | Q40: 73.897725 | R40: 95.147725 | S40: 95.147725 | T40: 95.147725 | U40: 91.63425 | V40: 175.16842 | W40: =SUM(O40:V40) -> 809.41207
A41: FACTURA ANTERIOR | B41: REFACTURACION | C41: REFERENCIA CLIENTE | D41: ORDEN | N41: 46 | O41: 155.45481 | P41: 155.45481 | Q41: 125.36532 | R41: 161.41532 | S41: 161.41532 | T41: 161.41532 | U41: 155.45481 | V41: 297.16808 | W41: =SUM(O41:V41) -> 1373.1438
A42: F 66469 | B42: F 66951 | C42: RM-M-039-SI26-M19 | D42: O-TN-2026-04253 | N42: 61 | O42: 203.96706 | P42: 203.96706 | Q42: 164.48764 | R42: 211.78764 | S42: 211.78764 | T42: 211.78764 | U42: 203.96706 | V42: 389.90431 | W42: =SUM(O42:V42) -> 1801.6561
A43: F 66465 | B43: F 66952 | C43: AF-M-104-SI26-M46 | D43: O-TN-2026-04247 | N43: 62 | O43: 32.3415 | P43: 32.3415 | Q43: 26.08155 | R43: 33.58155 | S43: 33.58155 | T43: 33.58155 | U43: 32.3415 | V43: 61.82415 | W43: =SUM(O43:V43) -> 285.67485
A44: F 66468 | B44: F 66953 | C44: RM-M-086-SI26-M19 | D44: O-TN-2026-04460 | O44: 2156.1 | P44: 2156.1 | Q44: 1738.77 | R44: 2238.77 | S44: 2238.77 | T44: 2238.77 | U44: 2156.1 | V44: 4121.61 | W44: =SUM(W38:W43) -> 19044.99
A45: F 64238 | B45: F 66892 | C45: RM-M-023-SI26-M19 | D45: O-TN-2026-02561
A46: F 64236 | B46: F 66893 | C46: RM-M-024-SI26-M19 | D46: O-TN-2026-02562 | O46: SAGS 33761
A47: F 64237 | B47: F 66894 | C47: RM-M-017-SI26-M19 | D47: O-TN-2026-02682
A48: F 64235 | B48: F 66895 | C48: RM-M-033-SI26-M19 | D48: O-TN-2026-02702 | O48: INVOICE | P48: INVOICE
A49: F 61969 | B49: F 66891 | C49: RM-M-572-SI25-M19 | D49: O-TN-2026-01626 | N49: BU | O49: SAGS 33654 | P49: SAGS 33652
N50: 01 | O50: 265.84713 | P50: 265.84713
N51: 19 | O51: 1406.8553 | P51: 1406.8553
N52: 23 | O52: 91.63425 | P52: 91.63425
N53: 46 | O53: 155.45481 | P53: 155.45481
N54: 61 | O54: 203.96706 | P54: 203.96706
A55: 3594 | N55: 62 | O55: 32.3415 | P55: 32.3415
A56: 1729529 | O56: 2156.1 | P56: 2156.1

Sheet CHINA
A1: Document Number | B1: Customer PO# | C1: Document Date | D1: Curr | E1: Outstanding Amount | F1: BU | G1: CTA | H1: CS000008981 | I1: =E2 -> 15631.1 | L1: CS000008981 | M1: 15618 | N1: Sebastian | R1: PFA | S1: Status | T1: PFA Cost | U1: Cuenta | V1: BU | W1: Invoice | X1: Invoice Amount
A2: 101011381293-F | B2: CS000008981 | C2: 46045 | D2: USD | E2: 15631.1 | F2: M23 | G2: 67180000 | H2: CS000009049 | I2: =E5+E10 -> 38602.6 | J2: =I7+I8+I10 -> 11537.1 | K2: =I2+J2 -> 50139.7 | L2: CS000009049 | M2: 58840 | N2: Marcos | R2: CS000009380 | S2: Approved | T2: 615 | U2: 67180000 | V2: M01 | W2: 101513735151-60F | X2: 1171.2 | AC2: Estos PFA se deben cobrar a ABC cuando se tengan las facturas completas de China.
A3: 101513721978-32F | B3: CS000009049 | C3: 46048 | D3: USD | E3: 27697.1 | F3: M23 | G3: 67180000 | H3: CS000009051 | I3: =E12 -> 1072 | J3: =M3-I3 -> 2176 | K3: =I3+J3 -> 3248 | L3: CS000009051 | M3: 3248 | N3: Marcos | R3: CS000009381 | S3: Approved | T3: 602 | U3: 67180000 | V3: M01
B4: CS9049+9051 | C4: 46048 | D4: USD | E4: 3169.1 | F4: M23 | G4: 67180000 | H4: CS000009050 | I4: =E6 -> 2023 | L4: CS000009050 | M4: 2380 | N4: Marcos | R4: CS000009382 | S4: Approved | T4: 4832 | U4: 67180000 | V4: M01 | W4: 101513753573-F | X4: 15097.6
B5: CS000009049 | C5: 46048 | D5: USD | E5: 17976 | F5: M23 | G5: 67180000 | H5: CS000009048 | I5: =E7 -> 4529 | J5: 3401.6 | K5: =I5+J5 -> 7930.6 | L5: CS000009048 | M5: 13584 | N5: Marcos | R5: CS000009385 | S5: Approved | T5: 4832 | U5: 67180000 | V5: M01
B6: CS000009050 | C6: 46048 | D6: USD | E6: 2023 | F6: M23 | G6: 67180000 | K6: =I1+K2+K3+I4+K5 -> 78972.4 | M6: =SUM(M1:M5) -> 93670 | R6: CS000009386 | S6: Approved | T6: 4832 | U6: 67180000 | V6: M01
B7: CS000009048 | C7: 46048 | D7: USD | E7: 4529 | F7: M23 | G7: 67180000 | I7: =E4-J7 -> 2081.1 | J7: =J3/2 -> 1088 | R7: CS000009437 | S7: Approved | T7: 22125 | U7: 67180000 | V7: M01
A8: 101513722893-37F | B8: CS000009049 | C8: 46048 | D8: USD | E8: 35644.2 | F8: M23 | G8: 67180000 | I8: =E9-J7 -> 6054.4 | M8: =M6-K6 -> 14697.6 | R8: CS000009542 | S8: Approved | T8: 28100 | U8: 67180000 | V8: M01 | W8: 101513751656-38F | X8: 15104
B9: CS9049+9051 | C9: 46048 | D9: USD | E9: 7142.4 | F9: M23 | G9: 67180000 | J9: =M2-K2 -> 8700.3 | K9: CS000009049 | T9: =SUM(T2:T8) -> 65938 | X9: =X2+X4+X8 -> 31372.8
B10: CS000009049 | C10: 46048 | D10: USD | E10: 20626.6 | F10: M23 | G10: 67180000 | I10: =E11/2 -> 3401.6
B11: CS9048+9049 | C11: 46048 | D11: USD | E11: 6803.2 | F11: M23 | G11: 67180000 | J11: =M5-K5 -> 5653.4 | K11: CS000009048 | R11: 9330 Y 9601 | S11: SE DEBEN COBRAR JUNTOS
B12: CS000009051 | C12: 46048 | D12: USD | E12: 1072 | F12: M23 | G12: 67180000
A13: AP101DN260011 | B13: DHL FREIGHT CHARGE | C13: 46048 | D13: USD | E13: 604.88 | F13: M19 | G13: 67180000
E14: =E2+E3+E8+E13 -> 79577.28
A15: Document Number | B15: Customer PO# | C15: Document Date | D15: Curr | E15: Outstanding Amount | F15: BU | G15: CTA
A16: 101513735151-60F | B16: CS000009049 | C16: 46077 | D16: USD | E16: 3840 | F16: M23 | G16: 67180000 | H16: CS000009049 | I16: =E16 -> 3840 | L16: CS000009049 | M16: 58840 | N16: Marcos
B17: CS000009048 | C17: 46077 | D17: USD | E17: 2726.4 | F17: M23 | G17: 67180000 | H17: CS000009048 | I17: =E17 -> 2726.4 | K17: =E7+E17+E28 -> 9988.2 | L17: CS000009048 | M17: 13584 | N17: Marcos
B18: CS000009388 | C18: 46077 | D18: USD | E18: 2009.6 | F18: M23 | G18: 67180000 | H18: CS000009388 | I18: =E18 -> 2009.6 | L18: CS000009388 | M18: 1984 | N18: Marcos
B19: CS9380+9381 | C19: 46077 | D19: USD | E19: 1171.2 | F19: M01 | G19: 67180000 | H19: CS000009380 | I19: =E19/2 -> 585.6 | L19: CS000009380 | M19: 615 | N19: Juan Pablo
B20: CS000009505 | C20: 46077 | D20: USD | E20: 8528 | F20: M19 | G20: 67180000 | H20: CS000009381 | I20: =E19/2 -> 585.6 | L20: CS000009381 | M20: 602 | N20: Juan Pablo
B21: CS000009505 | C21: 46077 | D21: USD | E21: 7104 | F21: M19 | G21: 67180000 | H21: CS000009505 | I21: =E20+E21+E22 -> 22736 | J21: =M21-I21 -> -14396 | L21: CS000009505 | M21: 8340 | N21: Arturo
B22: CS000009505 | C22: 46077 | D22: USD | E22: 7104 | F22: M19 | G22: 67180000 | H22: CS000009506 | I22: =E23 -> 8528 | L22: CS000009506 | M22: 19111 | N22: Arturo
B23: CS000009506 | C23: 46077 | D23: USD | E23: 8528 | F23: M19 | G23: 67180000 | H23: CS000009482 | I23: =E24 -> 17670.4 | L23: CS000009482 | M23: 17242 | N23: Sebastian
A24: 101011392811-12F | B24: CS000009482 | C24: 45713 | D24: USD | E24: 17670.4 | F24: M46 | G24: 67180000 | I24: =SUM(I16:I23) -> 58681.6
E25: =SUM(E16:E24) -> 58681.6
A27: Document Number | B27: Customer PO# | C27: Document Date | D27: Curr | E27: Outstanding Amount | F27: BU | G27: CTA
A28: 101513751656-38F | B28: CS000009048 | C28: 46107 | D28: USD | E28: 2732.8 | F28: M23 | G28: 67180000 | H28: CS000009048 | I28: 13584 | J28: Marcos
B29: CS000009506 | C29: 46107 | D29: USD | E29: 1433.6 | F29: M19 | G29: 67180000 | H29: CS000009506 | I29: 19111 | J29: Arturo
B30: CS000009542 | C30: 46107 | D30: USD | E30: 15104 | F30: M01 | G30: 67180000 | H30: CS000009542 | I30: 28100 | J30: Juan Pablo
B31: CS000009635 | C31: 46107 | D31: USD | E31: 2124.8 | F31: M19 | G31: 67180000 | H31: CS000009635 | I31: 1067 | J31: Arturo
A32: AP101DN260134 | B32: CS000009383 | C32: 46107 | D32: USD | E32: 2334.04 | F32: M19 | G32: 67180000
B33: CS000009898
H35: CS000009806 | I35: 1736 | K35: =4*31 -> 124
H36: CS000009805 | I36: 3432
H37: CS000009804 | I37: 31200
H38: CS000009803 | I38: 1336
I39: =SUM(I35:I38) -> 37704
H41: CS000009996
H42: CS000010007

Sheet NISS
A1: Date of invoice | B1: Date of export | C1: wk no | D1: PN | E1: Customer PO (Movex) | F1: DN | G1: ORACLE ORDER | H1: Quantity | I1: REV | J1: Invoice no | K1: Amount | L1: Freight cost | M1: Total Amount | N1: PLL | O1: CTN | P1: Nett | Q1: Gross | R1: Incoterms | S1: E-broj | T1: Customer number | U1: Bill to | V1: Ship to | W1: PFA | X1: Container No
A2: 45842 | B2: 45842 | C2: 27 | D2: 1663-5YY0194-MTEN/RS | F2: 2910069209 | G2: 1197004349 | H2: 2592 | I2: D | J2: 14745C | L2: 1295.49 | M2: 0.49980324 | N2: 2 | O2: 24 | P2: 189.22 | Q2: 323.9 | R2: CPT ALTAMIRA | S2: E-17349 | T2: W_34798 | U2: JENA | V2: Mexico | X2: SARU0013110 | AC2: 226 | AL2: PFA # | AM2: Status | AN2: Origin Company Name | AO2: Origin Country | AP2: Item Code | AQ2: Item Description | AR2: Quantity (pcs) | AS2: Bill to Cost Center (Primary)
A3: 45842 | B3: 45842 | C3: 27 | D3: 1663-5YY0194-MTEN/RS | F3: 2910069210 | G3: 3197001993 | H3: 2592 | I3: D | J3: 14746C | L3: 1295.49 | M3: 0.49980324 | N3: 2 | O3: 24 | P3: 189.22 | Q3: 323.9 | R3: CPT ALTAMIRA | S3: E-17349 | T3: W_34798 | U3: JENA | V3: Mexico | X3: SARU0013110 | AC3: 226 | AL3: CS000009615 | AM3: Approved | AN3: Johnson Electric d.o.o. Nis | AO3: Serbia | AP3: 1663-5YY0294ENNV00 | AQ3: PCBA | AR3: 30720 | AS3: Americas: APG PC MEXICO
A4: 45842 | B4: 45842 | C4: 27 | D4: 1663-5YY0294-H01 | F4: 2910069211 | G4: 1197004354 | H4: 6208 | I4: E | J4: 14752C | L4: 1150.18 | M4: 0.18527384 | N4: 2 | O4: 20 | P4: 130.37 | Q4: 287.57 | R4: CPT ALTAMIRA | S4: E-17349 | T4: W_34798 | U4: JENA | V4: Mexico | X4: SARU0013110 | AC4: 226 | AL4: CS000009614 | AM4: Pending 1st Level Approval | AN4: Johnson Electric d.o.o. Nis | AO4: Serbia | AP4: 1663-5YY0499ENNV00 | AQ4: PCBA | AR4: 10560 | AS4: Americas: APG- PC- Springfield
A5: 45842 | B5: 45842 | C5: 27 | D5: 1663-5YY0271EN | F5: 2910069212 | G5: 3197002016 | H5: 2112 | I5: G | J5: 14747C | L5: 723.85 | M5: 0.34273201 | N5: 1 | O5: 12 | P5: 80.26 | Q5: 180.98 | R5: CPT ALTAMIRA | S5: E-17349 | T5: W_34798 | U5: JENA | V5: Mexico | X5: SARU0013110 | AC5: 226 | AL5: CS000009613 | AM5: Approved | AN5: Johnson Electric d.o.o. Nis | AO5: Serbia | AP5: 1663-5YY0250ENNV00 | AQ5: PCBA | AR5: 8448 | AS5: Americas: APG- PC- Springfield
A6: 45842 | B6: 45842 | C6: 27 | D6: 1663-5YY0271EN | F6: 2910069213 | G6: 3197002020 | H6: 2112 | I6: G | J6: 14748C | L6: 723.85 | M6: 0.34273201 | N6: 1 | O6: 12 | P6: 80.26 | Q6: 180.98 | R6: CPT ALTAMIRA | S6: E-17349 | T6: W_34798 | U6: JENA | V6: Mexico | X6: SARU0013110 | AC6: 226 | AL6: CS000009612 | AM6: Approved | AN6: Johnson Electric d.o.o. Nis | AO6: Serbia | AP6: 1663-5YY0122ENNV00 | AQ6: PCBA | AR6: 3456 | AS6: Americas: APG PC MEXICO
A7: 45842 | B7: 45842 | C7: 27 | D7: 1663-5YY0274EN | F7: 2910069214 | G7: 1197004352 | H7: 2112 | I7: H | J7: 14749C | L7: 723.85 | M7: 0.34273201 | N7: 1 | O7: 12 | P7: 80.26 | Q7: 180.98 | R7: CPT ALTAMIRA | S7: E-17349 | T7: W_34798 | U7: JENA | V7: Mexico | X7: SARU0013110 | AC7: 226 | AL7: CS000009531 | AM7: Approved | AN7: Johnson Electric d.o.o. Nis | AO7: Serbia | AP7: 1663-5YY0296ENNV13 | AQ7: PCBA | AR7: 4224 | AS7: Americas: APG- PC BRAZIL
A8: 45842 | B8: 45842 | C8: 27 | D8: 1663-5YY0274EN | F8: 2910069215 | G8: 3197001996 | H8: 4224 | I8: H | J8: 14750C | L8: 1447.7 | M8: 0.34273201 | N8: 2 | O8: 24 | P8: 160.51 | Q8: 361.95 | R8: CPT ALTAMIRA | S8: E-17349 | T8: W_34798 | U8: JENA | V8: Mexico | X8: SARU0013110 | AC8: 226 | AL8: CS000009530 | AM8: Approved | AN8: Johnson Electric d.o.o. Nis | AO8: Serbia | AP8: 1663-5YY0294ENNV00 | AQ8: PCBA | AR8: 23040 | AS8: Americas: APG PC MEXICO
A9: 45842 | B9: 45842 | C9: 27 | D9: 1663-5YY0333EN | F9: 2910069216 | G9: 3197002018 | H9: 3840 | I9: C | J9: 14751C | L9: 686.03 | M9: 0.17865365 | N9: 1 | O9: 12 | P9: 76.8 | Q9: 167 | R9: CPT ALTAMIRA | S9: E-17349 | T9: W_34798 | U9: JENA | V9: Mexico | X9: SARU0013110 | AC9: 226 | AL9: CS000009529 | AM9: Approved | AN9: Johnson Electric d.o.o. Nis | AO9: Serbia | AP9: 1663-5YY0250ENNV00 | AQ9: PCBA | AR9: 8448 | AS9: Americas: APG- PC- Springfield
A10: 45847 | B10: 45847 | C10: 28 | D10: 1663-5YY0196EN | F10: 2910069305 | G10: 3197001989 | H10: 613 | I10: D | J10: 14781C | L10: 1629.95 | M10: 2.6589723 | N10: 1 | O10: 6 | P10: 58.84 | Q10: 103 | R10: CPT ALTAMIRA | S10: E-17415 | T10: W_34798 | U10: JENA | V10: Mexico | W10: CS000007888 | X10: avio | AC10: 228
A11: 45849 | B11: 45849 | C11: 28 | D11: 1663-5YY0122EN/RS | F11: 2910069396 | G11: 1197004322 | H11: 3456 | I11: B | J11: 14815C | L11: 1062.64 | M11: 0.30747685 | N11: 2 | O11: 24 | P11: 248.83 | Q11: 398 | R11: CPT ALTAMIRA | S11: E-17388 | T11: W_34798 | U11: JENA | V11: Mexico | X11: GESU5563043 | AC11: 229
A12: 45849 | B12: 45849 | C12: 28 | D12: 1663-5YY0247EN/RS | F12: 2910069397 | G12: 3197001983 | H12: 6912 | I12: B | J12: 14816C | L12: 2125.28 | M12: 0.30747685 | N12: 4 | O12: 48 | P12: 497.66 | Q12: 804 | R12: CPT ALTAMIRA | S12: E-17388 | T12: W_34798 | U12: JENA | V12: Mexico | X12: GESU5563043 | AC12: 229
A13: 45849 | B13: 45849 | C13: 28 | D13: 1663-5YY0247EN/RS | F13: 2910069398 | G13: 3197001974 | H13: 1728 | I13: B | J13: 14817C | L13: 531.32 | M13: 0.30747685 | N13: 1 | O13: 12 | P13: 124.42 | Q13: 201 | R13: CPT ALTAMIRA | S13: E-17388 | T13: W_34798 | U13: JENA | V13: Mexico | X13: GESU5563043 | AC13: 229
A14: 45849 | B14: 45849 | C14: 28 | D14: 1663-5YY0318EN | F14: 2910069399 | G14: 1197004357 | H14: 2016 | I14: C | J14: 14818C | L14: 393.52 | M14: 0.19519841 | N14: 1 | O14: 12 | P14: 53.43 | Q14: 142.02 | R14: CPT ALTAMIRA | S14: E-17388 | T14: W_34798 | U14: JENA | V14: Mexico | X14: GESU5563043 | AC14: 229
A15: 45849 | B15: 45849 | C15: 28 | D15: 1663-5YY0333EN | F15: 2910069400 | G15: 3197002017 | H15: 3840 | I15: C | J15: 14819C | L15: 475.25 | M15: 0.12376302 | N15: 1 | O15: 12 | P15: 76.8 | Q15: 167 | R15: CPT ALTAMIRA | S15: E-17388 | T15: W_34798 | U15: JENA | V15: Mexico | X15: GESU5563043 | AC15: 229
A16: 45849 | B16: 45849 | C16: 28 | D16: 1663-5YY0445EN | F16: 2910069401 | G16: 3197001966 | H16: 2592 | I16: E | J16: 14822C | L16: 930.42 | M16: 0.35895833 | N16: 2 | O16: 24 | P16: 181.44 | Q16: 316 | R16: CPT ALTAMIRA | S16: E-17388 | T16: W_34798 | U16: JENA | V16: Mexico | X16: GESU5563043 | AC16: 229
A17: 45849 | B17: 45849 | C17: 28 | D17: 1663-5YY0445EN | F17: 2910069402 | G17: 1197004330 | H17: 1296 | I17: E | J17: 14823C | L17: 465.21 | M17: 0.35895833 | N17: 1 | O17: 12 | P17: 90.72 | Q17: 158 | R17: CPT ALTAMIRA | S17: E-17388 | T17: W_34798 | U17: JENA | V17: Mexico | X17: GESU5563043 | AC17: 229
A18: 45849 | B18: 45849 | C18: 28 | D18: 1663-5YY0445EN | F18: 2910069403 | G18: 3197001987 | H18: 2592 | I18: E | J18: 14824C | L18: 930.42 | M18: 0.35895833 | N18: 2 | O18: 24 | P18: 181.44 | Q18: 316 | R18: CPT ALTAMIRA | S18: E-17388 | T18: W_34798 | U18: JENA | V18: Mexico | X18: GESU5563043 | AC18: 229
A19: 45849 | B19: 45849 | C19: 28 | D19: 1663-5YY0445EN | F19: 2910069404 | G19: 1197004348 | H19: 1137 | I19: E | J19: 14825C | L19: 422.32 | M19: 0.3714336 | N19: 1 | O19: 11 | P19: 79.59 | Q19: 137 | R19: CPT ALTAMIRA | S19: E-17388 | T19: W_34798 | U19: JENA | V19: Mexico | X19: GESU5563043 | AC19: 229
A20: 45849 | B20: 45849 | C20: 28 | D20: 1663-5YY0078EN/RS | F20: 2910069405 | G20: 3197002025 | H20: 1728 | I20: D | J20: 14821C | L20: 520.91 | M20: 0.30145255 | N20: 1 | O20: 12 | P20: 0 | Q20: 132.92 | R20: CPT ALTAMIRA | S20: E-17388 | T20: W_34798 | U20: JENA | V20: Mexico | X20: GESU5563043 | AC20: 229
A21: 45849 | B21: 45849 | C21: 28 | D21: 1663-5YY0061EN/RS | F21: 2910069406 | G21: 3197001988 | H21: 657 | I21: G | J21: 14820C | L21: 120.15 | M21: 0.18287671 | N21: 1 | O21: 5 | P21: 43.34 | Q21: 86 | R21: CPT ALTAMIRA | S21: E-17388 | T21: W_34798 | U21: JENA | V21: Mexico | X21: GESU5563043 | AC21: 229
A22: 45856 | B22: 45856 | C22: 29 | D22: 1663-5YY0194-MTEN/RS | F22: 2910069584 | G22: 3197002046 | H22: 2592 | I22: D | J22: 14913C | L22: 714.49 | M22: 0.27565201 | N22: 2 | O22: 24 | P22: 189.22 | Q22: 323.9 | R22: CPT ALTAMIRA | S22: E-17432 | T22: W_34798 | U22: JENA | V22: Mexico | X22: MSDU8734823 | AC22: 230
... A49: 45863 | B49: 45863 | C49: 30 | D49: 1663-5YY0333EN | F49: 2910069793 | G49: 3197002023 | H49: 7680 | I49: C | J49: 15026C | L49: 898.88 | M49: 0.11704167 | N49: 2 | O49: 24 | P49: 153.6 | Q49: 343.04 | R49: CPT ALTAMIRA | S49: E-17445 | T49: W_34798 | U49: JENA | V49: Mexico | X49: TGCU0233629 | AC49: 232
A50: 45867 | B50: 45867 | C50: 31 | D50: 1663-5YY0262EN/RS | F50: 2910069841 | G50: 3197002032 | H50: 1008 | I50: A | J50: 15038C | L50: 3923 | M50: 3.8918651 | N50: 1 | O50: 7 | P50: 83.66 | Q50: 121 | R50: CPT ALTAMIRA | S50: E-17519 | T50: W_34798 | U50: JENA | V50: Mexico | W50: CS000008061 | X50: avio | AC50: 233
A51: 45869 | B51: 45869 | C51: 31 | D51: 1663-5YY0257-H02 | F51: 2910069862 | G51: 3197001995 | H51: 3840 | I51: H | J51: 15040C | L51: 1541.5 | M51: 0.40143229 | N51: 1 | O51: 12 | P51: 84.48 | Q51: 163 | R51: CPT ALTAMIRA | S51: E-17524 | T51: W_34798 | U51: JENA | V51: Mexico | W51: CS000007967 | X51: avio | AC51: 234
A52: 45869 | B52: 45869 | C52: 31 | D52: 1663-5YY0257-H02 | F52: 2910069863 | G52: 1197004356 | H52: 3840 | I52: H | J52: 15041C | L52: 1541.5 | M52: 0.40143229 | N52: 1 | O52: 12 | P52: 84.48 | Q52: 162 | R52: CPT ALTAMIRA | S52: E-17524 | T52: W_34798 | U52: JENA | V52: Mexico | W52: CS000007967 | X52: avio | AC52: 234
A53: 45876 | B53: 45876 | C53: 32 | D53: 1663-5YY0257-H02 | F53: 2910069897 | G53: 1197004347 | H53: 3200 | I53: H | J53: 15044C | L53: 4893.18 | M53: 1.5291188 | N53: 1 | O53: 10 | P53: 70.4 | Q53: 139 | R53: CPT ALTAMIRA | S53: E-17532 | T53: W_34798 | U53: JENA | V53: Mexico | W53: CS000007887 | X53: avio | AC53: 236
A54: 45876 | B54: 45876 | C54: 32 | D54: 1663-5YY0257-H02 | F54: 2910069898 | G54: 3197001964 | H54: 1549 | I54: H | J54: 15045C | L54: 2813.26 | M54: 1.8161782 | N54: 1 | O54: 5 | P54: 34.08 | Q54: 79 | R54: CPT ALTAMIRA | S54: E-17532 | T54: W_34798 | U54: JENA | V54: Mexico | W54: CS000007887 | X54: avio | AC54: 236
A55: 45877 | B55: 45881 | C55: 32 | D55: 1663-5YY0294-H01 | F55: 2910069923 | G55: 3197002051 | H55: 3840 | I55: E | J55: 15059C | L55: 580.23 | M55: 0.15110156 | N55: 1 | O55: 12 | P55: 80.64 | Q55: 177 | R55: CPT ALTAMIRA | S55: E-17473 | T55: W_34798 | U55: JENA | V55: Mexico | X55: MSDU6387941 | AC55: 237
A56: 45877 | B56: 45881 | C56: 32 | D56: 1663-5YY0294-H01 | F56: 2910069924 | G56: 3197002043 | H56: 3840 | I56: E | J56: 15060C | L56: 580.23 | M56: 0.15110156 | N56: 1 | O56: 12 | P56: 80.64 | Q56: 177 | R56: CPT ALTAMIRA | S56: E-17473 | T56: W_34798 | U56: JENA | V56: Mexico | X56: MSDU6387941 | AC56: 237
A57: 45877 | B57: 45881 | C57: 32 | D57: 1663-5YY0122EN/RS | F57: 2910069925 | G57: 1197004322 | H57: 771 | I57: B | J57: 15050C | L57: 342.02 | M57: 0.44360571 | N57: 1 | O57: 6 | P57: 55.51 | Q57: 98 | R57: CPT ALTAMIRA | S57: E-17473 | T57: W_34798 | U57: JENA | V57: Mexico | X57: MSDU6387941 | AC57: 237
A58: 45877 | B58: 45881 | C58: 32 | D58: 1663-5YY0247EN/RS | F58: 2910069926 | G58: 1197004331 | H58: 5184 | I58: B | J58: 15051C | L58: 1963.93 | M58: 0.37884452 | N58: 3 | O58: 36 | P58: 373.25 | Q58: 603 | R58: CPT ALTAMIRA | S58: E-17473 | T58: W_34798 | U58: JENA | V58: Mexico | X58: MSDU6387941 | AC58: 237
A59: 45877 | B59: 45881 | C59: 32 | D59: 1663-5YY0247EN/RS | F59: 2910069927 | G59: 3197002062 | H59: 2953 | I59: B | J59: 15052C | L59: 1146.95 | M59: 0.38840163 | N59: 2 | O59: 21 | P59: 212.62 | Q59: 344 | R59: CPT ALTAMIRA | S59: E-17473 | T59: W_34798 | U59: JENA | V59: Mexico | X59: MSDU6387941 | AC59: 237
A60: 45877 | B60: 45881 | C60: 32 | D60: 1663-5YY0268-H02 | F60: 2910069928 | G60: 1197004388 | H60: 2016 | I60: H | J60: 15058C | L60: 451.51 | M60: 0.22396329 | N60: 1 | O60: 12 | P60: 54.43 | Q60: 140 | R60: CPT ALTAMIRA | S60: E-17473 | T60: W_34798 | U60: JENA | V60: Mexico | X60: MSDU6387941 | AC60: 237
A61: 45877 | B61: 45881 | C61: 32 | D61: 1663-5YY0274EN | F61: 2910069929 | G61: 3197002042 | H61: 2112 | I61: H | J61: 15053C | L61: 617.84 | M61: 0.29253788 | N61: 1 | O61: 12 | P61: 80.26 | Q61: 180.98 | R61: CPT ALTAMIRA | S61: E-17473 | T61: W_34798 | U61: JENA | V61: Mexico | X61: MSDU6387941 | AC61: 237
A62: 45877 | B62: 45881 | C62: 32 | D62: 1663-5YY0274EN | F62: 2910069930 | G62: 3197002038 | H62: 2112 | I62: H | J62: 15054C | L62: 617.84 | M62: 0.29253788 | N62: 1 | O62: 12 | P62: 80.26 | Q62: 180.98 | R62: CPT ALTAMIRA | S62: E-17473 | T62: W_34798 | U62: JENA | V62: Mexico | X62: MSDU6387941 | AC62: 237
A63: 45877 | B63: 45881 | C63: 32 | D63: 1663-5YY0274EN | F63: 2910069931 | G63: 1197004413 | H63: 2112 | I63: H | J63: 15055C | L63: 617.84 | M63: 0.29253788 | N63: 1 | O63: 12 | P63: 80.26 | Q63: 180.98 | R63: CPT ALTAMIRA | S63: E-17473 | T63: W_34798 | U63: JENA | V63: Mexico | X63: MSDU6387941 | AC63: 237
A64: 45877 | B64: 45881 | C64: 32 | D64: 1663-5YY0333EN | F64: 2910069932 | G64: 1197004405 | H64: 3840 | I64: C | J64: 15057C | L64: 585.56 | M64: 0.15248958 | N64: 1 | O64: 12 | P64: 76.8 | Q64: 167 | R64: CPT ALTAMIRA | S64: E-17473 | T64: W_34798 | U64: JENA | V64: Mexico | X64: MSDU6387941 | AC64: 237
A65: 45877 | B65: 45881 | C65: 32 | D65: 1663-5YY0333EN | F65: 2910069933 | G65: 1197004407 | H65: 2880 | I65: C | J65: 15056C | L65: 460.51 | M65: 0.15989931 | N65: 1 | O65: 9 | P65: 57.6 | Q65: 127 | R65: CPT ALTAMIRA | S65: E-17473 | T65: W_34798 | U65: JENA | V65: Mexico | X65: MSDU6387941 | AC65: 237
A66: 45881 | B66: 45881 | C66: 33 | D66: 1663-5YY0194-MTEN/RS | F66: 2910069962 | G66: 3197002040 | H66: 2592 | I66: D | J66: 15072C | L66: 10288.26 | M66: 3.9692361 | N66: 2 | O66: 24 | P66: 189.22 | Q66: 323.9 | R66: CPT ALTAMIRA | S66: E-17540 | T66: W_34798 | U66: JENA | V66: Mexico | W66: CS000008149 | X66: avio | AC66: 238
A67: 45881 | B67: 45881 | C67: 33 | D67: 1663-5YY0294-H01 | F67: 2910069963 | G67: 3197002035 | H67: 3840 | I67: E | J67: 15074C | L67: 5398.62 | M67: 1.4058906 | N67: 1 | O67: 12 | P67: 80.64 | Q67: 169.96 | R67: CPT ALTAMIRA | S67: E-17540 | T67: W_34798 | U67: JENA | V67: Mexico | W67: CS000008148 | X67: avio | AC67: 238
A68: 45881 | B68: 45881 | C68: 33 | D68: 1663-5YY0271EN | F68: 2910069964 | G68: 1197004406 | H68: 2112 | I68: G | J68: 15073C | L68: 5748.54 | M68: 2.7218466 | N68: 1 | O68: 12 | P68: 80.26 | Q68: 180.98 | R68: CPT ALTAMIRA | S68: E-17540 | T68: W_34798 | U68: JENA | V68: Mexico | W68: CS000008150 | X68: avio | AC68: 238
A69: 45884 | B69: 45888 | C69: 33 | D69: 1663-5YY0194-MTEN/RS | F69: 2910070035 | G69: 1197004409 | H69: 1296 | I69: D | J69: 15084C | L69: 997.14 | M69: 0.76939815 | N69: 1 | O69: 12 | P69: 94.61 | Q69: 161.95 | R69: CPT ALTAMIRA | S69: E-17512 | T69: W_34798 | U69: JENA | V69: Mexico | AC69: 239
A70: 45884 | B70: 45888 | C70: 33 | D70: 1663-5YY0294-H01 | F70: 2910070036 | G70: 3197002035 | H70: 3574 | I70: E | J70: 15089C | L70: 1012.08 | M70: 0.28317851 | N70: 1 | O70: 12 | P70: 75.05 | Q70: 152 | R70: CPT ALTAMIRA | S70: E-17512 | T70: W_34798 | U70: JENA | V70: Mexico | AC70: 239
A71: 45884 | B71: 45888 | C71: 33 | D71: 1663-5YY0208EN/RS | F71: 2910070037 | G71: 3197002001 | H71: 1717 | I71: B | J71: 15085C | L71: 1101.79 | M71: 0.64169482 | N71: 1 | O71: 12 | P71: 111.61 | Q71: 182 | R71: CPT ALTAMIRA | S71: E-17512 | T71: W_34798 | U71: JENA | V71: Mexico | AC71: 239
A72: 45884 | B72: 45888 | C72: 33 | D72: 1663-5YY0274EN | F72: 2910070038 | G72: 3197002077 | H72: 2112 | I72: H | J72: 15087C | L72: 1114.3 | M72: 0.52760417 | N72: 1 | O72: 12 | P72: 80.26 | Q72: 180.98 | R72: CPT ALTAMIRA | S72: E-17512 | T72: W_34798 | U72: JENA | V72: Mexico | AC72: 239
A73: 45884 | B73: 45888 | C73: 33 | D73: 1663-5YY0321EN | F73: 2910070039 | G73: 1197004387 | H73: 2016 | I73: C | J73: 15088C | L73: 825.11 | M73: 0.40928075 | N73: 1 | O73: 12 | P73: 56.45 | Q73: 141 | R73: CPT ALTAMIRA | S73: E-17512 | T73: W_34798 | U73: JENA | V73: Mexico | AC73: 239
A74: 45884 | B74: 45888 | C74: 33 | D74: 1663-5YY0445EN | F74: 2910070040 | G74: 1197004415 | H74: 1296 | I74: E | J74: 15090C | L74: 1033.76 | M74: 0.79765432 | N74: 1 | O74: 12 | P74: 90.72 | Q74: 158 | R74: CPT ALTAMIRA | S74: E-17512 | T74: W_34798 | U74: JENA | V74: Mexico | AC74: 239
A75: 45884 | B75: 45888 | C75: 33 | D75: 1663-5YY0445EN | F75: 2910070041 | G75: 3197002102 | H75: 1296 | I75: E | J75: 15091C | L75: 1033.76 | M75: 0.79765432 | N75: 1 | O75: 12 | P75: 90.72 | Q75: 158 | R75: CPT ALTAMIRA | S75: E-17512 | T75: W_34798 | U75: JENA | V75: Mexico | AC75: 239
A76: 45884 | B76: 45888 | C76: 33 | D76: 1663-5YY0078EN/RS | F76: 2910070042 | G76: 1197004325 | H76: 720 | I76: D | J76: 15086C | L76: 556.3 | M76: 0.77263889 | N76: 1 | O76: 5 | P76: 0 | Q76: 90 | R76: CPT ALTAMIRA | S76: E-17512 | T76: W_34798 | U76: JENA | V76: Mexico | AC76: 239
A77: 45889 | B77: 45889 | C77: 34 | D77: 1663-5YY0371EN | F77: 2910070166 | G77: 3197002045 | H77: 3840 | I77: C | J77: 15174C | L77: 2525.45 | M77: 0.65766927 | N77: 1 | O77: 12 | P77: 80.64 | Q77: 160 | R77: CPT ALTAMIRA | S77: E-17579 | T77: W_34798 | U77: JENA | V77: Mexico | W77: CS000008185 | X77: avio | AC77: 241
A78: 45891 | B78: 45891 | C78: 34 | D78: 1663-5YY0194-MTEN/RS | F78: 2910070218 | G78: 1197004409 | H78: 1296 | I78: D | J78: 15184C | L78: 656.47 | M78: 0.50653549 | N78: 1 | O78: 12 | P78: 94.61 | Q78: 161.95 | R78: CPT ALTAMIRA | S78: E-17556 | T78: W_34798 | U78: JENA | V78: Mexico | X78: MSNU1061818 | AC78: 242
A79: 45891 | B79: 45891 | C79: 34 | D79: 1663-5YY0294-H01 | F79: 2910070219 | G79: 1197004410 | H79: 3840 | I79: F | J79: 15191C | L79: 688.95 | M79: 0.17941406 | N79: 1 | O79: 12 | P79: 80.64 | Q79: 177 | R79: CPT ALTAMIRA | S79: E-17556 | T79: W_34798 | U79: JENA | V79: Mexico | X79: MSNU1061818 | AC79: 242
A80: 45891 | B80: 45891 | C80: 34 | D80: 1663-5YY0247EN/RS | F80: 2910070220 | G80: 3197002060 | H80: 5184 | I80: B | J80: 15185C | L80: 2331.9 | M80: 0.44982639 | N80: 3 | O80: 36 | P80: 373.25 | Q80: 603 | R80: CPT ALTAMIRA | S80: E-17556 | T80: W_34798 | U80: JENA | V80: Mexico | X80: MSNU1061818 | AC80: 242
A81: 45891 | B81: 45891 | C81: 34 | D81: 1663-5YY0247EN/RS | F81: 2910070221 | G81: 3197002062 | H81: 1728 | I81: B | J81: 15186C | L81: 777.3 | M81: 0.44982639 | N81: 1 | O81: 12 | P81: 124.42 | Q81: 201 | R81: CPT ALTAMIRA | S81: E-17556 | T81: W_34798 | U81: JENA | V81: Mexico | X81: MSNU1061818 | AC81: 242
A82: 45891 | B82: 45891 | C82: 34 | D82: 1663-5YY0318EN | F82: 2910070222 | G82: 1197004414 | H82: 2016 | I82: C | J82: 15187C | L82: 575.71 | M82: 0.28557044 | N82: 1 | O82: 12 | P82: 53.43 | Q82: 142.02 | R82: CPT ALTAMIRA | S82: E-17556 | T82: W_34798 | U82: JENA | V82: Mexico | X82: MSNU1061818 | AC82: 242
A83: 45891 | B83: 45891 | C83: 34 | D83: 1663-5YY0333EN | F83: 2910070223 | G83: 3197002101 | H83: 6720 | I83: C | J83: 15188C | L83: 1242.06 | M83: 0.18483036 | N83: 2 | O83: 21 | P83: 134.4 | Q83: 292 | R83: CPT ALTAMIRA | S83: E-17556 | T83: W_34798 | U83: JENA | V83: Mexico | X83: MSNU1061818 | AC83: 242
A84: 45891 | B84: 45891 | C84: 34 | D84: 1663-5YY0321EN | F84: 2910070224 | G84: 3197002075 | H84: 2016 | I84: C | J84: 15189C | L84: 543.21 | M84: 0.2694494 | N84: 1 | O84: 12 | P84: 56.45 | Q84: 141 | R84: CPT ALTAMIRA | S84: E-17556 | T84: W_34798 | U84: JENA | V84: Mexico | X84: MSNU1061818 | AC84: 242
A85: 45891 | B85: 45891 | C85: 34 | D85: 1663-5YY0296EN | F85: 2910070225 | G85: 1197004411 | H85: 2112 | I85: E | J85: 15190C | L85: 807.34 | M85: 0.38226326 | N85: 1 | O85: 12 | P85: 82.37 | Q85: 180 | R85: CPT ALTAMIRA | S85: E-17556 | T85: W_34798 | U85: JENA | V85: Mexico | X85: MSNU1061818 | AC85: 242
A86: 45891 | B86: 45891 | C86: 34 | D86: 1663-5YY0394EN | F86: 2910070235 | G86: 3197002079 | H86: 2637 | I86: D | J86: 15201C | L86: 3589.38 | M86: 1.3611604 | N86: 1 | O86: 11 | P86: 0 | Q86: 151 | R86: CPT ALTAMIRA | S86: E-17605 | T86: W_34798 | U86: JENA | V86: Mexico | W86: CS000008186 | X86: avio | AC86: 243
A87: 45898 | B87: 45898 | C87: 35 | D87: 1663-5YY0394EN | F87: 2910070355 | G87: 3197002053 | H87: 2080 | I87: D | J87: 15232C | L87: 2202.79 | M87: 1.0590337 | N87: 1 | O87: 8 | P87: 0 | Q87: 117 | R87: CPT ALTAMIRA | S87: E-17652 | T87: W_34798 | U87: JENA | V87: Mexico | W87: CS000008186 | X87: avio | AC87: 245
A88: 45898 | B88: 45902 | C88: 35 | D88: 1663-5YY0194-MTEN/RS | F88: 2910070384 | G88: 1197004409 | H88: 1175 | I88: D | J88: 15233C | L88: 895.93 | M88: 0.76249362 | N88: 1 | O88: 11 | P88: 85.78 | Q88: 141 | R88: CPT ALTAMIRA | S88: E-17601 | T88: W_34798 | U88: JENA | V88: Mexico | X88: MSMU1751928 | AC88: 246
A89: 45898 | B89: 45902 | C89: 35 | D89: 1663-5YY0294-H01 | F89: 2910070385 | G89: 1197004410 | H89: 7680 | I89: F | J89: 15236C | L89: 2039.31 | M89: 0.26553516 | N89: 2 | O89: 24 | P89: 161.28 | Q89: 354 | R89: CPT ALTAMIRA | S89: E-17601 | T89: W_34798 | U89: JENA | V89: Mexico | X89: MSMU1751928 | AC89: 246
A90: 45898 | B90: 45902 | C90: 35 | D90: 1663-5YY0294-H01 | F90: 2910070386 | G90: 3197002107 | H90: 3520 | I90: F | J90: 15237C | L90: 947.18 | M90: 0.26908523 | N90: 1 | O90: 11 | P90: 73.92 | Q90: 153 | R90: CPT ALTAMIRA | S90: E-17601 | T90: W_34798 | U90: JENA | V90: Mexico | X90: MSMU1751928 | AC90: 246
A91: 45898 | B91: 45902 | C91: 35 | D91: 1663-5YY0294-H01 | F91: 2910070387 | G91: 3197002107 | H91: 2091 | I91: F | J91: 15238C | L91: 638.52 | M91: 0.30536585 | N91: 1 | O91: 7 | P91: 43.91 | Q91: 100 | R91: CPT ALTAMIRA | S91: E-17601 | T91: W_34798 | U91: JENA | V91: Mexico | X91: MSMU1751928 | AC91: 246
A92: 45898 | B92: 45902 | C92: 35 | D92: 1663-5YY0247EN/RS | F92: 2910070388 | G92: 3197002063 | H92: 3027 | I92: B | J92: 15234C | L92: 2070.19 | M92: 0.68390816 | N92: 2 | O92: 22 | P92: 217.94 | Q92: 354 | R92: CPT ALTAMIRA | S92: E-17601 | T92: W_34798 | U92: JENA | V92: Mexico | X92: MSMU1751928 | AC92: 246
A93: 45898 | B93: 45902 | C93: 35 | D93: 1663-5YY0274EN | F93: 2910070389 | G93: 3197002077 | H93: 2112 | I93: H | J93: 15235C | L93: 1085.74 | M93: 0.51408144 | N93: 1 | O93: 12 | P93: 80.26 | Q93: 181 | R93: CPT ALTAMIRA | S93: E-17601 | T93: W_34798 | U93: JENA | V93: Mexico | X93: MSMU1751928 | AC93: 246
A94: 45898 | B94: 45898 | C94: 35 | D94: 1663-1120026EN | F94: 2910070419 | G94: 3237000001 | H94: 840 | I94: E | J94: 15275C | L94: 235.15 | M94: 0.27994048 | N94: 1 | O94: 3 | P94: 0 | Q94: 30 | R94: CPT ALTAMIRA | S94: E-17652 | T94: W_34798 | U94: JENA | V94: Mexico | X94: avio | AC94: 247
A95: 45902 | B95: 45902 | C95: 36 | D95: 1663-5YY0294-H01 | F95: 2910070478 | G95: 3197002107 | H95: 1280 | I95: F | J95: 15293 | L95: 0 | M95: 0 | N95: 1 | O95: 4 | P95: 26.88 | Q95: 50 | R95: FCA Nis | S95: Hand & Carry | T95: W_34798 | U95: JENA | V95: Mexico | W95: CS000008302 | X95: H&C | AC95: 249
A96: 45903 | B96: 45903 | C96: 36 | D96: 1663-5YY0318EN | F96: 2910070497 | G96: 1197004412 | H96: 2016 | I96: C | J96: 15294C | L96: 1032.34 | M96: 0.51207341 | N96: 1 | O96: 12 | P96: 53.43 | Q96: 123 | R96: CPT ALTAMIRA | S96: E-17670 | T96: W_34798 | U96: JENA | V96: Mexico | W96: CS000008283 | X96: avio | AC96: 250
A97: 45903 | B97: 45903 | C97: 36 | D97: 1663-5YY0318EN | F97: 2910070498 | G97: 3197002109 | H97: 2016 | I97: C | J97: 15295C | L97: 1032.34 | M97: 0.51207341 | N97: 1 | O97: 12 | P97: 53.43 | Q97: 124 | R97: CPT ALTAMIRA | S97: E-17670 | T97: W_34798 | U97: JENA | V97: Mexico | W97: CS000008283 | X97: avio | AC97: 250
A98: 45905 | B98: 45909 | C98: 36 | D98: 1663-5YY0247EN/RS | F98: 2910070549 | G98: 3197002061 | H98: 4320 | I98: B | J98: 15336C | L98: 3925.62 | M98: 0.90870833 | N98: 3 | O98: 30 | P98: 311.04 | Q98: 511 | R98: CPT ALTAMIRA | S98: E-17649 | T98: W_34798 | U98: JENA | V98: Mexico | X98: MSNU1899061 | AC98: 251
A99: 45905 | B99: 45909 | C99: 36 | D99: 1663-5YY0262EN/RS | F99: 2910070550 | G99: 3197002093 | H99: 1728 | I99: A | J99: 15337C | L99: 1687.19 | M99: 0.9763831 | N99: 1 | O99: 12 | P99: 143.42 | Q99: 210.76 | R99: CPT ALTAMIRA | S99: E-17649 | T99: W_34798 | U99: JENA | V99: Mexico | X99: MSNU1899061 | AC99: 251
A100: 45905 | B100: 45909 | C100: 36 | D100: 1663-5YY0321EN | F100: 2910070551 | G100: 3197002075 | H100: 2016 | I100: C | J100: 15338C | L100: 1072.75 | M100: 0.53211806 | N100: 1 | O100: 12 | P100: 56.45 | Q100: 141 | R100: CPT ALTAMIRA | S100: E-17649 | T100: W_34798 | U100: JENA | V100: Mexico | X100: MSNU1899061 | AC100: 251
A101: 45905 | B101: 45909 | C101: 36 | D101: 1663-5YY0321EN | F101: 2910070552 | G101: 3197002078 | H101: 1818 | I101: C | J101: 15339C | L101: 993.3 | M101: 0.54636964 | N101: 1 | O101: 11 | P101: 50.9 | Q101: 115 | R101: CPT ALTAMIRA | S101: E-17649 | T101: W_34798 | U101: JENA | V101: Mexico | X101: MSNU1899061 | AC101: 251
A102: 45905 | B102: 45905 | C102: 36 | D102: 1663-5YY0294-H01 | F102: 2910070582 | G102: 3197002106 | H102: 6106 | I102: F | J102: 15354C | L102: 3858.39 | M102: 0.63190141 | N102: 2 | O102: 20 | P102: 128.23 | Q102: 273 | R102: CPT ALTAMIRA | S102: E-17694 | T102: W_34798 | U102: JENA | V102: Mexico | W102: CS000008311 | X102: avio | AC102: 252
A103: 45905 | B103: 45905 | C103: 36 | D103: 1663-1120026EN | F103: 2910070583 | G103: 3237000001 | H103: 1260 | I103: E | J103: 15355C | L103: 425.47 | M103: 0.3376746 | N103: 1 | O103: 4 | P103: 0 | Q103: 57 | R103: CPT ALTAMIRA | S103: E-17694 | T103: W_34798 | U103: JENA | V103: Mexico | X103: avio | AC103: 252
A104: 45910 | B104: 45910 | C104: 37 | D104: 1663-1120026EN | F104: 2910070657 | G104: 3237000001 | H104: 840 | I104: E | J104: 15385C | L104: 1636.86 | M104: 1.9486429 | N104: 1 | O104: 3 | P104: 0 | Q104: 45 | R104: CPT ALTAMIRA | S104: E-17712 | T104: W_34798 | U104: JENA | V104: Mexico | X104: avio | AC104: 253
A105: 45911 | B105: 45911 | C105: 37 | D105: 1663-5YY0318EN | F105: 2910070707 | G105: 3197002087 | H105: 2016 | I105: C | J105: 15396C | L105: 2910.46 | M105: 1.4436806 | N105: 1 | O105: 12 | P105: 53.43 | Q105: 123.6 | R105: CPT ALTAMIRA | S105: E-17728 | T105: W_34798 | U105: JENA | V105: Mexico | W105: CS000008283 | X105: avio | AC105: 254
A106: 45911 | B106: 45911 | C106: 37 | D106: 1663-5YY0318EN | F106: 2910070708 | G106: 1197004450 | H106: 2016 | I106: C | J106: 15397C | L106: 2910.46 | M106: 1.4436806 | N106: 1 | O106: 12 | P106: 53.43 | Q106: 123 | R106: CPT ALTAMIRA | S106: E-17728 | T106: W_34798 | U106: JENA | V106: Mexico | W106: CS000008283 | X106: avio | AC106: 254
A107: 45915 | B107: 45915 | C107: 38 | D107: 1663-5YY0257-H02 | F107: 2910070771 | G107: 3197002091 | H107: 2264 | I107: H | J107: 15420C | L107: 1283.95 | M107: 0.56711572 | N107: 1 | O107: 8 | P107: 49.81 | Q107: 105 | R107: CPT ALTAMIRA | S107: E-17738 | T107: W_34798 | U107: JENA | V107: Mexico | W107: CS000008357 | X107: avio | AC107: 255
A108: 45915 | B108: 45915 | C108: 38 | D108: 1663-5YY0274EN | F108: 2910070772 | G108: 3197002100 | H108: 4224 | I108: H | J108: 15422C | L108: 3874.03 | M108: 0.91714725 | N108: 2 | O108: 24 | P108: 160.51 | Q108: 325 | R108: CPT ALTAMIRA | S108: E-17738 | T108: W_34798 | U108: JENA | V108: Mexico | W108: CS000008358 | X108: avio | AC108: 255
A109: 45915 | B109: 45915 | C109: 38 | D109: 1663-5YY0271EN | F109: 2910070773 | G109: 3197002151 | H109: 2112 | I109: G | J109: 15421C | L109: 1937.02 | M109: 0.91714962 | N109: 1 | O109: 12 | P109: 80.26 | Q109: 165 | R109: CPT ALTAMIRA | S109: E-17738 | T109: W_34798 | U109: JENA | V109: Mexico | W109: CS000008365 | X109: avio | AC109: 255
A110: 45916 | B110: 45916 | C110: 38 | D110: 1663-5YY0294-H01 | F110: 2910070797 | G110: 3197002086 | H110: 7680 | I110: F | J110: 15432C | L110: 1765.44 | M110: 0.229875 | N110: 2 | O110: 24 | P110: 161.28 | Q110: 339.92 | R110: CPT ALTAMIRA | S110: E-17688 | T110: W_34798 | U110: JENA | V110: Mexico | X110: MSBU7017121 | AC110: 256
A111: 45916 | B111: 45916 | C111: 38 | D111: 1663-5YY0294-H01 | F111: 2910070798 | G111: 3197002107 | H111: 3840 | I111: F | J111: 15433C | L111: 882.72 | M111: 0.229875 | N111: 1 | O111: 12 | P111: 80.64 | Q111: 177 | R111: CPT ALTAMIRA | S111: E-17688 | T111: W_34798 | U111: JENA | V111: Mexico | X111: MSBU7017121 | AC111: 256
A112: 45916 | B112: 45916 | C112: 38 | D112: 1663-5YY0294-H01 | F112: 2910070799 | G112: 1197004443 | H112: 1752 | I112: F | J112: 15434C | L112: 487.96 | M112: 0.27851598 | N112: 1 | O112: 6 | P112: 36.79 | Q112: 93.95 | R112: CPT ALTAMIRA | S112: E-17688 | T112: W_34798 | U112: JENA | V112: Mexico | X112: MSBU7017121 | AC112: 256
A113: 45916 | B113: 45916 | C113: 38 | D113: 1663-5YY0268-H02 | F113: 2910070800 | G113: 3197002165 | H113: 2016 | I113: H | J113: 15430C | L113: 686.9 | M113: 0.34072421 | N113: 1 | O113: 12 | P113: 54.43 | Q113: 132.26 | R113: CPT ALTAMIRA | S113: E-17688 | T113: W_34798 | U113: JENA | V113: Mexico | X113: MSBU7017121 | AC113: 256
A114: 45916 | B114: 45916 | C114: 38 | D114: 1663-5YY0274EN | F114: 2910070801 | G114: 3197002082 | H114: 2112 | I114: H | J114: 15426C | L114: 939.93 | M114: 0.44504261 | N114: 1 | O114: 12 | P114: 80.26 | Q114: 180.98 | R114: CPT ALTAMIRA | S114: E-17688 | T114: W_34798 | U114: JENA | V114: Mexico | X114: MSBU7017121 | AC114: 256
A115: 45916 | B115: 45916 | C115: 38 | D115: 1663-5YY0318EN | F115: 2910070802 | G115: 3197002177 | H115: 1036 | I115: C | J115: 15427C | L115: 465.12 | M115: 0.44895753 | N115: 1 | O115: 7 | P115: 27.46 | Q115: 89.55 | R115: CPT ALTAMIRA | S115: E-17688 | T115: W_34798 | U115: JENA | V115: Mexico | X115: MSBU7017121 | AC115: 256
A116: 45916 | B116: 45916 | C116: 38 | D116: 1663-5YY0333EN | F116: 2910070803 | G116: 3197002089 | H116: 3840 | I116: C | J116: 15428C | L116: 890.82 | M116: 0.23198438 | N116: 1 | O116: 12 | P116: 76.8 | Q116: 167 | R116: CPT ALTAMIRA | S116: E-17688 | T116: W_34798 | U116: JENA | V116: Mexico | X116: MSBU7017121 | AC116: 256
A117: 45916 | B117: 45916 | C117: 38 | D117: 1663-5YY0371EN | F117: 2910070804 | G117: 3197002050 | H117: 3840 | I117: C | J117: 15429C | L117: 891.07 | M117: 0.23204948 | N117: 1 | O117: 12 | P117: 80.64 | Q117: 171.57 | R117: CPT ALTAMIRA | S117: E-17688 | T117: W_34798 | U117: JENA | V117: Mexico | X117: MSBU7017121 | AC117: 256
A118: 45916 | B118: 45916 | C118: 38 | D118: 1663-5YY0296EN | F118: 2910070805 | G118: 3197002108 | H118: 2112 | I118: E | J118: 15431C | L118: 1034.42 | M118: 0.4897822 | N118: 1 | O118: 12 | P118: 82.37 | Q118: 180 | R118: CPT ALTAMIRA | S118: E-17688 | T118: W_34798 | U118: JENA | V118: Mexico | X118: MSBU7017121 | AC118: 256
A119: 45919 | B119: 45919 | C119: 38 | D119: 1663-5YY0271EN | F119: 2910070925 | G119: 3197002145 | H119: 2112 | I119: G | J119: 15508C | L119: 6643.73 | M119: 3.1457055 | N119: 1 | O119: 12 | P119: 80.26 | Q119: 160 | R119: CPT ALTAMIRA | S119: E-17774 | T119: W_34798 | U119: JENA | V119: Mexico | W119: CS000008365 | X119: avio | AC119: 258
A120: 45919 | B120: 45919 | C120: 38 | D120: 1663-1E90059EN | F120: 2910070935 | G120: 3237000006 | H120: 600 | I120: F | J120: 15510C | L120: 6711.75 | M120: 11.18625 | N120: 1 | O120: 1 | P120: 0 | Q120: 9.5 | R120: CPT ALTAMIRA | S120: E-17769 | T120: W_34798 | U120: JENA | V120: Mexico | W120: CS000008398H&C | X120: H&C | AC120: 259
A121: 45919 | B121: 45919 | C121: 38 | D121: 1663-1E90059EN | F121: 2910070936 | G121: 3237000006 | H121: 400 | I121: F | J121: 15512C | L121: 0 | M121: 0 | N121: 1 | O121: 1 | P121: 0 | Q121: 6.3 | R121: CPT ALTAMIRA | S121: E-17769 | T121: W_34798 | U121: JENA | V121: Mexico | W121: CS000008398H&C | X121: H&C | AC121: 259
A122: 45924 | B122: 45924 | C122: 39 | D122: 1663-5YY0284EN | F122: 2910070986 | G122: 3197002094 | H122: 2016 | I122: D | J122: 15522C | L122: 2948.64 | M122: 1.462619 | N122: 1 | O122: 12 | P122: 42.34 | Q122: 128 | R122: CPT ALTAMIRA | S122: E-17791 | T122: W_34798 | U122: JENA | V122: Mexico | W122: CS000008366 | X122: avio | AC122: 260
A123: 45926 | B123: 45929 | C123: 39 | D123: 1663-5YY0194-MTEN/RS | F123: 2910071088 | G123: 3197002097 | H123: 2592 | I123: D | J123: 15586C | L123: 755.82 | M123: 0.29159722 | N123: 2 | O123: 24 | P123: 189.22 | Q123: 323.9 | R123: CPT ALTAMIRA | S123: E-17765 | T123: W_34798 | U123: JENA | V123: Mexico | X123: MSMU7392445 | AC123: 261
A124: 45926 | B124: 45929 | C124: 39 | D124: 1663-5YY0294-H01 | F124: 2910071089 | G124: 1197004443 | H124: 3840 | I124: F | J124: 15587C | L124: 396.61 | M124: 0.10328385 | N124: 1 | O124: 12 | P124: 80.64 | Q124: 177 | R124: CPT ALTAMIRA | S124: E-17765 | T124: W_34798 | U124: JENA | V124: Mexico | X124: MSMU7392445 | AC124: 261
A125: 45926 | B125: 45929 | C125: 39 | D125: 1663-5YY0294-H01 | F125: 2910071090 | G125: 3197002192 | H125: 7680 | I125: F | J125: 15588C | L125: 793.21 | M125: 0.10328255 | N125: 2 | O125: 24 | P125: 161.28 | Q125: 354 | R125: CPT ALTAMIRA | S125: E-17765 | T125: W_34798 | U125: JENA | V125: Mexico | X125: MSMU7392445 | AC125: 261
A126: 45926 | B126: 45929 | C126: 39 | D126: 1663-5YY0247EN/RS | F126: 2910071091 | G126: 3197002063 | H126: 1728 | I126: B | J126: 15590C | L126: 447.47 | M126: 0.25895255 | N126: 1 | O126: 12 | P126: 124.42 | Q126: 201 | R126: CPT ALTAMIRA | S126: E-17765 | T126: W_34798 | U126: JENA | V126: Mexico | X126: MSMU7392445 | AC126: 261
...

Sheet SPG
A1: PFA # | B1: Item Code | C1: Item Description | D1: FG | E1: JE Zac. Customer | F1: PFA Cost | G1: Cuenta | H1: BU | P1: EUROPARTNERS
A2: CS000009338 | B2: 1663-5YY0333ENNV00 | C2: PCBA | D2: 1999-5YY1255EN | E2: JE Springfield | F2: 11000 | G2: 67180000 | H2: M19 | J2: 9338 | P2: TRINITY LOGISTICS
A3: CS000009271 | B3: 1663-5YY0196EN | C3: PCBA | D3: 1999-5YY0937EN | E3: JE Springfield | F3: 600 | G3: 67180000 | H3: M19 | P3: CH ROBINSON
A4: CS000009270 | B4: 1663-5YY0294-H01 | C4: PCBA | D4: 1905-5YY0792AN | E4: GM | F4: 23500 | G4: 67180000 | H4: M19 | P4: TRANSCONTINENTAL TDS
F5: =SUM(F2:F4) -> 35100 | P5: MEXPROUD
P6: ALLIANCESHARE
P7: FERENS
P8: ALOW
F9: 20000 | P9: DSV
F10: =F2+F3 -> 11600 | P10: SOLUTIONS CARGO
F11: =F9-F10 -> 8400 | P11: ROYALE INTERNATIONAL
P12: AERO WORLDWIDE
P13: GRAND AIR
P14: ADIONE
P15: DICEX INTERNATIONAL

Sheet Explicaciones Feb 
A1: Inbound: | K1: 178204
B2: Import Freight by Sea | F2: Premium Inbound Freight | K2: 54127.77
A3: Purchase Invoices | B3: 260255.19 | C3: Zacatecas | E3: Purchase Invoices | F3: -2314.81 | G3: Zacatecas | K3: =SUM(K1:K2) -> 232331.77
B4: 57931.99 | C4: China | F4: 79577.28 | G4: China | K4: =K3-F9 -> 16414.55
B5: 30045.75 | C5: Niss | F5: 54127.77 | G5: Niss | H5: Estos cobros de Niss se debe verificar que si es a nuestro cargo y que se le debe cobrar a SPG por el alza de la demanda de cliente.
B6: =SUM(B3:B5) -> 348232.93 | F6: =SUM(F3:F5) -> 131390.24
A7: Reversa | B7: 231546.85 | E7: Reversa | F7: 224287.24
A8: Provision | B8: 329830.83 | C8: En esta provisión se incluyen $63,220.00 de la compra de las maquinas a China de AS/Responsables Niaz y Eduardo | E8: Provision | F8: 308814.22 | H8: En esta provisión estan $65,938.00 que se le deben cobrar a ABC, pero hasta tener el cobro por parte de China.
A9: TOTAL CTA | B9: =B6-B7+B8 -> 446516.91 | C9: Se liberaron 63 contenedores. | E9: TOTAL CTA | F9: =F6-F7+F8 -> 215917.22
A11: Outbound:
B12: Freight by Land | F12: Freight by Air
A13: Purchase Invoices | B13: 145157.76 | C13: Zacatecas | E13: Purchase Invoices | F13: 18599.88 | G13: Zacatecas | H13: $17,691.32 en cobros por envios Proyectos de mas de 100 kilos porque DHL cobro por peso volumetrico.
B14: 1045.79 | C14: SPG | F14: 4180.8 | G14: China
B15: =SUM(B13:B14) -> 146203.55 | F15: =SUM(F13:F14) -> 22780.68
A16: Charge back SPG | B16: 27442 | C16: En el charge back con SPG solo se estan cobrando 7 cajas de 12 que se deben estar cobrando por mes
A17: Reversa | B17: 107774.52 | E17: Reversa | F17: 6876.39
A18: Provision | B18: 122398.2 | E18: Provision | F18: 16504.33 | H18: $7,945.22 en provisión por envios de Proyectos de mas de 100 kilos porque DHL cobrara por peso volumetrico
A19: TOTAL CTA | B19: =(B15-B16-B17+B18) -> 133385.23 | E19: TOTAL CTA | F19: =(F15-F17+F18) -> 32408.62
B21: 135000
B22: =B21-B19 -> 1614.77

Sheet Explicaciones Mar
A1: Inbound:
B2: Import Freight by Sea | F2: Premium Inbound Freight
A3: Purchase Invoices | B3: 325578.19 | C3: Zacatecas /$57,427.58 Proyectos | E3: Purchase Invoices | F3: 40835.92 | G3: Zacatecas
B4: 181768.26 | C4: China Intercompany | F4: 97508.44 | G4: China | H4: $17,670.40 de Proyectos PFA 9482
B5: 30534.83 | C5: Niss | F5: 66305.21 | G5: Niss | H5: En este mes Niss volvio a cargar en automatico al sistema sin indicar PFA ni nada $44,616.86, lo que suma de febrero a marzo $98,744.63 que debe regresar.
B6: 4301 | C6: Murten
B7: =SUM(B3:B6) -> 542182.28 | F7: =SUM(F3:F5) -> 204649.57
A8: Reversa | B8: 329830.83 | E8: Reversa | F8: 308814.22
E9: Charge back ABC | F9: 31372.8
E10: Charge back SPG | F10: 11600
A11: Provision | B11: 271456.52 | C11: $84,491 son de Proyectos lo que hace un total de $141,918.58 el total que corresponde a Proyectos quedando solo $341,889.39 de gasto en materiales. | E11: Provision | F11: 249575.8 | H11: Se gastaron en el mes $53,054.80 y esta en el gasto PFA´s de proyectos que no se capitalizaron por falta de Capex por un monto total de $43,323.00 PFA 9609
A12: TOTAL CTA | B12: =B7-B8+B11 -> 483807.97 | C12: Se liberaron 89 contenedores. | E12: TOTAL CTA | F12: =F7+F11-F8-F9-F10 -> 102438.35
F15: 102

Sheet PFA NISS
A1: Customer/Vendor | B1: Invoice NO. | C1: Invoice Date | D1: Posted Date | E1: Curr | F1: Func Total | L1: PORT | M1: DISPATCH | N1: CONTENEDOR | O1: DESPACHO | P1: E.T.A ZAC | Q1: COMMENTS | R1: REFERENCIA
A2: JOHNSON ELECTRIC DOO NIS | B2: 291500018921 | C2: 46080 | D2: 46081 | E2: USD | F2: 2290 | G2: CS000009531 | H2: BRAZIL | L2: IMP-MZO | M2: SABADO 21 SSA | N2: CAAU8734885 | O2: SOLMAR | P2: 46104 | Q2: UNLOADED 03/23 | R2: AF-M-106-SI26-M46 | S2: =VLOOKUP(R2,'[2]PROVISION MARZO 2026'!$A:$AU,47,0) -> ABIERTO
A3: JOHNSON ELECTRIC DOO NIS | B3: 291500018920 | C3: 46080 | D3: 46081 | E3: USD | F3: 2290 | G3: CS000009531 | H3: BRAZIL | L3: IMP-MZO | M3: SABADO 21 SSA | N3: CAIU4417756 | O3: SOLMAR | P3: 46104 | Q3: UNLOADED 03/23 | R3: AF-M-098-SI26-M46 | S3: =VLOOKUP(R3,'[2]PROVISION MARZO 2026'!$A:$AU,47,0) -> ABIERTO
A4: JOHNSON ELECTRIC DOO NIS | B4: 291500018676 | C4: 46073 | D4: 46081 | E4: USD | F4: 5890.4 | G4: CS000009529 | H4: SPG | L4: IMP-MZO | M4: SABADO 21 SSA | N4: CAAU7765834 | O4: SOLMAR | P4: 46104 | Q4: UNLOADED 03/23 | R4: AF-M-099-SI26-M46 | S4: =VLOOKUP(R4,'[2]PROVISION MARZO 2026'!$A:$AU,47,0) -> ABIERTO
A5: JOHNSON ELECTRIC DOO NIS | B5: 291500018675 | C5: 46073 | D5: 46081 | E5: USD | F5: 2945.2 | G5: CS000009529 | H5: SPG | L5: IMP-MZO | M5: LUNES 23 SSA | N5: CAAU8743568 | O5: MEX | P5: 46105 | Q5: ETA 09:00 HRS | R5: AF-M-114-SI26-M46 | S5: =VLOOKUP(R5,'[2]PROVISION MARZO 2026'!$A:$AU,47,0) -> ABIERTO
A6: JOHNSON ELECTRIC DOO NIS | B6: 291500018674 | C6: 46073 | D6: 46081 | E6: USD | F6: 6134.39 | G6: CS000009530 | H6: ZAC | L6: IMP-MZO | M6: LUNES 23 SSA | N6: JXLU6406640 | O6: MEX | P6: 46105 | Q6: ETA 09:00 HRS | R6: AF-M-113-SI26-M46 | S6: =VLOOKUP(R6,'[2]PROVISION MARZO 2026'!$A:$AU,47,0) -> ABIERTO
A7: JOHNSON ELECTRIC DOO NIS | B7: 291500018501 | C7: 46066 | D7: 46081 | E7: USD | F7: 2917.06 | G7: CS000009529 | H7: SPG | L7: IMP-MZO | M7: LUNES 23 SSA | N7: JXLU6464673 | O7: MEX | P7: 46105 | Q7: ETA 06:00 HRS | R7: AF-M-115-SI26-M46 | S7: =VLOOKUP(R7,'[2]PROVISION MARZO 2026'!$A:$AU,47,0) -> ABIERTO
A8: JOHNSON ELECTRIC DOO NIS | B8: 291500018500 | C8: 46066 | D8: 46081 | E8: USD | F8: 5834.13 | G8: CS000009529 | H8: SPG | L8: IMP-MZO | M8: LUNES 23 SSA | N8: ZCSU7435480 | O8: MEX | P8: 46105 | Q8: ETA 06:00 HRS | R8: AF-M-116-SI26-M46 | S8: =VLOOKUP(R8,'[2]PROVISION MARZO 2026'!$A:$AU,47,0) -> ABIERTO
A9: JOHNSON ELECTRIC DOO NIS | B9: 291500018499 | C9: 46066 | D9: 46081 | E9: USD | F9: 6075.79 | G9: CS000009530 | H9: ZAC | L9: IMP-MZO | M9: LUNES 23 SSA SENCILLO | N9: TLNU2006850 | O9: MEX | P9: 46105 | Q9: ETA 12:00 HRS | R9: AF-M-117-SI26-M46 | S9: =VLOOKUP(R9,'[2]PROVISION MARZO 2026'!$A:$AU,47,0) -> ABIERTO
A10: JOHNSON ELECTRIC DOO NIS | B10: 291500018233 | C10: 46062 | D10: 46081 | E10: USD | F10: 5688.24 | G10: CS000009270 | H10: Niss | L10: IMP-MZO | M10: LUNES 23 SSA SOLMAR 14 | N10: JXLU6251750 | O10: SOLMAR | P10: 46105 | Q10: ETA 15:00 HRS | R10: AF-M-120-SI26-M46 | S10: =VLOOKUP(R10,'[2]PROVISION MARZO 2026'!$A:$AU,47,0) -> ABIERTO
A11: JOHNSON ELECTRIC DOO NIS | B11: 291500018232 | C11: 46062 | D11: 46081 | E11: USD | F11: 805.04 | G11: CS000009271 | H11: Niss | L11: IMP-MZO | M11: LUNES 23 SSA SOLMAR 14 | N11: GAOU6435070 | O11: SOLMAR | P11: 46105 | Q11: ETA 15:00 HRS | R11: AF-M-121-SI26-M46 | S11: =VLOOKUP(R11,'[2]PROVISION MARZO 2026'!$A:$AU,47,0) -> ABIERTO
A12: JOHNSON ELECTRIC DOO NIS | B12: 291500018231 | C12: 46062 | D12: 46081 | E12: USD | F12: 2536.89 | G12: CS000009272 | H12: Niss | L12: IMP-MZO | M12: LUNES 23 SSA SOLMAR 14 | N12: ZCSU6946192 | O12: SOLMAR | P12: 46105 | Q12: ETA 16:00 HRS | R12: AF-M-122-SI26-M46 | S12: =VLOOKUP(R12,'[2]PROVISION MARZO 2026'!$A:$AU,47,0) -> ABIERTO
A13: JOHNSON ELECTRIC DOO NIS | B13: 291500018103 | C13: 46057 | D13: 46081 | E13: USD | F13: 2680.16 | G13: CS000009270 | H13: Niss | L13: IMP-MZO | M13: LUNES 23 SSA SOLMAR 14 | N13: CAAU6868967 | O13: SOLMAR | P13: 46105 | Q13: ETA 22:00 HRS | R13: AF-M-123-SI26-M46 | S13: =VLOOKUP(R13,'[2]PROVISION MARZO 2026'!$A:$AU,47,0) -> ABIERTO
A14: JOHNSON ELECTRIC DOO NIS | B14: 291500018102 | C14: 46057 | D14: 46081 | E14: USD | F14: 5360.31 | G14: CS000009270 | H14: Niss | L14: IMP-MZO | M14: LUNES 23 SSA SOLMAR 9 AM | N14: GOSU1040487 | O14: 46104 | P14: 46106 | Q14: Depending on the unloading | R14: AF-M-124-SI26-M46 | S14: =VLOOKUP(R14,'[2]PROVISION MARZO 2026'!$A:$AU,47,0) -> ABIERTO
A15: JOHNSON ELECTRIC DOO NIS | B15: 291500018101 | C15: 46057 | D15: 46081 | E15: USD | F15: 2680.16 | G15: CS000009270 | H15: Niss | L15: IMP-MZO | M15: LUNES 23 SSA SOLMAR 9 AM | N15: ZCSU7370882 | O15: 46104 | P15: 46106 | Q15: Depending on the unloading | R15: AF-M-125-SI26-M46 | S15: =VLOOKUP(R15,'[2]PROVISION MARZO 2026'!$A:$AU,47,0) -> ABIERTO
A16: JOHNSON ELECTRIC DOO NIS | B16: 291500019291 | C16: 46091 | D16: 46093 | E16: USD | F16: 4773.68 | L16: IMP-MZO | M16: LUNES 23 SSA SOLMAR 13 | N16: TGBU7246054 | O16: 46104 | P16: 46106 | Q16: Depending on the unloading | R16: AF-M-126-SI26-M46 | S16: =VLOOKUP(R16,'[2]PROVISION MARZO 2026'!$A:$AU,47,0) -> ABIERTO
A17: JOHNSON ELECTRIC DOO NIS | B17: 291500019290 | C17: 46091 | D17: 46093 | E17: USD | F17: 7160.52 | L17: IMP-MZO | M17: LUNES 23 SSA SOLMAR 13 | N17: TGBU7088010 | O17: 46104 | P17: 46106 | Q17: Depending on the unloading | R17: AF-M-127-SI26-M46 | S17: =VLOOKUP(R17,'[2]PROVISION MARZO 2026'!$A:$AU,47,0) -> ABIERTO
A18: JOHNSON ELECTRIC DOO NIS | B18: 291500019289 | C18: 46091 | D18: 46093 | E18: USD | F18: 2115.54 | L18: IMP-MZO | M18: MARTES 24 SOLMAR 12 PM | N18: ZCSU6722145 | O18: 46105 | P18: 46106 | Q18: Depending on the unloading | R18: AF-M-108-SI26-M46 | S18: =VLOOKUP(R18,'[2]PROVISION MARZO 2026'!$A:$AU,47,0) -> ABIERTO
A19: JOHNSON ELECTRIC DOO NIS | B19: 291500019288 | C19: 46091 | D19: 46093 | E19: USD | F19: 4231.08 | L19: IMP-MZO | M19: MARTES 24 SOLMAR 12 PM | N19: ZCSU7975826 | O19: 46105 | P19: 46106 | Q19: Depending on the unloading | R19: AF-M-109-SI26-M46 | S19: =VLOOKUP(R19,'[2]PROVISION MARZO 2026'!$A:$AU,47,0) -> ABIERTO
A20: JOHNSON ELECTRIC DOO NIS | B20: 291500019287 | C20: 46091 | D20: 46093 | E20: USD | F20: 2115.54 | L20: IMP-MZO | M20: MARTES 24 SSA SOLMAR 11 AM | N20: ZCSU7903873 | O20: 46105 | P20: 46106 | Q20: Depending on the unloading | R20: AF-M-110-SI26-M46 | S20: =VLOOKUP(R20,'[2]PROVISION MARZO 2026'!$A:$AU,47,0) -> ABIERTO
A21: JOHNSON ELECTRIC DOO NIS | B21: 291500019286 | C21: 46091 | D21: 46093 | E21: USD | F21: 1969.16 | L21: IMP-MZO | M21: MARTES 24 SSA SOLMAR 11 AM | N21: JXLU4460299 | O21: 46105 | P21: 46106 | Q21: Depending on the unloading | R21: AF-M-111-SI26-M46 | S21: =VLOOKUP(R21,'[2]PROVISION MARZO 2026'!$A:$AU,47,0) -> ABIERTO
A22: JOHNSON ELECTRIC DOO NIS | B22: 291500019059 | C22: 46084 | D22: 46093 | E22: USD | F22: 3188 | L22: IMP-MZO | M22: MIERCOLES 25 SSA SOLMAR 6 AM | N22: JXLU6186187 | O22: 46106 | P22: 46107 | Q22: Depending on the unloading | R22: AF-M-100-SI26-M46 | S22: =VLOOKUP(R22,'[2]PROVISION MARZO 2026'!$A:$AU,47,0) -> ABIERTO
A23: JOHNSON ELECTRIC DOO NIS | B23: 291500019058 | C23: 46084 | D23: 46093 | E23: USD | F23: 5934.83 | L23: IMP-MZO | M23: MARTES 24 SOLMAR SENCILLO 12 PM | N23: ZIMU3033558 | O23: 46105 | P23: 46107 | Q23: Depending on the unloading | R23: AF-M-112-SI26-M46 | S23: =VLOOKUP(R23,'[2]PROVISION MARZO 2026'!$A:$AU,47,0) -> #N/A
A24: JOHNSON ELECTRIC DOO NIS | B24: 291500019057 | C24: 46084 | D24: 46093 | E24: USD | F24: 5934.83 | L24: IMP-MZO | M24: MIERCOLES 25 SSA SOLMAR 6 AM | N24: ZCSU7665899 | O24: 46106 | P24: 46107 | Q24: Depending on the unloading | R24: AF-M-118-SI26-M46 | S24: =VLOOKUP(R24,'[2]PROVISION MARZO 2026'!$A:$AU,47,0) -> #N/A
A25: JOHNSON ELECTRIC DOO NIS | B25: 291500019056 | C25: 46084 | D25: 46093 | E25: USD | F25: 3596.84 | L25: IMP-MZO | M25: MARTES 24 SENCILLO SOLMAR | N25: CAAU5455552 | O25: 46105 | P25: 46107 | Q25: Depending on the unloading | R25: AF-M-119-SI26-M46 | S25: =VLOOKUP(R25,'[2]PROVISION MARZO 2026'!$A:$AU,47,0) -> #N/A
A26: JOHNSON ELECTRIC DOO NIS | B26: 291500019055 | C26: 46084 | D26: 46093 | E26: USD | F26: 3596.84 | L26: IMP-MZO | M26: MIERCOLES 25 SSA SOLMAR 9 AM | N26: JXLU4463750 | O26: 46106 | P26: 46107 | Q26: Depending on the unloading | R26: AF-M-128-SI26-M46 | S26: =VLOOKUP(R26,'[2]PROVISION MARZO 2026'!$A:$AU,47,0) -> #N/A
F27: =SUM(F2:F26) -> 98744.63 | L27: IMP-MZO | M27: MIERCOLES 25 SSA SOLMAR 9 AM | N27: BMOU4503941 | O27: 46106 | P27: 46107 | Q27: Depending on the unloading | R27: AF-M-129-SI26-M46 | S27: =VLOOKUP(R27,'[2]PROVISION MARZO 2026'!$A:$AU,47,0) -> #N/A
A28: JOHNSON ELECTRIC DOO NIS | B28: 20714 | C28: 46080 | D28: 46106 | E28: EUR | F28: 21688.35 | L28: IMP-MZO | M28: MIERCOLES 25 SSA SOLMAR 12 AM | N28: ZCSU6901623 | O28: 46106 | P28: 46107 | Q28: Depending on the unloading | R28: AF-M-101-SI26-M46 | S28: =VLOOKUP(R28,'[2]PROVISION MARZO 2026'!$A:$AU,47,0) -> #N/A
L29: IMP-MZO | M29: MIERCOLES 25 SSA SOLMAR 11 AM | N29: TCNU5546561 | O29: 46106 | P29: 46107 | Q29: Depending on the unloading | R29: AF-M-105-SI26-M46 | S29: =VLOOKUP(R29,'[2]PROVISION MARZO 2026'!$A:$AU,47,0) -> #N/A
L30: IMP-MZO | M30: MIERCOLES 25 SSA SOLMAR 11 AM | N30: ZCSU7700599 | O30: 46106 | P30: 46108 | Q30: Depending on the unloading | R30: AF-M-107-SI26-M46 | S30: =VLOOKUP(R30,'[2]PROVISION MARZO 2026'!$A:$AU,47,0) -> #N/A
L31: IMP-MZO | M31: MIERCOLES 25 SSA SOLMAR 9 AM | N31: ZCSU7234783 | O31: 46106 | P31: 46108 | Q31: Depending on the unloading | R31: AF-M-102-SI26-M46 | S31: =VLOOKUP(R31,'[2]PROVISION MARZO 2026'!$A:$AU,47,0) -> #N/A
L32: IMP-MZO | M32: MIERCOLES 25 SSA SOLMAR 9 AM SENCILLO | N32: ZCSU7105575 | O32: 46106 | P32: 46108 | Q32: Depending on the unloading | R32: AF-M-103-SI26-M46 | S32: =VLOOKUP(R32,'[2]PROVISION MARZO 2026'!$A:$AU,47,0) -> #N/A
L33: IMP-MZO | M33: MIERCOLES 25 SSA SOLMAR 9 AM | N33: JXLU6440603 | O33: 46106 | P33: 46108 | Q33: Depending on the unloading | R33: AF-M-104-SI26-M46 | S33: =VLOOKUP(R33,'[2]PROVISION MARZO 2026'!$A:$AU,47,0) -> #N/A
G35: E-18601 | H35: CS000009614, CS000009615, CS000009647
G41: E-18568 | H41: CS000009612, CS000009614, CS000009615
A50: PN | B50: REV | C50: Total Pll | D50: Quantity | E50: Gross weight | F50: DN number | G50: ORACLE ORDER | H50: Invoice number | I50: Freight cost | J50: PFA | K50: Shipment
A51: 1663-5YY0250ENNV00 | B51: G | C51: 2 | D51: 4224 | E51: 326 | F51: 2910074359 | G51: 3197002494 | H51: 18663C | I51: 6134.39 | J51: CS000009529 | K51: E-18516 | L51: Americas: APG- PC- Springfield
A52: 1663-5YY0294ENNV00 | B52: F | C52: 1 | D52: 3840 | E52: 162 | F52: 2910074360 | G52: 3197002465 | H52: 18662C | I52: 2945.2 | J52: CS000009530 | K52: E-18516 | L52: Americas: APG PC MEXICO | M52: Cobrarle a Niss
A53: 1663-5YY0294ENNV00 | B53: F | C53: 2 | D53: 7680 | E53: 327 | F53: 2910074361 | G53: 3197002495 | H53: 18661C | I53: 5890.4 | J53: CS000009530 | K53: E-18516 | L53: Americas: APG PC MEXICO | M53: Cobrarle a Niss
A54: 1663-5YY0250ENNV00 | B54: G | C54: 2 | D54: 4224 | E54: 321 | F54: 2910074187 | G54: 3197002504 | H54: 18436C | I54: 6075.79 | J54: CS000009529 | K54: E-18489 | L54: Americas: APG- PC- Springfield
A55: 1663-5YY0294ENNV00 | B55: F | C55: 2 | D55: 7680 | E55: 327 | F55: 2910074188 | G55: 3197002499 | H55: 18434C | I55: 5834.13 | J55: CS000009530 | K55: E-18489 | L55: Americas: APG PC MEXICO | M55: Cobrarle a Niss
A56: 1663-5YY0294ENNV00 | B56: F | C56: 1 | D56: 3520 | E56: 153 | F56: 2910074055 | G56: 3197002464 | H56: 18228C | I56: 2536.89 | J56: CS000009270 | K56: E-18461 | L56: Europe: APG- PC JE Nis
A57: 1663-5YY0196ENNV00 | B57: D | C57: 1 | D57: 214 | E57: 33 | F57: 2910074056 | G57: 3197002461 | H57: 18230C | I57: 805.04 | J57: CS000009271 | K57: E-18461 | L57: Springfield
A58: 1663-5YY0250ENNV13 | B58: G | C58: 2 | D58: 4224 | E58: 329 | F58: 2910074057 | G58: 3197002485 | H58: 18229C | I58: 5688.24 | J58: CS000009272 | K58: E-18461 | L58: Europe: APG- PC JE Nis
A59: 1663-5YY0294ENNV00 | B59: F | C59: 1 | D59: 3840 | E59: 162 | F59: 2910073969 | G59: 3197002462 | H59: 18098C | I59: 2680.16 | J59: CS000009270 | K59: E-18437 | L59: Mexico
A60: 1663-5YY0294ENNV00 | B60: F | C60: 2 | D60: 7680 | E60: 323 | F60: 2910073970 | G60: 3197002463 | H60: 18097C | I60: 5360.31 | J60: CS000009270 | K60: E-18437 | L60: Mexico
A61: 1663-5YY0294ENNV00 | B61: F | C61: 1 | D61: 3840 | E61: 163 | F61: 2910073972 | G61: 3197002464 | H61: 18096C | I61: 2680.16 | J61: CS000009270 | K61: E-18437 | L61: Mexico
A62: 1663-5YY0296ENNV13 | B62: E | C62: 1 | D62: 2112 | E62: 161 | F62: 2910074501 | G62: 3197002480 | H62: 18918C | I62: 2290 | J62: CS000009531 | K62: E-18555 | L62: Americas: APG- PC BRAZIL
A63: 1663-5YY0296ENNV13 | B63: E | C63: 1 | D63: 2112 | E63: 165 | F63: 2910074502 | G63: 3197002481 | H63: 18919C | I63: 2290 | J63: CS000009531 | K63: E-18555 | L63: Americas: APG- PC BRAZIL

Sheet CONSOLIDADO 2026 (2)
A1: WEEK | B1: MXT/MXG | C1: ITEM | D1: SUPPLIER | E1: TYPE | F1: NO TOCAR | G1: REFERENCIA | H1: INVOICE # | I1: MOUTH | J1: INVOICE DATE | K1: PEDIMENTO | L1: PRO NUMBER/ TRACKING # | M1: IMPO/ EXPO MOOD | N1: TRAILER/ CONTAINER | O1: PAGO DE IMPUESTOS | P1: PAGO A TERCEROS | Q1: SUB-TOTAL | R1: IVA | S1: RETENTION | T1: TOTAL | U1: CURRENCY | V1: USD AMOUNT | W1: SHIP DATE | X1: SHIPPER | Y1: ORIGIN | Z1: DESTINATION | AA1: CONSIGNEE | AB1: BU | AC1: I/O | AD1: TYPE | AE1: ACCOUNT | AF1: COMMENTS | AG1: ACCOUNT | AH1: MXN AMOUNT | AI1: W | AJ1: CHARGE BACK | AK1: AMOUNT USD | AL1: INVOICED
A2: 01 | B2: MXG | C2: 20 | D2: DICEX S.A DE C.V. | E2: Broker | F2: =E2&G2 -> BrokerRM-M-487-SI25-M19-B | G2: RM-M-487-SI25-M19-B | H2: MZO185524 | I2: ENERO | J2: 46003 | K2: 25 16 1690 5042158 | L2: COSU6433823132 | M2: IMPO | N2: OOLU9447086 | O2: 0 | P2: 11671.42 | Q2: 3631.63 | R2: 581.07 | S2: 0 | T2: 15884.12 | U2: MXN | V2: =T2/17.9075 -> 887.00935 | W2: 12-Dec-25 | X2: JOHNSON ELECTRIC INDUSTRIAL MANUFACTORY LIMITED | Y2: CHN | Z2: ZCL | AA2: JEG | AB2: M19 | AC2: I | AD2: SEA IMPO | AE2: 67120000 | AF2: NO COMMENTS | AI2: 01 | AJ2: NO | AK2: 0 | AL2: NO | AM2: =VLOOKUP(G2,'[3]Master template02'!$D:$D,1,0) -> RM-M-487-SI25-M19-B
A3: 01 | B3: MXG | C3: 25 | D3: DICEX S.A DE C.V. | E3: Broker | F3: =E3&G3 -> BrokerRM-M-492-SI25-M19-B | G3: RM-M-492-SI25-M19-B | H3: MZO185614 | I3: ENERO | J3: 46003 | K3: 25 16 1690 5038773 | L3: OOLU2038157981 | M3: IMPO | N3: TGBU7698706 | O3: 0 | P3: 15672.47 | Q3: 3544.16 | R3: 567.06 | S3: 0 | T3: 19783.69 | U3: MXN | V3: =T3/17.9075 -> 1104.7712 | W3: 12-Dec-25 | X3: JOHNSON ELECTRIC INDUSTRIAL MANUFACTORY LIMITED | Y3: CHN | Z3: ZCL | AA3: JEG | AB3: M19 | AC3: I | AD3: SEA IMPO | AE3: 67120000 | AF3: NO COMMENTS | AI3: 01 | AJ3: NO | AK3: 0 | AL3: NO | AM3: =VLOOKUP(G3,'[3]Master template02'!$D:$D,1,0) -> RM-M-492-SI25-M19-B
A4: 01 | B4: MXG | C4: 28 | D4: DICEX S.A DE C.V. | E4: Broker | F4: =E4&G4 -> BrokerRM-M-488-SI25-M19-B | G4: RM-M-488-SI25-M19-B | H4: MZO185640 | I4: ENERO | J4: 46003 | K4: 25 16 1690 5042157 | L4: COSU6433823133 | M4: IMPO | N4: CSNU7797874 | O4: 0 | P4: 11671.42 | Q4: 6693.5 | R4: 1070.96 | S4: 0 | T4: 19435.88 | U4: MXN | V4: =T4/17.9075 -> 1085.3486 | W4: 12-Dec-25 | X4: JOHNSON ELECTRIC INDUSTRIAL MANUFACTORY LIMITED | Y4: CHN | Z4: ZCL | AA4: JEG | AB4: M19 | AC4: I | AD4: SEA IMPO | AE4: 67120000 | AF4: NO COMMENTS | AI4: 01 | AJ4: NO | AK4: 0 | AL4: NO | AM4: =VLOOKUP(G4,'[3]Master template02'!$D:$D,1,0) -> RM-M-488-SI25-M19-B
A5: 01 | B5: MXG | C5: 29 | D5: DICEX S.A DE C.V. | E5: Broker | F5: =E5&G5 -> BrokerRM-M-490-SI25-M19-B | G5: RM-M-490-SI25-M19-B | H5: MZO185644 | I5: ENERO | J5: 46003 | K5: 25 16 1690 5042156 | L5: OOLU2038174630 | M5: IMPO | N5: CSNU6882837 | O5: 0 | P5: 12430.27 | Q5: 4920.08 | R5: 787.21 | S5: 0 | T5: 18137.56 | U5: MXN | V5: =T5/17.9075 -> 1012.8471 | W5: 12-Dec-25 | X5: JOHNSON ELECTRIC INDUSTRIAL MANUFACTORY LIMITED | Y5: CHN | Z5: ZCL | AA5: JEG | AB5: M19 | AC5: I | AD5: SEA IMPO | AE5: 67120000 | AF5: NO COMMENTS | AI5: 01 | AJ5: NO | AK5: 0 | AL5: NO | AM5: =VLOOKUP(G5,'[3]Master template02'!$D:$D,1,0) -> RM-M-490-SI25-M19-B
A6: 01 | B6: MXG | C6: 30 | D6: DICEX S.A DE C.V. | E6: Broker | F6: =E6&G6 -> BrokerRM-M-488-SI25-M19-B | G6: RM-M-488-SI25-M19-B | H6: MZO185726 | I6: ENERO | J6: 46006 | K6: 25 16 1690 5042161 | L6: COSU6433823133 | M6: IMPO | N6: CSNU7797874 | O6: 0 | P6: 0 | Q6: 1498.91 | R6: 239.83 | S6: 0 | T6: 1738.74 | U6: MXN | V6: =T6/17.9075 -> 97.09563 | W6: 15-Dec-25 | X6: JOHNSON ELECTRIC INDUSTRIAL MANUFACTORY LIMITED | Y6: CHN | Z6: ZCL | AA6: JEG | AB6: M19 | AC6: I | AD6: SEA IMPO | AE6: 67120000 | AF6: NO COMMENTS | AI6: 01 | AJ6: NO | AK6: 0 | AL6: NO | AM6: =VLOOKUP(G6,'[3]Master template02'!$D:$D,1,0) -> RM-M-488-SI25-M19-B
A7: 01 | B7: MXG | C7: 38 | D7: DICEX S.A DE C.V. | E7: Broker | F7: =E7&G7 -> BrokerRM-M-490-SI25-M19-B | G7: RM-M-490-SI25-M19-B | H7: MZO185998 | I7: ENERO | J7: 46008 | K7: 25 16 1690 5042156 | L7: OOLU2038174630 | M7: IMPO | N7: CSNU6882837 | O7: 0 | P7: 6264 | Q7: 0 | R7: 0 | S7: 0 | T7: 6264 | U7: MXN | V7: =T7/17.9075 -> 349.79757 | W7: 17-Dec-25 | X7: JOHNSON ELECTRIC INDUSTRIAL MANUFACTORY LIMITED | Y7: CHN | Z7: ZCL | AA7: JEG | AB7: M19 | AC7: I | AD7: SEA IMPO | AE7: 67120000 | AF7: NO COMMENTS | AI7: 01 | AJ7: NO | AK7: 0 | AL7: NO | AM7: =VLOOKUP(G7,'[3]Master template02'!$D:$D,1,0) -> RM-M-490-SI25-M19-B
A8: 01 | B8: MXG | C8: 43 | D8: DICEX S.A DE C.V. | E8: Broker | F8: =E8&G8 -> BrokerRM-M-492-SI25-M19-B | G8: RM-M-492-SI25-M19-B | H8: MZO186242 | I8: ENERO | J8: 46010 | K8: 25 16 1690 5038773 | L8: OOLU2038157981 | M8: IMPO | N8: TGBU7698706 | O8: 0 | P8: 12992 | Q8: 0 | R8: 0 | S8: 0 | T8: 12992 | U8: MXN | V8: =T8/17.9075 -> 725.50607 | W8: 19-Dec-25 | X8: JOHNSON ELECTRIC INDUSTRIAL MANUFACTORY LIMITED | Y8: CHN | Z8: ZCL | AA8: JEG | AB8: M19 | AC8: I | AD8: SEA IMPO | AE8: 67120000 | AF8: NO COMMENTS | AI8: 01 | AJ8: NO | AK8: 0 | AL8: NO | AM8: =VLOOKUP(G8,'[3]Master template02'!$D:$D,1,0) -> RM-M-492-SI25-M19-B
A9: 01 | B9: MXG | C9: 44 | D9: DICEX S.A DE C.V. | E9: Broker | F9: =E9&G9 -> BrokerRM-M-488-SI25-M19-B | G9: RM-M-488-SI25-M19-B | H9: MZO186245 | I9: ENERO | J9: 46010 | K9: 25 16 1690 5042157 | L9: COSU6433823133 | M9: IMPO | N9: CSNU7797874 | O9: 0 | P9: 7540 | Q9: 0 | R9: 0 | S9: 0 | T9: 7540 | U9: MXN | V9: =T9/17.9075 -> 421.05263 | W9: 19-Dec-25 | X9: JOHNSON ELECTRIC INDUSTRIAL MANUFACTORY LIMITE | Y9: CHN | Z9: ZCL | AA9: JEG | AB9: M19 | AC9: I | AD9: SEA IMPO | AE9: 67120000 | AF9: NO COMMENTS | AI9: 01 | AJ9: NO | AK9: 0 | AL9: NO | AM9: =VLOOKUP(G9,'[3]Master template02'!$D:$D,1,0) -> RM-M-488-SI25-M19-B
A10: 01 | B10: MXG | C10: 45 | D10: DICEX S.A DE C.V. | E10: Broker | F10: =E10&G10 -> BrokerRM-M-487-SI25-M19-B | G10: RM-M-487-SI25-M19-B | H10: MZO186246 | I10: ENERO | J10: 46010 | K10: 25 16 1690 5042158 | L10: COSU6433823132 | M10: IMPO | N10: OOLU9447086 | O10: 0 | P10: 6844 | Q10: 0 | R10: 0 | S10: 0 | T10: 6844 | U10: MXN | V10: =T10/17.9075 -> 382.18623 | W10: 19-Dec-25 | X10: JOHNSON ELECTRIC INDUSTRIAL MANUFACTORY LIMITE | Y10: CHN | Z10: ZCL | AA10: JEG | AB10: M19 | AC10: I | AD10: SEA IMPO | AE10: 67120000 | AF10: NO COMMENTS | AI10: 01 | AJ10: NO | AK10: 0 | AL10: NO | AM10: =VLOOKUP(G10,'[3]Master template02'!$D:$D,1,0) -> RM-M-487-SI25-M19-B
A11: 01 | B11: MXG | C11: 46 | D11: DICEX S.A DE C.V. | E11: Broker | F11: =E11&G11 -> BrokerRM-M-504-SI25-M19-B | G11: RM-M-504-SI25-M19-B | H11: MZO186254 | I11: ENERO | J11: 46010 | K11: 25 16 1690 5042740 | L11: OOLU2038188200 | M11: IMPO | N11: OOCU7164584 | O11: 0 | P11: 12430.27 | Q11: 4795.36 | R11: 767.25 | S11: 0 | T11: 17992.88 | U11: MXN | V11: =T11/17.9075 -> 1004.7678 | W11: 19-Dec-25 | X11: JOHNSON ELECTRIC INDUSTRIAL MANUFACTORY LIMITED | Y11: CHN | Z11: ZCL | AA11: JEG | AB11: M19 | AC11: I | AD11: SEA IMPO | AE11: 67120000 | AF11: NO COMMENTS | AI11: 01 | AJ11: NO | AK11: 0 | AL11: NO | AM11: =VLOOKUP(G11,'[3]Master template02'!$D:$D,1,0) -> RM-M-504-SI25-M19-B
A12: 01 | B12: MXG | C12: 47 | D12: DICEX S.A DE C.V. | E12: Broker | F12: =E12&G12 -> BrokerRM-M-505-SI25-M19-B | G12: RM-M-505-SI25-M19-B | H12: MZO186257 | I12: ENERO | J12: 46010 | K12: 25 16 1690 5042741 | L12: OOLU2038188201 | M12: IMPO | N12: TXGU4115032 | O12: 0 | P12: 12430.27 | Q12: 6761.96 | R12: 1081.91 | S12: 0 | T12: 20274.14 | U12: MXN | V12: =T12/17.9075 -> 1132.1592 | W12: 19-Dec-25 | X12: JOHNSON ELECTRIC INDUSTRIAL MANUFACTORY LIMITED | Y12: CHN | Z12: ZCL | AA12: JEG | AB12: M19 | AC12: I | AD12: SEA IMPO | AE12: 67120000 | AF12: NO COMMENTS | AI12: 01 | AJ12: NO | AK12: 0 | AL12: NO | AM12: =VLOOKUP(G12,'[3]Master template02'!$D:$D,1,0) -> RM-M-505-SI25-M19-B
A13: 01 | B13: MXG | C13: 59 | D13: DICEX S.A DE C.V. | E13: Broker | F13: =E13&G13 -> BrokerRM-M-523-SI25-M19-B | G13: RM-M-523-SI25-M19-B | H13: MZO187006 | I13: ENERO | J13: 46024 | K13: 25 16 1690 5043760 | L13: OOLU2038223200 | M13: IMPO | N13: CSNU6814540 | O13: 0 | P13: 0 | Q13: 2438.4 | R13: 390.14 | S13: 0 | T13: 2828.54 | U13: MXN | V13: =T13/17.9075 -> 157.95281 | W13: 46024 | X13: JOHNSON ELECTRIC INDUSTRIAL MANUFACTORY LIMITE | Y13: CHN | Z13: ZCL | AA13: JEG | AB13: M19 | AC13: I | AD13: SEA IMPO | AE13: 67120000 | AF13: NO COMMENTS | AI13: 01 | AJ13: NO | AK13: 0 | AL13: NO | AM13: =VLOOKUP(G13,'[3]Master template02'!$D:$D,1,0) -> RM-M-523-SI25-M19-B
A14: 01 | B14: MXG | C14: 60 | D14: DICEX S.A DE C.V. | E14: Broker | F14: =E14&G14 -> BrokerRM-M-504-SI25-M19-B | G14: RM-M-504-SI25-M19-B | H14: MZO187018 | I14: ENERO | J14: 46024 | K14: 25 16 1690 5042740 | L14: OOLU2038188200 | M14: IMPO | N14: OOCU7164584 | O14: 0 | P14: 6148 | Q14: 0 | R14: 0 | S14: 0 | T14: 6148 | U14: MXN | V14: =T14/17.9075 -> 343.31984 | W14: 46024 | X14: JOHNSON ELECTRIC INDUSTRIAL MANUFACTORY LIMITE | Y14: CHN | Z14: ZCL | AA14: JEG | AB14: M19 | AC14: I | AD14: SEA IMPO | AE14: 67120000 | AF14: NO COMMENTS | AI14: 01 | AJ14: NO | AK14: 0 | AL14: NO | AM14: =VLOOKUP(G14,'[3]Master template02'!$D:$D,1,0) -> RM-M-504-SI25-M19-B
A15: 01 | B15: MXG | C15: 61 | D15: DICEX S.A DE C.V. | E15: Broker | F15: =E15&G15 -> BrokerRM-M-505-SI25-M19-B | G15: RM-M-505-SI25-M19-B | H15: MZO187205 | I15: ENERO | J15: 46024 | K15: 25 16 1690 5042741 | L15: OOLU2038188201 | M15: IMPO | N15: TXGU4115032 | O15: 0 | P15: 6844 | Q15: 0 | R15: 0 | S15: 0 | T15: 6844 | U15: MXN | V15: =T15/17.9075 -> 382.18623 | W15: 46024 | X15: JOHNSON ELECTRIC INDUSTRIAL MANUFACTORY LIMITED | Y15: CHN | Z15: ZCL | AA15: JEG | AB15: M19 | AC15: I | AD15: SEA IMPO | AE15: 67120000 | AF15: NO COMMENTS | AI15: 01 | AJ15: NO | AK15: 0 | AL15: NO | AM15: =VLOOKUP(G15,'[3]Master template02'!$D:$D,1,0) -> RM-M-505-SI25-M19-B
A16: 01 | B16: MXG | C16: 145 | D16: TRANSPORTES L. DOMINGUEZ | E16: Freight | F16: =E16&G16 -> FreightFG-A-0078-SE25-M19 | G16: FG-A-0078-SE25-M19 | H16: 4571 | I16: ENERO | J16: 46024 | L16: OTRO | M16: LAND EXPO | N16: HAMU 2689969 | O16: 0 | P16: 0 | Q16: 35000 | R16: 5600 | S16: 1400 | T16: 39200 | U16: MXN | V16: =T16/17.9075 -> 2189.0269 | W16: VARIAS | X16: VARIOUS | Y16: ALT | Z16: ZAC | AA16: JOHNSON ELECTRIC GROUP MEXICO | AB16: M19 | AC16: O | AD16: SEA EXPO | AE16: 59220000 | AF16: NO COMMENTS | AI16: 01 | AJ16: NO | AK16: 0 | AL16: NO | AM16: =VLOOKUP(G16,'[3]Master template02'!$D:$D,1,0) -> FG-A-0078-SE25-M19
A17: 01 | B17: MXG | C17: 146 | D17: TRANSPORTES L. DOMINGUEZ | E17: Freight | F17: =E17&G17 -> FreightFG-A-0077-SE25-M19 | G17: FG-A-0077-SE25-M19 | H17: 4573 | I17: ENERO | J17: 46024 | L17: OTRO | M17: LAND EXPO | N17: FANU 3643239 | O17: 0 | P17: 0 | Q17: 35000 | R17: 5600 | S17: 1400 | T17: 39200 | U17: MXN | V17: =T17/17.9075 -> 2189.0269 | W17: VARIAS | X17: VARIOUS | Y17: ALT | Z17: ZAC | AA17: JOHNSON ELECTRIC GROUP MEXICO | AB17: M19 | AC17: O | AD17: SEA EXPO | AE17: 59220000 | AF17: NO COMMENTS | AI17: 01 | AJ17: NO | AK17: 0 | AL17: NO | AM17: =VLOOKUP(G17,'[3]Master template02'!$D:$D,1,0) -> FG-A-0077-SE25-M19
A18: 01 | B18: MXG | C18: 149 | D18: TRANSPORTES L. DOMINGUEZ | E18: Freight | F18: =E18&G18 -> FreightRM-M-203-SI25-M19-L | G18: RM-M-203-SI25-M19-L | H18: 4576 | I18: ENERO | J18: 46024 | K18: 25-810-3818-5001826 | L18: OTRO | M18: LAND IMPO | N18: CARGA SUELTA | O18: 0 | P18: 0 | Q18: 27750 | R18: 4440 | S18: 1110 | T18: 31080 | U18: MXN | V18: =T18/17.9075 -> 1735.5856 | W18: VARIAS | X18: GSL MARIA | Y18: ALT | Z18: ZAC | AA18: JOHNSON ELECTRIC GROUP MEXICO | AB18: M19 | AC18: I | AD18: SEA IMPO | AE18: 67120000 | AF18: NO COMMENTS | AI18: 01 | AJ18: NO | AK18: 0 | AL18: NO | AM18: =VLOOKUP(G18,'[3]Master template02'!$D:$D,1,0) -> RM-M-203-SI25-M19-L
A19: 01 | B19: MXG | C19: 150 | D19: TRANSPORTES L. DOMINGUEZ | E19: Freight | F19: =E19&G19 -> FreightRM-M-202-SI25-M19-L | G19: RM-M-202-SI25-M19-L | H19: 4576 | I19: ENERO | J19: 46024 | K19: 25-810-3818-5001842 | L19: OTRO | M19: LAND IMPO | N19: CARGA SUELTA | O19: 0 | P19: 0 | Q19: 0 | R19: 0 | S19: 0 | T19: 0 | U19: MXN | V19: =T19/17.9075 -> 0 | W19: VARIAS | X19: VARIOUS | Y19: ALT | Z19: ZAC | AA19: JOHNSON ELECTRIC GROUP MEXICO | AB19: M19 | AC19: I | AD19: SEA IMPO | AE19: 67120000 | AF19: NO COMMENTS | AI19: 01 | AJ19: NO | AK19: 0 | AL19: NO | AM19: =VLOOKUP(G19,'[3]Master template02'!$D:$D,1,0) -> RM-M-202-SI25-M19-L
A20: 02 | B20: MXG | C20: 186 | D20: TRANSPORTES BRABER,S.A.DE C.V. | E20: Freight | F20: =E20&G20 -> FreightFG-V-174-V1E25-M19 | G20: FG-V-174-V1E25-M19 | H20: C8033 | I20: ENERO | J20: 46031 | K20: 25-730 3658-5008652 | L20: 5656 | M20: NACIONAL | N20: RB-002 | O20: 0 | P20: 0 | Q20: 8000 | R20: 1280 | S20: 320 | T20: 8960 | U20: MXN | V20: =T20/17.599 -> 509.11984 | W20: 46033 | X20: ZAC-AGS | Y20: JOHNSON | Z20: MARELLI | AA20: ZAC | AB20: M19 | AC20: O | AD20: LAND EXPO | AE20: 59210003 | AF20: NO COMMENTS | AI20: 02 | AJ20: NO | AK20: 0 | AL20: NO | AM20: =VLOOKUP(G20,'[3]Master template02'!$D:$D,1,0) -> FG-V-174-V1E25-M19
A21: 02 | B21: MXG | C21: 193 | D21: TRANSPORTES BRABER,S.A.DE C.V. | E21: Freight | F21: =E21&G21 -> FreightRM-J-1139LI25-M19.3 | G21: RM-J-1139LI25-M19.3 | H21: C7950 | I21: ENERO | J21: 46027 | K21: 26 24 3483 6089003/ 26 24 3483 6089005 | L21: 5915 | M21: IMPO | N21: TB-007 | O21: 0 | P21: 0 | Q21: 1200 | R21: 192 | S21: 48 | T21: 1344 | U21: USD | V21: =T21 -> 1344 | W21: 46029 | X21: USA-ZAC | Y21: TDS | Z21: JOHNSON | AA21: ZAC | AB21: M19 | AC21: I | AD21: LAND IMPO | AE21: 67110002 | AF21: NO COMMENTS | AI21: 02 | AJ21: NO | AK21: 0 | AL21: NO | AM21: =VLOOKUP(G21,'[3]Master template02'!$D:$D,1,0) -> RM-J-1139LI25-M19.3
A22: 02 | B22: MXG | C22: 194 | D22: TRANSPORTES BRABER,S.A.DE C.V. | E22: Freight | F22: =E22&G22 -> FreightRM-J-1137LI25-M19.2 | G22: RM-J-1137LI25-M19.2 | H22: C7970 | I22: ENERO | J22: 46029 | K22: 25 24 3483 5035824 | L22: 5825 | M22: IMPO | N22: TB-019 | O22: 0 | P22: 0 | Q22: 1150 | R22: 184 | S22: 46 | T22: 1288 | U22: USD | V22: =T22 -> 1288 | W22: 46029 | X22: USA-ZAC | Y22: TDS | Z22: JOHNSON | AA22: ZAC | AB22: M19 | AC22: I | AD22: LAND IMPO | AE22: 67110002 | AF22: NO COMMENTS | AI22: 02 | AJ22: NO | AK22: 0 | AL22: NO | AM22: =VLOOKUP(G22,'[3]Master template02'!$D:$D,1,0) -> RM-J-1137LI25-M19.2
A23: 02 | B23: MXG | C23: 195 | D23: TRANSPORTES BRABER,S.A.DE C.V. | E23: Freight | F23: =E23&G23 -> FreightRM-J-1134LI25-M19.4 | G23: RM-J-1134LI25-M19.4 | H23: C7971 | I23: ENERO | J23: 46029 | K23: 25 24 3483 5035818/25 24 3483 5035819 | L23: 5808 | M23: IMPO | N23: TB-031 | O23: 0 | P23: 0 | Q23: 1150 | R23: 184 | S23: 46 | T23: 1288 | U23: USD | V23: =T23 -> 1288 | W23: 46029 | X23: USA-ZAC | Y23: TDS | Z23: JOHNSON | AA23: ZAC | AB23: M19 | AC23: I | AD23: LAND IMPO | AE23: 67110002 | AF23: NO COMMENTS | AI23: 02 | AJ23: NO | AK23: 0 | AL23: NO | AM23: =VLOOKUP(G23,'[3]Master template02'!$D:$D,1,0) -> RM-J-1134LI25-M19.4
A24: 02 | B24: MXG | C24: 196 | D24: TRANSPORTES BRABER,S.A.DE C.V. | E24: Freight | F24: =E24&G24 -> FreightRM-J-1131LI25-M19.2 | G24: RM-J-1131LI25-M19.2 | H24: C7972 | I24: ENERO | J24: 46029 | K24: 25 24 3483 5035815 | L24: 5758 | M24: IMPO | N24: TB-007 | O24: 0 | P24: 0 | Q24: 1150 | R24: 184 | S24: 46 | T24: 1288 | U24: USD | V24: =T24 -> 1288 | W24: 46029 | X24: USA-ZAC | Y24: TDS | Z24: JOHNSON | AA24: ZAC | AB24: M19 | AC24: I | AD24: LAND IMPO | AE24: 67110002 | AF24: NO COMMENTS | AI24: 02 | AJ24: NO | AK24: 0 | AL24: NO | AM24: =VLOOKUP(G24,'[3]Master template02'!$D:$D,1,0) -> RM-J-1131LI25-M19.2
A25: 02 | B25: MXG | C25: 197 | D25: TRANSPORTES BRABER,S.A.DE C.V. | E25: Freight | F25: =E25&G25 -> FreightRM-J-1121LI25-M19.2 | G25: RM-J-1121LI25-M19.2 | H25: C7973 | I25: ENERO | J25: 46029 | K25: 25 24 3483 5035815 | L25: 5734 | M25: IMPO | N25: TB-010 | O25: 0 | P25: 0 | Q25: 1150 | R25: 184 | S25: 46 | T25: 1288 | U25: USD | V25: =T25 -> 1288 | W25: 46029 | X25: USA-ZAC | Y25: TDS | Z25: JOHNSON | AA25: ZAC | AB25: M19 | AC25: I | AD25: LAND IMPO | AE25: 67110002 | AF25: NO COMMENTS | AI25: 02 | AJ25: NO | AK25: 0 | AL25: NO | AM25: =VLOOKUP(G25,'[3]Master template02'!$D:$D,1,0) -> RM-J-1121LI25-M19.2
A26: 02 | B26: MXG | C26: 198 | D26: TRANSPORTES BRABER,S.A.DE C.V. | E26: Freight | F26: =E26&G26 -> FreightRM-J-1115LI25-M19.3 | G26: RM-J-1115LI25-M19.3 | H26: C7974 | I26: ENERO | J26: 46029 | K26: 25 24 3483 5035812/25 24 3483 5035817 | L26: 5658 | M26: IMPO | N26: TB-011 | O26: 0 | P26: 0 | Q26: 1150 | R26: 184 | S26: 46 | T26: 1288 | U26: USD | V26: =T26 -> 1288 | W26: 46029 | X26: USA-ZAC | Y26: TDS | Z26: JOHNSON | AA26: ZAC | AB26: M19 | AC26: I | AD26: LAND IMPO | AE26: 67110002 | AF26: NO COMMENTS | AI26: 02 | AJ26: NO | AK26: 0 | AL26: NO | AM26: =VLOOKUP(G26,'[3]Master template02'!$D:$D,1,0) -> RM-J-1115LI25-M19.3
A27: 02 | B27: MXG | C27: 255 | D27: DICEX S.A DE C.V. | E27: Broker | F27: =E27&G27 -> BrokerRM-M-506-S125-M19-B | G27: RM-M-506-S125-M19-B | H27: ALT81449 | I27: ENERO | J27: 46027 | K27: 25-810-3699-5005885 | L27: MEDUKJ605360 | M27: IMPO | N27: MSDU2811711 | O27: 0 | P27: 10097.12 | Q27: 2630.03 | R27: 420.8 | S27: 0 | T27: 13147.95 | U27: MXN | V27: =T27/17.599 -> 747.08506 | W27: 46006 | X27: DSV AIR & SEA GERMANY | Y27: GERMANY | Z27: MEX | AA27: DSV AIR & SEA, S.A. DE C.V | AB27: M19 | AC27: I | AD27: SEA IMPO | AE27: 67120000 | AF27: NO COMMENTS | AI27: 02 | AJ27: NO | AK27: 0 | AL27: NO | AM27: =VLOOKUP(G27,'[3]Master template02'!$D:$D,1,0) -> #N/A
A28: 02 | B28: MXG | C28: 256 | D28: DICEX S.A DE C.V. | E28: Broker | F28: =E28&G28 -> BrokerRM-M-506-S125-M19-B | G28: RM-M-506-S125-M19-B | H28: ALT81450 | I28: ENERO | J28: 46027 | K28: 25-810-3699-5001765 | L28: MEDUKJ558155 | M28: IMPO | N28: DFSU2885364 | O28: 781 | P28: 10096.68 | Q28: 2536.65 | R28: 405.86 | S28: 0 | T28: 13820.19 | U28: MXN | V28: =T28/17.599 -> 785.28269 | W28: 46000 | X28: DSV AIR & SEA GERMANY | Y28: GERMANY | Z28: MEX | AA28: DSV AIR & SEA, S.A. DE C.V | AB28: M19 | AC28: I | AD28: SEA IMPO | AE28: 67120000 | AF28: NO COMMENTS | AI28: 02 | AJ28: NO | AK28: 0 | AL28: NO | AM28: =VLOOKUP(G28,'[3]Master template02'!$D:$D,1,0) -> #N/A
A29: 02 | B29: MXG | C29: 269 | D29: DICEX S.A DE C.V. | E29: Broker | F29: =E29&G29 -> BrokerFG-I-0037-SE25-M23-L.D | G29: FG-I-0037-SE25-M23-L.D | H29: ALT81550 | I29: ENERO | J29: 46029 | K29: 25-810-3699-5001734 | L29: ATMPRG152840V | M29: IMPO | N29: NEYNO 20251126 | O29: 336 | P29: 1508 | Q29: 2536.65 | R29: 405.86 | S29: 0 | T29: 4786.51 | U29: MXN | V29: =T29/17.599 -> 271.97625 | W29: 45999 | X29: JOHNSON ELECTRIC GROUP MEXICO S DE RL DE CV | Y29: MEX | Z29: USA | AA29: JOHNSON ELECTRIC NORTH AMERICA INC | AB29: M23 | AC29: O | AD29: SEA EXPO | AE29: 59220000 | AF29: ESTA CUENTA SUSTITUYE EL FOLIO ALT81472 | AI29: 02 | AJ29: NO | AK29: 0 | AL29: NO | AM29: =VLOOKUP(G29,'[3]Master template02'!$D:$D,1,0) -> #N/A
A30: 02 | B30: MXG | C30: 270 | D30: DICEX S.A DE C.V. | E30: Broker | F30: =E30&G30 -> BrokerFG-I-0037-SE25-M23-L.D | G30: FG-I-0037-SE25-M23-L.D | H30: ALT81551 | I30: ENERO | J30: 46029 | K30: 25-810-3699-5001906 | L30: ATMPRG152840V | M30: IMPO | N30: NEYNO 20251126 | O30: 428 | P30: 0 | Q30: 1005.38 | R30: 160.86 | S30: 0 | T30: 1594.24 | U30: MXN | V30: =T30/17.599 -> 90.586965 | W30: 46008 | X30: JOHNSON ELECTRIC GROUP MEXICO S DE RL DE CV | Y30: MEX | Z30: USA | AA30: JOHNSON ELECTRIC NORTH AMERICA INC | AB30: M23 | AC30: O | AD30: SEA EXPO | AE30: 59220000 | AF30: NO COMMENTS | AI30: 02 | AJ30: NO | AK30: 0 | AL30: NO | AM30: =VLOOKUP(G30,'[3]Master template02'!$D:$D,1,0) -> #N/A
A31: 02 | B31: MXG | C31: 310 | D31: DICEX S.A DE C.V. | E31: Broker | F31: =E31&G31 -> BrokerRM-M-523-SI25-M19-B | G31: RM-M-523-SI25-M19-B | H31: MZO187573 | I31: ENERO | J31: 46028 | K31: 25 16 1690 5043461 | L31: OOLU2038223200 | M31: IMPO | N31: CSNU6814540 | O31: 0 | P31: 19081.27 | Q31: 5594.66 | R31: 895.14 | S31: 0 | T31: 25571.07 | U31: MXN | V31: =T31/17.599 -> 1452.9843 | W31: 46028 | X31: JOHNSON ELECTRIC INDUSTRIAL MANUFACTORY LIMITED | Y31: CHN | Z31: ZCL | AA31: JEG | AB31: M19 | AC31: I | AD31: SEA IMPO | AE31: 67120000 | AF31: NO COMMENTS | AI31: 02 | AJ31: NO | AK31: 0 | AL31: NO | AM31: =VLOOKUP(G31,'[3]Master template02'!$D:$D,1,0) -> RM-M-523-SI25-M19-B
A32: 02 | B32: MXG | C32: 323 | D32: DICEX S.A DE C.V. | E32: Broker | F32: =E32&G32 -> BrokerRM-M-540-SI25-M19-B | G32: RM-M-540-SI25-M19-B | H32: MZO187863 | I32: ENERO | J32: 46030 | K32: 26 16 1690 6000179 | L32: MEDURH708055 | M32: IMPO | N32: TRHU6556188 | O32: 0 | P32: 14017.17 | Q32: 3858.68 | R32: 617.38 | S32: 0 | T32: 18493.23 | U32: MXN | V32: =T32/17.599 -> 1050.8114 | W32: 46030 | X32: JOHNSON ELECTRIC INDUSTRIAL MANUFACTORY LIMITED | Y32: CHN | Z32: ZCL | AA32: JEG | AB32: M19 | AC32: I | AD32: SEA IMPO | AE32: 67120000 | AF32: NO COMMENTS | AI32: 02 | AJ32: NO | AK32: 0 | AL32: NO | AM32: =VLOOKUP(G32,'[3]Master template02'!$D:$D,1,0) -> RM-M-540-SI25-M19-B
A33: 02 | B33: MXG | C33: 419 | D33: TRANSPORTES L. DOMINGUEZ | E33: Freight | F33: =E33&G33 -> FreightRM-M-574-SI25-M19 | G33: RM-M-574-SI25-M19 | H33: 4604 | I33: ENERO | J33: 46029 | L33: MEDU7352639 | M33: LAND IMPO | N33: MEDU 7352639 | O33: 0 | P33: 0 | Q33: 36500 | R33: 5840 | S33: 1460 | T33: 40880 | U33: MXN | V33: =T33/17.599 -> 2322.8593 | W33: 6-Jan | X33: MSC PILAR VI - NH550A | Y33: ALT | Z33: ZAC | AA33: JEG | AB33: M19 | AC33: I | AD33: SEA IMPO | AE33: 67120000 | AF33: NO COMMENTS | AI33: 02 | AJ33: NO | AK33: 0 | AL33: NO | AM33: =VLOOKUP(G33,'[3]Master template02'!$D:$D,1,0) -> #N/A
A34: 02 | B34: MXG | C34: 420 | D34: TRANSPORTES L. DOMINGUEZ | E34: Freight | F34: =E34&G34 -> FreightRM-M-226-SI25-M19-L | G34: RM-M-226-SI25-M19-L | H34: 4610 | I34: ENERO | J34: 46029 | L34: OTRO | M34: LAND IMPO | N34: CARGA SUELTA | O34: 0 | P34: 0 | Q34: 27750 | R34: 4440 | S34: 1110 | T34: 31080 | U34: MXN | V34: =T34/17.599 -> 1766.0094 | W34: VARIAS | X34: VARIOUS | Y34: ALT | Z34: ZAC | AA34: JEG | AB34: M19 | AC34: I | AD34: SEA IMPO | AE34: 67120000 | AF34: NO COMMENTS | AI34: 02 | AJ34: NO | AK34: 0 | AL34: NO | AM34: =VLOOKUP(G34,'[3]Master template02'!$D:$D,1,0) -> #N/A
A35: 02 | B35: MXG | C35: 421 | D35: TRANSPORTES L. DOMINGUEZ | E35: Freight | F35: =E35&G35 -> FreightRM-R-002-SI25-M19 | G35: RM-R-002-SI25-M19 | H35: 4625 | I35: ENERO | J35: 46032 | L35: OTRO | M35: LAND IMPO | N35: TXGU 4132298 | O35: 0 | P35: 0 | Q35: 54000 | R35: 8640 | S35: 2160 | T35: 60480 | U35: MXN | V35: =T35/17.599 -> 3436.5589 | W35: VARIAS | X35: VARIOUS | Y35: ALT | Z35: ZAC | AA35: JEG | AB35: M19 | AC35: I | AD35: SEA IMPO | AE35: 67120000 | AF35: NO COMMENTS | AI35: 02 | AJ35: NO | AK35: 0 | AL35: NO | AM35: =VLOOKUP(G35,'[3]Master template02'!$D:$D,1,0) -> RM-R-002-SI25-M19
A36: 02 | B36: MXG | C36: 422 | D36: TRANSPORTES L. DOMINGUEZ | E36: Freight | F36: =E36&G36 -> FreightRM-R-003-SI25-M19 | G36: RM-R-003-SI25-M19 | H36: 4625 | I36: ENERO | J36: 46032 | L36: OTRO | M36: LAND IMPO | N36: MSMU 1892090 | O36: 0 | P36: 0 | Q36: 0 | R36: 0 | S36: 0 | T36: 0 | U36: MXN | V36: =T36/17.599 -> 0 | W36: VARIAS | X36: VARIOUS | Y36: ALT | Z36: ZAC | AA36: JEG | AB36: M19 | AC36: I | AD36: SEA IMPO | AE36: 67120000 | AF36: NO COMMENTS | AI36: 02 | AJ36: NO | AK36: 0 | AL36: NO | AM36: =VLOOKUP(G36,'[3]Master template02'!$D:$D,1,0) -> RM-R-003-SI25-M19
A37: 02 | B37: MXG | C37: 423 | D37: TRANSPORTES L. DOMINGUEZ | E37: Freight | F37: =E37&G37 -> FreightRM-M-494-SI25-M19 | G37: RM-M-494-SI25-M19 | H37: 4608 | I37: ENERO | J37: 46029 | L37: OTRO | M37: LAND IMPO | N37: HLXU 1178560 | O37: 0 | P37: 0 | Q37: 54000 | R37: 8640 | S37: 2160 | T37: 60480 | U37: MXN | V37: =T37/17.599 -> 3436.5589 | W37: VARIAS | X37: VARIOUS | Y37: ALT | Z37: ZAC | AA37: JEG | AB37: M19 | AC37: I | AD37: SEA IMPO | AE37: 67120000 | AF37: NO COMMENTS | AI37: 02 | AJ37: NO | AK37: 0 | AL37: NO | AM37: =VLOOKUP(G37,'[3]Master template02'!$D:$D,1,0) -> RM-M-494-SI25-M19
A38: 02 | B38: MXG | C38: 424 | D38: TRANSPORTES L. DOMINGUEZ | E38: Freight | F38: =E38&G38 -> FreightRM-M-494-SI25-M19 | G38: RM-M-494-SI25-M19 | H38: 4608 | I38: ENERO | J38: 46029 | L38: OTRO | M38: LAND IMPO | N38: BSIU 3312735 | O38: 0 | P38: 0 | Q38: 0 | R38: 0 | S38: 0 | T38: 0 | U38: MXN | V38: =T38/17.599 -> 0 | W38: VARIAS | X38: VARIOUS | Y38: ALT | Z38: ZAC | AA38: JEG | AB38: M19 | AC38: I | AD38: SEA IMPO | AE38: 67120000 | AF38: NO COMMENTS | AI38: 02 | AJ38: NO | AK38: 0 | AL38: NO | AM38: =VLOOKUP(G38,'[3]Master template02'!$D:$D,1,0) -> RM-M-494-SI25-M19
A39: 02 | B39: MXG | C39: 427 | D39: TRANSPORTES L. DOMINGUEZ | E39: Freight | F39: =E39&G39 -> FreightRM-M-213-SI25-M19-L | G39: RM-M-213-SI25-M19-L | H39: 4609 | I39: ENERO | J39: 46029 | L39: OTRO | M39: LAND IMPO | N39: OTRO | O39: 0 | P39: 0 | Q39: 0 | R39: 0 | S39: 0 | T39: 0 | U39: MXN | V39: =T39/17.599 -> 0 | W39: VARIAS | X39: VARIOUS | Y39: ALT | Z39: ZAC | AA39: JEG | AB39: M19 | AC39: I | AD39: SEA IMPO | AE39: 67120000 | AF39: NO COMMENTS | AI39: 02 | AJ39: NO | AK39: 0 | AL39: NO | AM39: =VLOOKUP(G39,'[3]Master template02'!$D:$D,1,0) -> #N/A
A40: 02 | B40: MXG | C40: 428 | D40: TRANSPORTES L. DOMINGUEZ | E40: Freight | F40: =E40&G40 -> FreightRM-M-206-SI25-M19-L | G40: RM-M-206-SI25-M19-L | H40: 4609 | I40: ENERO | J40: 46029 | L40: OTRO | M40: LAND IMPO | N40: OTRO | O40: 0 | P40: 0 | Q40: 0 | R40: 0 | S40: 0 | T40: 0 | U40: MXN | V40: =T40/17.599 -> 0 | W40: VARIAS | X40: VARIOUS | Y40: ALT | Z40: ZAC | AA40: JEG | AB40: M19 | AC40: I | AD40: SEA IMPO | AE40: 67120000 | AF40: NO COMMENTS | AI40: 02 | AJ40: NO | AK40: 0 | AL40: NO | AM40: =VLOOKUP(G40,'[3]Master template02'!$D:$D,1,0) -> #N/A
A41: 02 | B41: MXG | C41: 432 | D41: TRANSPORTES L. DOMINGUEZ | E41: Freight | F41: =E41&G41 -> FreightRM-M-553-SI25-M19 | G41: RM-M-553-SI25-M19 | H41: 4614 | I41: ENERO | J41: 46029 | L41: MEDUBG226070 | M41: LAND IMPO | N41: MSMU 7768640 | O41: 0 | P41: 0 | Q41: 36500 | R41: 5840 | S41: 1460 | T41: 40880 | U41: MXN | V41: =T41/17.599 -> 2322.8593 | W41: 20-Dec | X41: HUBERT SCHULTE - NH548A | Y41: ALT | Z41: ZAC | AA41: JEG | AB41: M19 | AC41: I | AD41: SEA IMPO | AE41: 67120000 | AF41: NO COMMENTS | AI41: 02 | AJ41: NO | AK41: 0 | AL41: NO | AM41: =VLOOKUP(G41,'[3]Master template02'!$D:$D,1,0) -> #N/A
A42: 02 | B42: MXG | C42: 435 | D42: TRANSPORTES L. DOMINGUEZ | E42: Freight | F42: =E42&G42 -> FreightRM-M-564-SI25-M19 | G42: RM-M-564-SI25-M19 | H42: 4616 | I42: ENERO | J42: 46029 | L42: MEDUBG226716 | M42: LAND IMPO | N42: MSBU 5315338 | O42: 0 | P42: 0 | Q42: 36500 | R42: 5840 | S42: 1460 | T42: 40880 | U42: MXN | V42: =T42/17.599 -> 2322.8593 | W42: 28-Dec | X42: MSC BHAVYA V - NH549A | Y42: ALT | Z42: ZAC | AA42: JEG | AB42: M19 | AC42: I | AD42: SEA IMPO | AE42: 67120000 | AF42: NO COMMENTS | AI42: 02 | AJ42: NO | AK42: 0 | AL42: NO | AM42: =VLOOKUP(G42,'[3]Master template02'!$D:$D,1,0) -> #N/A
A43: 03 | B43: MXG | C43: 468 | D43: TRANSPORTES BRABER,S.A.DE C.V. | E43: Freight | F43: =E43&G43 -> FreightFG-V-001-V1E26-M01 | G43: FG-V-001-V1E26-M01 | H43: C8122 | I43: ENERO | J43: 46036 | K43: 26-730 3658-6000200 | L43: 5934 | M43: NAC | N43: S/N | O43: 0 | P43: 0 | Q43: 12800 | R43: 2048 | S43: 0 | T43: 14848 | U43: MXN | V43: =T43/17.283 -> 859.11011 | W43: 46037 | X43: ZAC-SALTI | Y43: JOHNSON | Z43: JIT DERRAMADERO | AA43: ZAC | AB43: M01 | AC43: O | AD43: LAND EXPO | AE43: 59210003 | AF43: NO COMMENTS | AI43: 03 | AJ43: NO | AK43: 0 | AL43: NO | AM43: =VLOOKUP(G43,'[3]Master template02'!$D:$D,1,0) -> FG-V-001-V1E26-M01
A44: 03 | B44: MXG | C44: 469 | D44: TRANSPORTES BRABER,S.A.DE C.V. | E44: Freight | F44: =E44&G44 -> FreightRM-J-1144LI26-M19.3 | G44: RM-J-1144LI26-M19.3 | H44: C8143 | I44: ENERO | J44: 46038 | K44: 26 24 3483 6089003/26 24 3483 6089008 | L44: 5968 | M44: IMPO | N44: TB-004 | O44: 0 | P44: 0 | Q44: 1200 | R44: 192 | S44: 48 | T44: 1344 | U44: USD | V44: =T44 -> 1344 | W44: 46038 | X44: USA-ZAC | Y44: TDS | Z44: JOHNSON | AA44: ZAC | AB44: M19 | AC44: I | AD44: LAND IMPO | AE44: 67110002 | AF44: NO COMMENTS | AI44: 03 | AJ44: NO | AK44: 0 | AL44: NO | AM44: =VLOOKUP(G44,'[3]Master template02'!$D:$D,1,0) -> RM-J-1144LI26-M19.3
A45: 03 | B45: MXG | C45: 470 | D45: TRANSPORTES BRABER,S.A.DE C.V. | E45: Freight | F45: =E45&G45 -> FreightRM-J-1150LI26-M19.2 | G45: RM-J-1150LI26-M19.2 | H45: C8106 | I45: ENERO | J45: 46034 | K45: 26 24 3483 6089006 | L45: 6026 | M45: IMPO | N45: TB-011 | O45: 0 | P45: 0 | Q45: 1200 | R45: 192 | S45: 48 | T45: 1344 | U45: USD | V45: =T45 -> 1344 | W45: 46035 | X45: USA-ZAC | Y45: TDS | Z45: JOHNSON | AA45: ZAC | AB45: M19 | AC45: I | AD45: LAND IMPO | AE45: 67110002 | AF45: NO COMMENTS | AI45: 03 | AJ45: NO | AK45: 0 | AL45: NO | AM45: =VLOOKUP(G45,'[3]Master template02'!$D:$D,1,0) -> RM-J-1150LI26-M19.2
A46: 03 | B46: MXG | C46: 506 | D46: DICEX S.A DE C.V. | E46: Broker | F46: =E46&G46 -> BrokerRM-M-574-SI25-M19 | G46: RM-M-574-SI25-M19 | H46: ALT81851 | I46: ENERO | J46: 46036 | K46: 25-810-3699-6000191 | L46: MEDUBG227383 | M46: IMPO | N46: MEDU7352639 | O46: 0 | P46: 10111.55 | Q46: 3936.89 | R46: 629.9 | S46: 0 | T46: 14678.34 | U46: MXN | V46: =T46/17.283 -> 849.29353 | W46: 46029 | X46: JOHNSON ELECTRIC DOO | Y46: SERBIA | Z46: MEX | AA46: DSV AIR & SEA SA DE CV | AB46: M19 | AC46: I | AD46: SEA IMPO | AE46: 67120000 | AF46: NO COMMENTS | AI46: 03 | AJ46: NO | AK46: 0 | AL46: NO | AM46: =VLOOKUP(G46,'[3]Master template02'!$D:$D,1,0) -> #N/A
A47: 03 | B47: MXG | C47: 508 | D47: DICEX S.A DE C.V. | E47: Broker | F47: =E47&G47 -> BrokerRM-R-002-SI25-M19 | G47: RM-R-002-SI25-M19 | H47: ALT81890 | I47: ENERO | J47: 46037 | K47: 25-810-3699-6000192 | L47: MEDUKJ733824 | M47: IMPO | N47: TXGU4132298 | O47: 0 | P47: 10141.3 | Q47: 2499.3 | R47: 399.89 | S47: 0 | T47: 13040.49 | U47: MXN | V47: =T47/17.283 -> 754.52699 | W47: 46032 | X47: DSV AIR & SEA GERMANY | Y47: GERMANY | Z47: MEX | AA47: DSV AIR & SEA, S.A. DE C.V. | AB47: M19 | AC47: I | AD47: SEA IMPO | AE47: 67120000 | AF47: NO COMMENTS | AI47: 03 | AJ47: NO | AK47: 0 | AL47: NO | AM47: =VLOOKUP(G47,'[3]Master template02'!$D:$D,1,0) -> RM-R-002-SI25-M19
A48: 03 | B48: MXG | C48: 606 | D48: TRANSPORTES L. DOMINGUEZ | E48: Freight | F48: =E48&G48 -> FreightRM-R-011-SI26-M19 | G48: RM-R-011-SI26-M19 | H48: 4626 | I48: ENERO | J48: 46034 | L48: MEDUBG229355 | M48: LAND IMPO | N48: MSMU 7895033 | O48: 0 | P48: 0 | Q48: 36500 | R48: 5840 | S48: 1460 | T48: 40880 | U48: MXN | V48: =T48/17.283 -> 2365.3301 | W48: 9-Jan | X48: MSC SYDNEY VI - NH551A | Y48: ALT | Z48: ZCL | AA48: JOHNSON MX | AB48: M19 | AC48: I | AD48: SEA IMPO | AE48: 67120000 | AF48: NO COMMENTS | AI48: 03 | AJ48: NO | AK48: 0 | AL48: NO | AM48: =VLOOKUP(G48,'[3]Master template02'!$D:$D,1,0) -> #N/A
A49: 03 | B49: MXG | C49: 607 | D49: TRANSPORTES L. DOMINGUEZ | E49: Freight | F49: =E49&G49 -> FreightRM-M-220-SI25-M19-L | G49: RM-M-220-SI25-M19-L | H49: 4632 | I49: ENERO | J49: 46036 | K49: 25-160-1690-6000184 | L49: OTRO | M49: LAND IMPO | N49: CARGA SUELTA | O49: 0 | P49: 0 | Q49: 36500 | R49: 5840 | S49: 1460 | T49: 40880 | U49: MXN | V49: =T49/17.283 -> 2365.3301 | W49: VARIAS | X49: VARIOUS | Y49: ALT | Z49: ZCL | AA49: JOHNSON MX | AB49: M19 | AC49: I | AD49: SEA IMPO | AE49: 67120000 | AF49: NO COMMENTS | AI49: 03 | AJ49: NO | AK49: 0 | AL49: NO | AM49: =VLOOKUP(G49,'[3]Master template02'!$D:$D,1,0) -> RM-M-220-SI25-M19-L
A50: 03 | B50: MXG | C50: 608 | D50: TRANSPORTES L. DOMINGUEZ | E50: Freight | F50: =E50&G50 -> FreightRM-M-223-SI25-M19-L | G50: RM-M-223-SI25-M19-L | H50: 4632 | I50: ENERO | J50: 46036 | K50: 25-160-1690-6000496 | L50: OTRO | M50: LAND IMPO | N50: OTRO | O50: 0 | P50: 0 | Q50: 0 | R50: 0 | S50: 0 | T50: 0 | U50: MXN | V50: =T50/17.283 -> 0 | W50: VARIAS | X50: VARIOUS | Y50: ALT | Z50: ZCL | AA50: JOHNSON MX | AB50: M19 | AC50: I | AD50: SEA IMPO | AE50: 67120000 | AF50: NO COMMENTS | AI50: 03 | AJ50: NO | AK50: 0 | AL50: NO | AM50: =VLOOKUP(G50,'[3]Master template02'!$D:$D,1,0) -> RM-M-223-SI25-M19-L
A51: 03 | B51: MXG | C51: 609 | D51: TRANSPORTES L. DOMINGUEZ | E51: Freight | F51: =E51&G51 -> FreightRM-M-228-SI25-M19-L | G51: RM-M-228-SI25-M19-L | H51: 4632 | I51: ENERO | J51: 46036 | K51: 25-160-1690-6000185 | L51: OTRO | M51: LAND IMPO | N51: OTRO | O51: 0 | P51: 0 | Q51: 0 | R51: 0 | S51: 0 | T51: 0 | U51: MXN | V51: =T51/17.283 -> 0 | W51: VARIAS | X51: VARIOUS | Y51: ALT | Z51: ZCL | AA51: JOHNSON MX | AB51: M19 | AC51: I | AD51: SEA IMPO | AE51: 67120000 | AF51: NO COMMENTS | AI51: 03 | AJ51: NO | AK51: 0 | AL51: NO | AM51: =VLOOKUP(G51,'[3]Master template02'!$D:$D,1,0) -> RM-M-228-SI25-M19-L
A52: 04 | B52: MXG | C52: 622 | D52: TRANSPORTES BRABER,S.A.DE C.V. | E52: FREIGHT | F52: =E52&G52 -> FREIGHTRM-V-028-V1I26-M19.1 | G52: RM-V-028-V1I26-M19.1 | H52: C8054 | I52: FEBRERO | J52: 46031 | L52: 5858 | M52: NAC | N52: S/N | O52: 0 | P52: 0 | Q52: 19000 | R52: 3040 | S52: 0 | T52: 22040 | U52: MXN | V52: =T52/17.407 -> 1266.1573 | W52: 46031 | X52: MTY-ZAC | Y52: REA | Z52: JOHNSON | AA52: ZAC | AB52: M19 | AC52: I | AD52: LAND IMPO | AE52: 67110002 | AF52: NO COMMENTS | AI52: 04 | AJ52: NO | AK52: 0 | AL52: NO | AM52: =VLOOKUP(G52,'[3]Master template02'!$D:$D,1,0) -> RM-V-028-V1I26-M19.1
A53: 04 | B53: MXG | C53: 623 | D53: TRANSPORTES BRABER,S.A.DE C.V. | E53: FREIGHT | F53: =E53&G53 -> FREIGHTRM-V-010-V1I26-M19 | G53: RM-V-010-V1I26-M19 | H53: C8117 | I53: FEBRERO | J53: 46035 | L53: 5955 | M53: NAC | N53: RB-002 | O53: 0 | P53: 0 | Q53: 2000 | R53: 320 | S53: 80 | T53: 2240 | U53: MXN | V53: =T53/17.407 -> 128.68386 | W53: 46036 | X53: SLP-ZAC | Y53: EJOTAF | Z53: JOHNSON | AA53: ZAC | AB53: M19 | AC53: I | AD53: LAND IMPO | AE53: 67110002 | AF53: NO COMMENTS | AI53: 04 | AJ53: NO | AK53: 0 | AL53: NO | AM53: =VLOOKUP(G53,'[3]Master template02'!$D:$D,1,0) -> RM-V-010-V1I26-M19
A54: 04 | B54: MXG | C54: 624 | D54: TRANSPORTES BRABER,S.A.DE C.V. | E54: FREIGHT | F54: =E54&G54 -> FREIGHTRM-V-028-V1I26-M19 | G54: RM-V-028-V1I26-M19 | H54: C8123 | I54: FEBRERO | J54: 46036 | L54: 5939 | M54: NAC | N54: S/N | O54: 0 | P54: 0 | Q54: 19000 | R54: 3040 | S54: 0 | T54: 22040 | U54: MXN | V54: =T54/17.407 -> 1266.1573 | W54: 46036 | X54: MTY-ZAC | Y54: REA | Z54: JOHNSON | AA54: ZAC | AB54: M19 | AC54: I | AD54: LAND IMPO | AE54: 67110002 | AF54: NO COMMENTS | AI54: 04 | AJ54: NO | AK54: 0 | AL54: NO | AM54: =VLOOKUP(G54,'[3]Master template02'!$D:$D,1,0) -> RM-V-028-V1I26-M19
A55: 04 | B55: MXG | C55: 625 | D55: TRANSPORTES BRABER,S.A.DE C.V. | E55: FREIGHT | F55: =E55&G55 -> FREIGHTRM-V-018-V1I26-M01.2 | G55: RM-V-018-V1I26-M01.2 | H55: C8223 | I55: FEBRERO | J55: 46042 | K55: 26-730 3658-6000226 | L55: 6019 | M55: NAC | N55: RB-002 | O55: 0 | P55: 0 | Q55: 19000 | R55: 3040 | S55: 760 | T55: 21280 | U55: MXN | V55: =T55/17.407 -> 1222.4967 | W55: 46042 | X55: QRO-ZAC | Y55: INNOVET | Z55: JOHNSON | AA55: ZAC | AB55: M01 | AC55: I | AD55: LAND IMPO | AE55: 67110002 | AF55: NO COMMENTS | AI55: 04 | AJ55: NO | AK55: 0 | AL55: NO | AM55: =VLOOKUP(G55,'[3]Master template02'!$D:$D,1,0) -> RM-V-018-V1I26-M01.2
A56: 04 | B56: MXG | C56: 626 | D56: TRANSPORTES BRABER,S.A.DE C.V. | E56: FREIGHT | F56: =E56&G56 -> FREIGHTRM-V-028-V1I26-M19.1 | G56: RM-V-028-V1I26-M19.1 | H56: C8248 | I56: FEBRERO | J56: 46043 | L56: 6031 | M56: NAC | N56: S/N | O56: 0 | P56: 0 | Q56: 19000 | R56: 3040 | S56: 0 | T56: 22040 | U56: MXN | V56: =T56/17.407 -> 1266.1573 | W56: 46043 | X56: MTY-ZAC | Y56: REA | Z56: JOHNSON | AA56: ZAC | AB56: M19 | AC56: I | AD56: LAND IMPO | AE56: 67110002 | AF56: NO COMMENTS | AI56: 04 | AJ56: NO | AK56: 0 | AL56: NO | AM56: =VLOOKUP(G56,'[3]Master template02'!$D:$D,1,0) -> RM-V-028-V1I26-M19.1
A57: 04 | B57: MXG | C57: 627 | D57: TRANSPORTES BRABER,S.A.DE C.V. | E57: FREIGHT | F57: =E57&G57 -> FREIGHTRM-J-1155LI26-M19.3 | G57: RM-J-1155LI26-M19.3 | H57: C8150 | I57: FEBRERO | J57: 46038 | K57: 26 24 3483 6089006/26 24 3483 6089011 | L57: 6075 | M57: IMPO | N57: TB-007 | O57: 0 | P57: 0 | Q57: 1200 | R57: 192 | S57: 48 | T57: 1344 | U57: USD | V57: =T57 -> 1344 | W57: 46038 | X57: USA-ZAC | Y57: TDS | Z57: JOHNSON | AA57: ZAC | AB57: M19 | AC57: I | AD57: LAND IMPO | AE57: 67110002 | AF57: NO COMMENTS | AI57: 04 | AJ57: NO | AK57: 0 | AL57: NO | AM57: =VLOOKUP(G57,'[3]Master template02'!$D:$D,1,0) -> RM-J-1155LI26-M19.3
A58: 04 | B58: MXG | C58: 628 | D58: TRANSPORTES BRABER,S.A.DE C.V. | E58: FREIGHT | F58: =E58&G58 -> FREIGHTRM-J-1157LI26-M19.3 | G58: RM-J-1157LI26-M19.3 | H58: C8210 | I58: FEBRERO | J58: 46041 | K58: 26 24 3483 6089009/26 24 3483 608901 | L58: 6132 | M58: IMPO | N58: TB-011 | O58: 0 | P58: 0 | Q58: 1200 | R58: 192 | S58: 48 | T58: 1344 | U58: USD | V58: =T58 -> 1344 | W58: 46042 | X58: USA-ZAC | Y58: TDS | Z58: JOHNSON | AA58: ZAC | AB58: M19 | AC58: I | AD58: LAND IMPO | AE58: 67110002 | AF58: NO COMMENTS | AI58: 04 | AJ58: NO | AK58: 0 | AL58: NO | AM58: =VLOOKUP(G58,'[3]Master template02'!$D:$D,1,0) -> RM-J-1157LI26-M19.3
A59: 04 | B59: MXG | C59: 660 | D59: DICEX S.A DE C.V. | E59: BROKER | F59: =E59&G59 -> BROKERRM-I-0881-AI25-M19 | G59: RM-I-0881-AI25-M19 | H59: GDL47814 | I59: FEBRERO | J59: 46041 | K59: 26-480-3993-6000029 | L59: 885924429827 | M59: AIR IMPO | N59: OTRO | O59: 0 | P59: 7412.85 | Q59: 809.66 | R59: 129.55 | S59: 0 | T59: 8352.06 | U59: MXN | V59: =T59/17.407 -> 479.81042 | W59: 46031 | X59: DICEX SA DE CV | Y59: CHN | Z59: ZCL | AA59: JEG | AB59: M19 | AC59: I | AD59: AIR IMPO | AE59: 67130000 | AF59: NO COMMENTS | AI59: 04 | AJ59: NO | AK59: 0 | AL59: NO | AM59: =VLOOKUP(G59,'[3]Master template02'!$D:$D,1,0) -> RM-I-0881-AI25-M19
A60: 04 | B60: MXG | C60: 661 | D60: DICEX S.A DE C.V. | E60: BROKER | F60: =E60&G60 -> BROKERRM-I-0881-AI25-M19 | G60: RM-I-0881-AI25-M19 | H60: GDL47815 | I60: FEBRERO | J60: 46041 | K60: 26-480-3993-6000026 | L60: 885924429827 | M60: AIR IMPO | N60: OTRO | O60: 0 | P60: 6518.59 | Q60: 809.66 | R60: 129.55 | S60: 0 | T60: 7457.8 | U60: MXN | V60: =T60/17.407 -> 428.43684 | W60: 46031 | X60: DICEX SA DE CV | Y60: USA | Z60: ZCL | AA60: JEG | AB60: M19 | AC60: I | AD60: AIR IMPO | AE60: 67130000 | AF60: NO COMMENTS | AI60: 04 | AJ60: NO | AK60: 0 | AL60: NO | AM60: =VLOOKUP(G60,'[3]Master template02'!$D:$D,1,0) -> RM-I-0881-AI25-M19
A61: 04 | B61: MXG | C61: 674 | D61: DICEX S.A DE C.V. | E61: BROKER | F61: =E61&G61 -> BROKERAF-M-493-SI25-M23-B | G61: AF-M-493-SI25-M23-B | H61: MZO189151 | I61: FEBRERO | J61: 46043 | K61: 26 16 1690 6000985 | L61: MEDURH604627 | M61: IMPO | N61: MSDU6713992 | O61: 0 | P61: 68970.08 | Q61: 2495.78 | R61: 399.32 | S61: 0 | T61: 71865.18 | U61: MXN | V61: =T61/17.407 -> 4128.5219 | W61: 21-Jan-26 | X61: SHANGHAI KRAH ELECTRONICS CO; LTD | Y61: CHN | Z61: ZCL | AA61: JEG | AB61: M23 | AC61: I | AD61: SEA IMPO | AE61: 67120000 | AF61: CM4592461 | AG61: 67115005 | AH61: 35434.08 | AI61: 04 | AJ61: NO | AK61: 0 | AL61: NO | AM61: =VLOOKUP(G61,'[3]Master template02'!$D:$D,1,0) -> #N/A
A62: 04 | B62: MXG | C62: 690 | D62: DICEX S.A DE C.V. | E62: BROKER | F62: =E62&G62 -> BROKERAF-M-493-SI25-M23-B | G62: AF-M-493-SI25-M23-B | H62: MZO189599 | I62: FEBRERO | J62: 46046 | K62: 26 16 1690 6000986 | L62: MEDURH604627 | M62: IMPO | N62: MSDU8958443 | O62: 0 | P62: 68970.08 | Q62: 2592.62 | R62: 414.81 | S62: 0 | T62: 71977.51 | U62: MXN | V62: =T62/17.407 -> 4134.975 | W62: 24-Jan-26 | X62: MULTITECH MACHINERY LTD. | Y62: CHN | Z62: ZCL | AA62: JEG | AB62: M23 | AC62: I | AD62: SEA IMPO | AE62: 67120000 | AF62: CM4591848 | AG62: 67115005 | AH62: 35434.08 | AI62: 04 | AJ62: NO | AK62: 0 | AL62: NO | AM62: =VLOOKUP(G62,'[3]Master template02'!$D:$D,1,0) -> #N/A
A63: 04 | B63: MXG | C63: 750 | D63: TRANSPORTES L. DOMINGUEZ | E63: FREIGHT | F63: =E63&G63 -> FREIGHT RM-R-013-SI26-M19 | G63: RM-R-013-SI26-M19 | H63: 4653 | I63: FEBRERO | J63: 46042 | L63: OTRO | M63: LAND IMPO | N63: CAAU 6961241 | O63: 0 | P63: 0 | Q63: 36500 | R63: 5840 | S63: 1460 | T63: 40880 | U63: MXN | V63: =T63/17.407 -> 2348.4805 | W63: VARIAS | X63: VARIOUS | Y63: ALT | Z63: ZAC | AA63: JOHNSON ELECTRIC GROUP MEXICO | AB63: M19 | AC63: I | AD63: SEA IMPO | AE63: 67120000 | AF63: NO COMMENTS | AI63: 04 | AJ63: NO | AK63: 0 | AL63: NO | AM63: =VLOOKUP(G63,'[3]Master template02'!$D:$D,1,0) -> #N/A
A64: 05 | B64: MXG | C64: 771 | D64: TRANSPORTES BRABER,S.A.DE C.V. | E64: FREIGHT | F64: =E64&G64 -> FREIGHTRM-V-018-V1I26-M01.2 | G64: RM-V-018-V1I26-M01.2 | H64: C8287 | I64: FEBRERO | J64: 46045 | K64: 26-730 3658-6000226 | L64: 6020 | M64: NAC | N64: RB-002 | O64: 0 | P64: 0 | Q64: 19000 | R64: 3040 | S64: 760 | T64: 21280 | U64: MXN | V64: =T64/17.2315 -> 1234.9476 | W64: 46045 | X64: QRO-ZAC | Y64: INNOVET | Z64: JOHNSON | AA64: ZAC | AB64: M01 | AC64: I | AD64: LAND IMPO | AE64: 67110002 | AF64: NO COMMENTS | AI64: 05 | AJ64: NO | AK64: 0 | AL64: NO | AM64: =VLOOKUP(G64,'[3]Master template02'!$D:$D,1,0) -> RM-V-018-V1I26-M01.2
A65: 05 | B65: MXG | C65: 773 | D65: TRANSPORTES BRABER,S.A.DE C.V. | E65: FREIGHT | F65: =E65&G65 -> FREIGHTRM-V-003-V1I26-M19.4 | G65: RM-V-003-V1I26-M19.4 | H65: C8295 | I65: FEBRERO | J65: 46045 | K65: 26-730-3658-6000204 | L65: 6198 | M65: NAC | N65: RB-002 | O65: 0 | P65: 0 | Q65: 9650 | R65: 1544 | S65: 386 | T65: 10808 | U65: MXN | V65: =T65/17.2315 -> 627.2234 | W65: 46045 | X65: SLP-ZAC | Y65: ASAHI | Z65: JOHNSON | AA65: ZAC | AB65: M19 | AC65: I | AD65: LAND IMPO | AE65: 67110002 | AF65: NO COMMENTS | AI65: 05 | AJ65: NO | AK65: 0 | AL65: NO | AM65: =VLOOKUP(G65,'[3]Master template02'!$D:$D,1,0) -> RM-V-003-V1I26-M19.4
A66: 05 | B66: MXG | C66: 774 | D66: TRANSPORTES BRABER,S.A.DE C.V. | E66: FREIGHT | F66: =E66&G66 -> FREIGHTRM-V-003-V1I26-M19.4 | G66: RM-V-003-V1I26-M19.4 | H66: C8372 | I66: FEBRERO | J66: 46048 | K66: 26-730 3658-6000204 | L66: 6146 | M66: NAC | N66: S/N | O66: 0 | P66: 0 | Q66: 9650 | R66: 1544 | S66: 0 | T66: 11194 | U66: MXN | V66: =T66/17.2315 -> 649.62423 | W66: 46049 | X66: SLP-ZAC | Y66: ASAHI | Z66: JOHNSON | AA66: ZAC | AB66: M19 | AC66: I | AD66: LAND IMPO | AE66: 67110002 | AF66: NO COMMENTS | AI66: 05 | AJ66: NO | AK66: 0 | AL66: NO | AM66: =VLOOKUP(G66,'[3]Master template02'!$D:$D,1,0) -> RM-V-003-V1I26-M19.4
A67: 05 | B67: MXG | C67: 777 | D67: TRANSPORTES BRABER,S.A.DE C.V. | E67: FREIGHT | F67: =E67&G67 -> FREIGHTRM-J-1158LI26-M19.3 | G67: RM-J-1158LI26-M19.3 | H67: C8370 | I67: FEBRERO | J67: 46048 | K67: 26 24 3483 6089009 | L67: 6208 | M67: IMPO | N67: TB-011 | O67: 0 | P67: 0 | Q67: 1200 | R67: 192 | S67: 48 | T67: 1344 | U67: USD | V67: =T67 -> 1344 | W67: 46049 | X67: USA-ZAC | Y67: TDS | Z67: JOHNSON | AA67: ZAC | AB67: M19 | AC67: I | AD67: LAND IMPO | AE67: 67110002 | AF67: NO COMMENTS | AI67: 05 | AJ67: NO | AK67: 0 | AL67: NO | AM67: =VLOOKUP(G67,'[3]Master template02'!$D:$D,1,0) -> RM-J-1158LI26-M19.3
A68: 05 | B68: MXG | C68: 779 | D68: TRANSPORTES BRABER,S.A.DE C.V. | E68: FREIGHT | F68: =E68&G68 -> FREIGHTRM-J-1181LI26-M19.3 | G68: RM-J-1181LI26-M19.3 | H68: C8455 | I68: FEBRERO | J68: 46052 | K68: 26 24 3483 6089013/26 24 3483 6089018 | L68: 6317 | M68: IMPO | N68: TB-011 | O68: 0 | P68: 0 | Q68: 1200 | R68: 192 | S68: 48 | T68: 1344 | U68: USD | V68: =T68 -> 1344 | W68: 46052 | X68: USA-ZAC | Y68: TDS | Z68: JOHNSON | AA68: ZAC | AB68: M19 | AC68: I | AD68: LAND IMPO | AE68: 67110002 | AF68: NO COMMENTS | AI68: 05 | AJ68: NO | AK68: 0 | AL68: NO | AM68: =VLOOKUP(G68,'[3]Master template02'!$D:$D,1,0) -> RM-J-1181LI26-M19.3
A69: 05 | B69: MXG | C69: 824 | D69: DICEX S.A DE C.V. | E69: BROKER | F69: =E69&G69 -> BROKERRM-M-573-SI25-M19-B | G69: RM-M-573-SI25-M19-B | H69: MZO190153 | I69: FEBRERO | J69: 46052 | K69: 26 16 1690 6002216 | L69: COSU6438984020 | M69: IMPO | N69: CSGU6508221 | O69: 0 | P69: 17295.72 | Q69: 7531.77 | R69: 1205.08 | S69: 0 | T69: 26032.57 | U69: MXN | V69: =T69/17.2315 -> 1510.7547 | W69: 30-Jan-26 | X69: JOHNSON ELECTRIC INDUSTRIAL MANUFACTORY LIMITED | Y69: CHN | Z69: ZCL | AA69: JEG | AB69: M19 | AC69: I | AD69: SEA IMPO | AE69: 67120000 | AF69: NO COMMENTS | AI69: 05 | AJ69: NO | AK69: 0 | AL69: NO | AM69: =VLOOKUP(G69,'[3]Master template02'!$D:$D,1,0) -> RM-M-573-SI25-M19-B
A70: 05 | B70: MXG | C70: 828 | D70: DICEX S.A DE C.V. | E70: BROKER | F70: =E70&G70 -> BROKERRM-M-011-SI26-M19-B | G70: RM-M-011-SI26-M19-B | H70: MZO190160 | I70: FEBRERO | J70: 46052 | K70: 26 16 1690 6002198 | L70: MEDUYM485320 | M70: IMPO | N70: MSMU5908635 | O70: 0 | P70: 20746.97 | Q70: 7300.89 | R70: 1168.15 | S70: 0 | T70: 29216.01 | U70: MXN | V70: =T70/17.2315 -> 1695.5001 | W70: 30-Jan-26 | X70: JOHNSON ELECTRIC INDUSTRIAL MANUFACTORY LIMITED | Y70: CHN | Z70: ZCL | AA70: JEG | AB70: M19 | AC70: I | AD70: SEA IMPO | AE70: 67120000 | AF70: NO COMMENTS | AI70: 05 | AJ70: NO | AK70: 0 | AL70: NO | AM70: =VLOOKUP(G70,'[3]Master template02'!$D:$D,1,0) -> RM-M-011-SI26-M19-B
A71: 05 | B71: MXG | C71: 829 | D71: DICEX S.A DE C.V. | E71: BROKER | F71: =E71&G71 -> BROKERRM-M-562-SI25-M19-B | G71: RM-M-562-SI25-M19-B | H71: MZO190161 | I71: FEBRERO | J71: 46052 | K71: 26 16 1690 6000721 | L71: MEDUYM382477 | M71: IMPO | N71: MSMU4424718 | O71: 0 | P71: 31816.04 | Q71: 7674.94 | R71: 1227.99 | S71: 0 | T71: 40718.97 | U71: MXN | V71: =T71/17.2315 -> 2363.0543 | W71: 30-Jan-26 | X71: JOHNSON ELECTRIC INDUSTRIAL MANUFACTORY LIMITED | Y71: CHN | Z71: ZCL | AA71: JEG | AB71: M19 | AC71: I | AD71: SEA IMPO | AE71: 67120000 | AF71: 8649437 | AG71: 67115005 | AH71: 18366.56 | AI71: 05 | AJ71: NO | AK71: 0 | AL71: NO | AM71: =VLOOKUP(G71,'[3]Master template02'!$D:$D,1,0) -> RM-M-562-SI25-M19-B
A72: 05 | B72: MXG | C72: 830 | D72: DICEX S.A DE C.V. | E72: BROKER | F72: =E72&G72 -> BROKERRM-M-562-SI25-M19-B | G72: RM-M-562-SI25-M19-B | H72: MZO190169 | I72: FEBRERO | J72: 46052 | K72: 26 16 1690 6000716 | L72: COSU6437870991 | M72: IMPO | N72: OOLU9983140 | O72: 0 | P72: 28622.44 | Q72: 5462.21 | R72: 873.95 | S72: 0 | T72: 34958.6 | U72: MXN | V72: =T72/17.2315 -> 2028.7613 | W72: 30-Jan-26 | X72: JOHNSON ELECTRIC INDUSTRIAL MANUFACTORY LIMITED | Y72: CHN | Z72: ZCL | AA72: JEG | AB72: M19 | AC72: I | AD72: SEA IMPO | AE72: 67120000 | AF72: D1392099/D1392045 | AG72: 67115005 | AH72: 22792.6 | AI72: 05 | AJ72: NO | AK72: 0 | AL72: NO | AM72: =VLOOKUP(G72,'[3]Master template02'!$D:$D,1,0) -> RM-M-562-SI25-M19-B
A73: 05 | B73: MXG | C73: 908 | D73: TRANSPORTES L. DOMINGUEZ | E73: FREIGHT | F73: =E73&G73 -> FREIGHT RM-R-014-SI26-M19 | G73: RM-R-014-SI26-M19 | H73: 4677 | I73: FEBRERO | J73: 46048 | L73: MEDUBG229371 | M73: LAND IMPO | N73: BEAU 4277372 | O73: 0 | P73: 0 | Q73: 36500 | R73: 5840 | S73: 1460 | T73: 40880 | U73: MXN | V73: =T73/17.2315 -> 2372.3994 | W73: 46050 | X73: MSC ANSHIKA VI - NH601A | Y73: ALT | Z73: ZAC | AA73: JEG | AB73: M19 | AC73: I | AD73: SEA IMPO | AE73: 67120000 | AF73: NO COMMENTS | AI73: 05 | AJ73: NO | AK73: 0 | AL73: NO | AM73: =VLOOKUP(G73,'[3]Master template02'!$D:$D,1,0) -> #N/A
A74: 05 | B74: MXG | C74: 909 | D74: TRANSPORTES L. DOMINGUEZ | E74: FREIGHT | F74: =E74&G74 -> FREIGHT RM-R-001-SI25-M19 | G74: RM-R-001-SI25-M19 | H74: 4701 | I74: FEBRERO | J74: 46052 | L74: OTRO | M74: LAND IMPO | N74: HLBU 3026847 | O74: 0 | P74: 0 | Q74: 36500 | R74: 5840 | S74: 1460 | T74: 40880 | U74: MXN | V74: =T74/17.2315 -> 2372.3994 | W74: 46053 | X74: GSL MARIA | Y74: ALT | Z74: ZAC | AA74: JEG | AB74: M19 | AC74: I | AD74: SEA IMPO | AE74: 67120000 | AF74: NO COMMENTS | AI74: 05 | AJ74: NO | AK74: 0 | AL74: NO | AM74: =VLOOKUP(G74,'[3]Master template02'!$D:$D,1,0) -> RM-R-001-SI25-M19
A75: 05 | B75: MXG | C75: 910 | D75: TRANSPORTES L. DOMINGUEZ | E75: FREIGHT | F75: =E75&G75 -> FREIGHT FG-A-0004-SE26-M19 | G75: FG-A-0004-SE26-M19 | H75: 4703 | I75: FEBRERO | J75: 46052 | L75: OTRO | M75: SEA EXPO | N75: HLBU 1534319 | O75: 0 | P75: 0 | Q75: 58000 | R75: 5600 | S75: 1400 | T75: 39200 | U75: MXN | V75: =T75/17.2315 -> 2274.9035 | W75: 46051 | X75: JEG | Y75: ZAC | Z75: ALT | AA75: JEG | AB75: M19 | AC75: O | AD75: SEA EXPO | AE75: 59220000 | AF75: NO COMMENTS | AI75: 05 | AJ75: NO | AK75: 0 | AL75: NO | AM75: =VLOOKUP(G75,'[3]Master template02'!$D:$D,1,0) -> #N/A
A76: 05 | B76: MXG | C76: 911 | D76: TRANSPORTES L. DOMINGUEZ | E76: FREIGHT | F76: =E76&G76 -> FREIGHT FG-A-0005-SE26-M19 | G76: FG-A-0005-SE26-M19 | H76: 4703 | I76: FEBRERO | J76: 46052 | L76: OTRO | M76: SEA EXPO | N76: SEKU 1167017 | O76: 0 | P76: 0 | Q76: 0 | R76: 0 | S76: 0 | T76: 0 | U76: MXN | V76: =T76/17.2315 -> 0 | W76: 46051 | X76: JEG | Y76: ZAC | Z76: ALT | AA76: JEG | AB76: M19 | AC76: O | AD76: SEA EXPO | AE76: 59220000 | AF76: NO COMMENTS | AI76: 05 | AJ76: NO | AK76: 0 | AL76: NO | AM76: =VLOOKUP(G76,'[3]Master template02'!$D:$D,1,0) -> FG-A-0005-SE26-M19
A77: 06 | B77: MXG | C77: 924 | D77: TRANSPORTES BRABER,S.A.DE C.V. | E77: FREIGHT | F77: =E77&G77 -> FREIGHTRM-J-1187LI26-M19.2 | G77: RM-J-1187LI26-M19.2 | H77: C8503 | I77: FEBRERO | J77: 46056 | K77: 26 24 3483 6089016 | L77: 6362 | M77: IMPO | N77: TB-036 | O77: 0 | P77: 0 | Q77: 1339.92 | R77: 214.38 | S77: 53.59 | T77: 1500.71 | U77: USD | V77: =T77 -> 1500.71 | W77: 46057 | X77: USA-ZAC | Y77: TDS | Z77: JOHNSON | AA77: ZAC | AB77: M19 | AC77: I | AD77: LAND IMPO | AE77: 67110002 | AF77: NO COMMENTS | AI77: 06 | AJ77: NO | AK77: 0 | AL77: NO | AM77: =VLOOKUP(G77,'[3]Master template02'!$D:$D,1,0) -> RM-J-1187LI26-M19.2
A78: 06 | B78: MXG | C78: 945 | D78: DICEX S.A DE C.V. | E78: BROKER | F78: =E78&G78 -> BROKERFG-A-0004-SE26-M19 | G78: FG-A-0004-SE26-M19 | H78: ALT82402 | I78: FEBRERO | J78: 46060 | K78: 25-810-3699-6021155 | L78: 30741187 | M78: EXPO | N78: HLBU1534319 | O78: 0 | P78: 12001.17 | Q78: 3164.85 | R78: 506.37 | S78: 0 | T78: 15672.39 | U78: MXN | V78: =T78/17.1723 -> 912.65526 | W78: 46057 | X78: JOHNSON ELECTRIC GROUP MEXICO S DE RL DE CV | Y78: MEX | Z78: USA | AA78: JOHNSON ELECTRIC NORTH AMERICA, INC | AB78: M19 | AC78: O | AD78: SEA EXPO | AE78: 59220000 | AF78: NO COMMENTS | AI78: 06 | AJ78: NO | AK78: 0 | AL78: NO | AM78: =VLOOKUP(G78,'[3]Master template02'!$D:$D,1,0) -> FG-A-0004-SE26-M19
A79: 06 | B79: MXG | C79: 956 | D79: DICEX S.A DE C.V. | E79: BROKER | F79: =E79&G79 -> BROKERRM-M-001-SI26-M19-L-B | G79: RM-M-001-SI26-M19-L-B | H79: MZO190396 | I79: FEBRERO | J79: 46056 | K79: 26 16 1690 6002261 | L79: HLCUSEL251163087 | M79: IMPO | N79: HLCUSEL251163087 | O79: 0 | P79: 9751.11 | Q79: 2449.66 | R79: 391.95 | S79: 0 | T79: 12592.72 | U79: MXN | V79: =T79/17.1723 -> 733.31586 | W79: 46056 | X79: JOHNSON ELECTRIC PVT LTD | Y79: IND | Z79: ZCL | AA79: JEG | AB79: M19 | AC79: I | AD79: SEA IMPO | AE79: 67120000 | AF79: NO COMMENTS | AI79: 06 | AJ79: NO | AK79: 0 | AL79: NO | AM79: =VLOOKUP(G79,'[3]Master template02'!$D:$D,1,0) -> #N/A
A80: 06 | B80: MXG | C80: 959 | D80: DICEX S.A DE C.V. | E80: BROKER | F80: =E80&G80 -> BROKERRM-M-567-SI25-M19-B | G80: RM-M-567-SI25-M19-B | H80: MZO190487 | I80: FEBRERO | J80: 46057 | K80: 26 16 1690 6002927 | L80: MEDUYM485346 | M80: IMPO | N80: CAXU9227982 | O80: 0 | P80: 0 | Q80: 1823.11 | R80: 291.7 | S80: 0 | T80: 2114.81 | U80: MXN | V80: =T80/17.1723 -> 123.1524 | W80: 46057 | X80: JOHNSON ELECTRIC INDUSTRIAL MANUFACTORY LIMITED | Y80: CHN | Z80: ZCL | AA80: JEG | AB80: M19 | AC80: I | AD80: SEA IMPO | AE80: 67120000 | AF80: NO COMMENTS | AI80: 06 | AJ80: NO | AK80: 0 | AL80: NO | AM80: =VLOOKUP(G80,'[3]Master template02'!$D:$D,1,0) -> RM-M-567-SI25-M19-B
A81: 06 | B81: MXG | C81: 962 | D81: DICEX S.A DE C.V. | E81: BROKER | F81: =E81&G81 -> BROKERRM-M-540-SI25-M19-B | G81: RM-M-540-SI25-M19-B | H81: MZO190601 | I81: FEBRERO | J81: 46058 | K81: 26 16 1690 6000179 | L81: MEDURH708055 | M81: IMPO | N81: TRHU6556188 | O81: 0 | P81: 14017.17 | Q81: 3858.68 | R81: 617.38 | S81: 0 | T81: 18493.23 | U81: MXN | V81: =T81/17.1723 -> 1076.9221 | W81: 46058 | X81: JOHNSON ELECTRIC INDUSTRIAL MANUFACTORY LIMITED | Y81: CHN | Z81: ZCL | AA81: JEG | AB81: M19 | AC81: I | AD81: SEA IMPO | AE81: 67120000 | AF81: NO COMMENTS | AI81: 06 | AJ81: NO | AK81: 0 | AL81: NO | AM81: =VLOOKUP(G81,'[3]Master template02'!$D:$D,1,0) -> RM-M-540-SI25-M19-B
A82: 06 | B82: MXG | C82: 1003 | D82: SOLUTIONS CARGO | E82: FREIGHT | F82: =E82&G82 -> FREIGHT RM-V-020-V1I26-M19.1 | G82: RM-V-020-V1I26-M19.1 | H82: 3385 | I82: FEBRERO | J82: 46059 | K82: 26-730-3658-6000232 | L82: OTRO | M82: NACIONAL | N82: OTRO | O82: 0 | P82: 0 | Q82: 2800 | R82: 448 | S82: 112 | T82: 3136 | U82: MXN | V82: =T82/17.1723 -> 182.61968 | W82: 46052 | X82: KRAYDEN DE MEXICO | Y82: GDL | Z82: ZAC | AA82: JOHNSON ELECTRIC GROUP MEXICO | AB82: M19 | AC82: I | AD82: LAND IMPO | AE82: 67110002 | AF82: NO COMMENTS | AI82: 06 | AJ82: NO | AK82: 0 | AL82: NO | AM82: =VLOOKUP(G82,'[3]Master template02'!$D:$D,1,0) -> RM-V-020-V1I26-M19.1
A83: 06 | B83: MXG | C83: 1004 | D83: TRANSPORTES L. DOMINGUEZ | E83: FREIGHT | F83: =E83&G83 -> FREIGHT RM-R-004-SI25-M19 | G83: RM-R-004-SI25-M19 | H83: 4716 | I83: FEBRERO | J83: 46056 | L83: OTRO | M83: LAND IMPO | N83: HAMU 3024510 | O83: 0 | P83: 0 | Q83: 36500 | R83: 5840 | S83: 1460 | T83: 40880 | U83: MXN | V83: =T83/17.1723 -> 2380.578 | W83: 46057 | X83: GSL MARIA | Y83: ALT | Z83: ZAC | AA83: JEG | AB83: M19 | AC83: I | AD83: SEA IMPO | AE83: 67120000 | AF83: NO COMMENTS | AI83: 06 | AJ83: NO | AK83: 0 | AL83: NO | AM83: =VLOOKUP(G83,'[3]Master template02'!$D:$D,1,0) -> RM-R-004-SI25-M19
A84: 06 | B84: MXG | C84: 1005 | D84: TRANSPORTES L. DOMINGUEZ | E84: FREIGHT | F84: =E84&G84 -> FREIGHT RM-R-005-SI25-M19 | G84: RM-R-005-SI25-M19 | H84: 4717 | I84: FEBRERO | J84: 46056 | L84: OTRO | M84: LAND IMPO | N84: ECMU 5012151 | O84: 0 | P84: 0 | Q84: 36500 | R84: 5840 | S84: 1460 | T84: 40880 | U84: MXN | V84: =T84/17.1723 -> 2380.578 | W84: 46057 | X84: OOCL VERACRUZ | Y84: ALT | Z84: ZAC | AA84: JEG | AB84: M19 | AC84: I | AD84: SEA IMPO | AE84: 67120000 | AF84: NO COMMENTS | AI84: 06 | AJ84: NO | AK84: 0 | AL84: NO | AM84: =VLOOKUP(G84,'[3]Master template02'!$D:$D,1,0) -> RM-R-005-SI25-M19
A85: 07 | B85: MXG | C85: 1032 | D85: TRANSPORTES BRABER,S.A.DE C.V. | E85: FREIGHT | F85: =E85&G85 -> FREIGHTRM-V-060-V1I26-M19 | G85: RM-V-060-V1I26-M19 | H85: C8692 | I85: FEBRERO | J85: 46065 | K85: 26-730 3658-6001044 | L85: 6395 | M85: NAC | N85: S/N | O85: 0 | P85: 0 | Q85: 19000 | R85: 3040 | S85: 0 | T85: 22040 | U85: MXN | V85: =T85/17.2162 -> 1280.1896 | W85: 46065 | X85: MTY-ZAC | Y85: REA | Z85: JOHNSON | AA85: ZAC | AB85: M19 | AC85: I | AD85: LAND IMPO | AE85: 67110002 | AF85: NO COMMENTS | AI85: 07 | AJ85: NO | AK85: 0 | AL85: NO | AM85: =VLOOKUP(G85,'[3]Master template02'!$D:$D,1,0) -> RM-V-060-V1I26-M19
A86: 07 | B86: MXG | C86: 1053 | D86: DICEX S.A DE C.V. | E86: BROKER | F86: =E86&G86 -> BROKERRM-I-1048-AI26-M19 | G86: RM-I-1048-AI26-M19 | H86: GDL47992 | I86: FEBRERO | J86: 46062 | K86: 26-480-3993-6000058 | L86: 888135367223 | M86: AIR IMPO | N86: OTRO | O86: 0 | P86: 4191.49 | Q86: 794.17 | R86: 127.07 | S86: 0 | T86: 5112.73 | U86: MXN | V86: =T86/17.2162 -> 296.97204 | W86: 46042 | X86: DICEX SA DE CV | Y86: USA | Z86: ZCL | AA86: JEG | AB86: M19 | AC86: I | AD86: AIR IMPO | AE86: 67130000 | AF86: NO COMMENTS | AI86: 07 | AJ86: NO | AK86: 0 | AL86: NO | AM86: =VLOOKUP(G86,'[3]Master template02'!$D:$D,1,0) -> RM-I-1048-AI26-M19
A87: 07 | B87: MXG | C87: 1054 | D87: DICEX S.A DE C.V. | E87: BROKER | F87: =E87&G87 -> BROKERRM-I-1048-AI26-M19 | G87: RM-I-1048-AI26-M19 | H87: GDL47993 | I87: FEBRERO | J87: 46062 | K87: 26-480-3993-6000101 | L87: 887824636971 | M87: AIR IMPO | N87: OTRO | O87: 0 | P87: 4135.2 | Q87: 771.44 | R87: 123.43 | S87: 0 | T87: 5030.07 | U87: MXN | V87: =T87/17.2162 -> 292.17075 | W87: 46050 | X87: DICEX SA DE CV | Y87: USA | Z87: ZCL | AA87: JEG | AB87: M19 | AC87: I | AD87: AIR IMPO | AE87: 67130000 | AF87: NO COMMENTS | AI87: 07 | AJ87: NO | AK87: 0 | AL87: NO | AM87: =VLOOKUP(G87,'[3]Master template02'!$D:$D,1,0) -> RM-I-1048-AI26-M19
A88: 07 | B88: MXG | C88: 1064 | D88: DICEX S.A DE C.V. | E88: BROKER | F88: =E88&G88 -> BROKERRM-M-575-SI25-M19-B | G88: RM-M-575-SI25-M19-B | H88: MZO191040 | I88: FEBRERO | J88: 46063 | K88: 26 16 1690 6003204 | L88: OOLU2038304190 | M88: IMPO | N88: OERU4257315 | O88: 0 | P88: 0 | Q88: 2401.94 | R88: 384.31 | S88: 0 | T88: 2786.25 | U88: MXN | V88: =T88/17.2162 -> 161.83885 | W88: 46063 | X88: JOHNSON ELECTRIC INDUSTRIAL MANUFACTORY LIMITED | Y88: CHN | Z88: ZCL | AA88: JEG | AB88: M19 | AC88: I | AD88: SEA IMPO | AE88: 67120000 | AF88: NO COMMENTS | AI88: 07 | AJ88: NO | AK88: 0 | AL88: NO | AM88: =VLOOKUP(G88,'[3]Master template02'!$D:$D,1,0) -> #N/A
A89: 07 | B89: MXG | C89: 1066 | D89: DICEX S.A DE C.V. | E89: BROKER | F89: =E89&G89 -> BROKERRM-M-567-SI25-M19-B | G89: RM-M-567-SI25-M19-B | H89: MZO191243 | I89: FEBRERO | J89: 46065 | K89: 26 16 1690 6002217 | L89: MEDUYM485346 | M89: IMPO | N89: CAXU9227982 | O89: 0 | P89: 34930.19 | Q89: 4679.75 | R89: 748.76 | S89: 0 | T89: 40358.7 | U89: MXN | V89: =T89/17.2162 -> 2344.2281 | W89: 46065 | X89: JOHNSON ELECTRIC INDUSTRIAL MANUFACTORY LIMITED | Y89: CHN | Z89: ZCL | AA89: JEG | AB89: M19 | AC89: I | AD89: SEA IMPO | AE89: 67120000 | AF89: 8666791 | AG89: 67115005 | AH89: 24631.79 | AI89: 07 | AJ89: NO | AK89: 0 | AL89: NO | AM89: =VLOOKUP(G89,'[3]Master template02'!$D:$D,1,0) -> RM-M-567-SI25-M19-B
A90: 07 | B90: MXG | C90: 1067 | D90: DICEX S.A DE C.V. | E90: BROKER | F90: =E90&G90 -> BROKERRM-M-583-SI25-M19-B | G90: RM-M-583-SI25-M19-B | H90: MZO191256 | I90: FEBRERO | J90: 46065 | K90: 26 16 1690 6002929 | L90: COSU6439565731 | M90: IMPO | N90: CSNU5795810 | O90: 0 | P90: 0 | Q90: 2401.94 | R90: 384.31 | S90: 0 | T90: 2786.25 | U90: MXN | V90: =T90/17.2162 -> 161.83885 | W90: 46065 | X90: JOHNSON ELECTRIC INDUSTRIAL MANUFACTORY LIMITED | Y90: CHN | Z90: ZCL | AA90: JEG | AB90: M19 | AC90: I | AD90: SEA IMPO | AE90: 67120000 | AF90: NO COMMENTS | AI90: 07 | AJ90: NO | AK90: 0 | AL90: NO | AM90: =VLOOKUP(G90,'[3]Master template02'!$D:$D,1,0) -> #N/A
A91: 07 | B91: MXG | C91: 1068 | D91: DICEX S.A DE C.V. | E91: BROKER | F91: =E91&G91 -> BROKERRM-M-573-SI25-M19-B | G91: RM-M-573-SI25-M19-B | H91: MZO191257 | I91: FEBRERO | J91: 46065 | K91: 26 16 1690 6002215 | L91: OOLU2038301701 | M91: IMPO | N91: OOLU6938830 | O91: 0 | P91: 19043.27 | Q91: 3472.14 | R91: 555.54 | S91: 0 | T91: 23070.95 | U91: MXN | V91: =T91/17.2162 -> 1340.0721 | W91: 46065 | X91: JOHNSON ELECTRIC INDUSTRIAL MANUFACTORY LIMITED | Y91: CHN | Z91: ZCL | AA91: JEG | AB91: M19 | AC91: I | AD91: SEA IMPO | AE91: 67120000 | AF91: NO COMMENTS | AI91: 07 | AJ91: NO | AK91: 0 | AL91: NO | AM91: =VLOOKUP(G91,'[3]Master template02'!$D:$D,1,0) -> RM-M-573-SI25-M19-B
A92: 07 | B92: MXG | C92: 1118 | D92: SOLUTIONS CARGO | E92: FREIGHT | F92: =E92&G92 -> FREIGHT RM-V-020-V1I26-M19.1 | G92: RM-V-020-V1I26-M19.1 | H92: 3385 | I92: FEBRERO | J92: 46059 | K92: 26-730-3658-6000232 | L92: OTRO | M92: NACIONAL | N92: OTRO | O92: 0 | P92: 0 | Q92: 20200 | R92: 3232 | S92: 808 | T92: 22624 | U92: MXN | V92: =T92/17.2162 -> 1314.1111 | W92: 46052 | X92: KRAYDEN DE MEXICO | Y92: GDL | Z92: ZAC | AA92: JOHNSON ELECTRIC GROUP MEXICO | AB92: M19 | AC92: I | AD92: LAND IMPO | AE92: 67110002 | AF92: NO COMMENTS | AI92: 07 | AJ92: NO | AK92: 0 | AL92: NO | AM92: =VLOOKUP(G92,'[3]Master template02'!$D:$D,1,0) -> RM-V-020-V1I26-M19.1
A93: 07 | B93: MXG | C93: 1127 | D93: TRANSPORTES L. DOMINGUEZ | E93: FREIGHT | F93: =E93&G93 -> FREIGHT FG-A-0004-SE26-M19 | G93: FG-A-0004-SE26-M19 | H93: 4703 | I93: FEBRERO | J93: 46052 | L93: OTRO | M93: SEA EXPO | N93: HLBU 1534319 | O93: 0 | P93: 0 | Q93: 0 | R93: 3680 | S93: 920 | T93: 25760 | U93: MXN | V93: =T93/17.2162 -> 1496.2651 | W93: 46051 | X93: JEG | Y93: ZAC | Z93: ALT | AA93: JEG | AB93: M19 | AC93: O | AD93: SEA EXPO | AE93: 59220000 | AF93: NO COMMENTS | AI93: 07 | AJ93: NO | AK93: 0 | AL93: NO | AM93: =VLOOKUP(G93,'[3]Master template02'!$D:$D,1,0) -> #N/A
A94: 08 | B94: MXG | C94: 1157 | D94: TRANSPORTES BRABER,S.A.DE C.V. | E94: FREIGHT | F94: =E94&G94 -> FREIGHTRM-V-018-V1I26-M01.2 | G94: RM-V-018-V1I26-M01.2 | H94: C8866 | I94: MARZO | J94: 46073 | K94: 26-730-3658-6000226 | L94: 6464 | M94: NAC | N94: S/N | O94: 0 | P94: 0 | Q94: 19000 | R94: 3040 | S94: 0 | T94: 22040 | U94: MXN | V94: =T94/17.5445 -> 1256.2341 | W94: 46073 | X94: QRO-ZAC | Y94: INNOVET | Z94: JOHNSON | AA94: ZAC | AB94: M01 | AC94: I | AD94: LAND IMPO | AE94: 67110002 | AF94: NO COMMENTS | AI94: 08 | AJ94: NO | AK94: 0 | AL94: NO
A95: 08 | B95: MXG | C95: 1161 | D95: TRANSPORTES BRABER,S.A.DE C.V. | E95: FREIGHT | F95: =E95&G95 -> FREIGHTFG-R-2138LE25.M19 | G95: FG-R-2138LE25.M19 | H95: C8831 | I95: MARZO | J95: 46071 | K95: 26-24-323 | L95: 6692 | M95: EXPO | N95: TB-029 | O95: 0 | P95: 0 | Q95: 5900 | R95: 944 | S95: 236 | T95: 6608 | U95: USD | V95: =T95 -> 6608 | W95: 46072 | X95: ZAC-KENTUCKY | Y95: JOHNSON | Z95: DRAIN KY USA | AA95: ZAC | AB95: M19 | AC95: O | AD95: LAND EXPO | AE95: 59210003 | AF95: NO COMMENTS | AI95: 08 | AJ95: NO | AK95: 0 | AL95: NO
A96: 08 | B96: MXG | C96: 1208 | D96: DICEX S.A DE C.V. | E96: BROKER | F96: =E96&G96 -> BROKERRM-A-0021AI26-M19-C9049.D | G96: RM-A-0021AI26-M19-C9049.D | H96: MEX126801 | I96: MARZO | J96: 46070 | K96: 26-85-34166012503 | L96: MXO101513735151 | M96: AIR IMPO | N96: OTRO | O96: 0 | P96: 17090.28 | Q96: 844.52 | R96: 135.12 | S96: 0 | T96: 18069.92 | U96: MXN | V96: =T96/17.5445 -> 1029.9478 | W96: 46070 | X96: JOHNSON ELECTRIC INDUSTRIAL MANUFACTORY LIMITED | Y96: USA | Z96: ZAC | AA96: JEG | AB96: M19 | AC96: I | AD96: AIR IMPO | AE96: 67130000 | AF96: NO COMMENTS | AI96: 08 | AJ96: NO | AK96: 0 | AL96: NO
A97: 08 | B97: MXG | C97: 1210 | D97: DICEX S.A DE C.V. | E97: BROKER | F97: =E97&G97 -> BROKERRM-M-011-SI26-M19-B | G97: RM-M-011-SI26-M19-B | H97: MZO191588 | I97: MARZO | J97: 46069 | K97: 26 16 1690 6003691 | L97: OOLU2038341220 | M97: IMPO | N97: TEMU7860817 | O97: 0 | P97: 0 | Q97: 2399.43 | R97: 383.91 | S97: 0 | T97: 2783.34 | U97: MXN | V97: =T97/17.5445 -> 158.64459 | W97: 46069 | X97: JOHNSON ELECTRIC INDUSTRIAL MANUFACTORY LIMITED | Y97: CHN | Z97: ZCL | AA97: JEG | AB97: M19 | AC97: I | AD97: SEA IMPO | AE97: 67120000 | AF97: NO COMMENTS | AI97: 08 | AJ97: NO | AK97: 0 | AL97: NO
A98: 08 | B98: MXG | C98: 1215 | D98: DICEX S.A DE C.V. | E98: BROKER | F98: =E98&G98 -> BROKERRM-M-014-SI26-M19-B | G98: RM-M-014-SI26-M19-B | H98: MZO191793 | I98: MARZO | J98: 46071 | K98: 26 16 1690 6003731 | L98: COSU6440036513 | M98: IMPO | N98: CSNU8857833 | O98: 0 | P98: 0 | Q98: 1218.49 | R98: 194.96 | S98: 0 | T98: 1413.45 | U98: MXN | V98: =T98/17.5445 -> 80.563709 | W98: 46071 | X98: JOHNSON ELECTRIC INDUSTRIAL MANUFACTORY LIMITED | Y98: CHN | Z98: ZCL | AA98: JEG | AB98: M19 | AC98: I | AD98: SEA IMPO | AE98: 67120000 | AF98: NO COMMENTS | AI98: 08 | AJ98: NO | AK98: 0 | AL98: NO
A99: 08 | B99: MXG | C99: 1216 | D99: DICEX S.A DE C.V. | E99: BROKER | F99: =E99&G99 -> BROKERRM-M-575-SI25-M19-B | G99: RM-M-575-SI25-M19-B | H99: MZO191841 | I99: MARZO | J99: 46071 | K99: 26 16 1690 6002203 | L99: OOLU2038304190 | M99: IMPO | N99: OERU4257315 | O99: 0 | P99: 67556.03 | Q99: 4451.68 | R99: 712.27 | S99: 0 | T99: 72719.98 | U99: MXN | V99: =T99/17.5445 -> 4144.8876 | W99: 46071 | X99: JOHNSON ELECTRIC INDUSTRIAL MANUFACTORY LIMITED | Y99: CHN | Z99: ZCL | AA99: JEG | AB99: M19 | AC99: I | AD99: SEA IMPO | AE99: 67120000 | AF99: MNND23753743 | AG99: 67115005 | AH99: 31500 | AI99: 08 | AJ99: NO | AK99: 0 | AL99: NO
A100: 08 | B100: MXG | C100: 1221 | D100: DICEX S.A DE C.V. | E100: BROKER | F100: =E100&G100 -> BROKERRM-M-002-SI26-M19-L | G100: RM-M-002-SI26-M19-L | H100: MZO192087 | I100: MARZO | J100: 46072 | K100: 26 16 1690 6003622 | L100: HLCUSEL251229287 | M100: IMPO | N100: HLCUSEL251229287 | O100: 0 | P100: 26522.24 | Q100: 2399.43 | R100: 383.91 | S100: 0 | T100: 29305.58 | U100: MXN | V100: =T100/17.5445 -> 1670.3571 | W100: 46072 | X100: JOHNSON ELECTRIC PVT LTD | Y100: IND | Z100: ZCL | AA100: JEG | AB100: M19 | AC100: I | AD100: SEA IMPO | AE100: 67120000 | AF100: 447071 | AG100: 67115005 | AH100: 8613 | AI100: 08 | AJ100: NO | AK100: 0 | AL100: NO
...

Sheet Sheet1
A1: REFERENCIA | B1: COSTO | C1: PROVEEDOR | D1: COSTO | E1: PROVEEDOR | F1: COSTO | G1: PROVEEDOR | H1: COSTO | I1: PROVEEDOR | J1: COSTO TOTAL
A2: FG-R-2135LE25.M45 | B2: 131.66816 | C2: DICEX S.A DE C.V. | J2: =B2+D2+F2+H2 -> 131.66816
A3: FG-R-2136LE25.M19 | J3: =B3+D3+F3+H3 -> 0
A4: FG-R-2137LE25.M01 | D4: 5225 | E4: P&P G | J4: =B4+D4+F4+H4 -> 5225
A5: FG-R-2137LE25.M01 | D5: 5225 | E5: P&P G | J5: =B5+D5+F5+H5 -> 5225
A6: FG-R-2138LE25.M19 | F6: 300.1 | G6: TDS | H6: 7438.89 | I6: BRABER | J6: =B6+D6+F6+H6 -> 7738.99
A7: FG-R-2138LE25.M19-2 | F7: 95.5 | G7: TDS | J7: =B7+D7+F7+H7 -> 95.5
A8: FG-R-2139LE25.M45 | B8: 133.95212 | C8: DICEX S.A DE C.V. | J8: =B8+D8+F8+H8 -> 133.95212
A9: FG-R-2140LE25.M01 | D9: 4545 | E9: P&P G | J9: =B9+D9+F9+H9 -> 4545
A10: FG-R-2141LE25.M19 | D10: 6025 | E10: P&P G | F10: 162 | G10: TDS | J10: =B10+D10+F10+H10 -> 6187
A11: FG-R-2141LE25.M19-2 | J11: =B11+D11+F11+H11 -> 0
A12: FG-R-2142LE25.M19 | D12: 5197 | E12: P&P G | J12: =B12+D12+F12+H12 -> 5197
A13: FG-R-2143LE25.M19 | D13: 5197 | E13: P&P G | J13: =B13+D13+F13+H13 -> 5197
A14: FG-R-2144LE25.M01 | D14: 5225 | E14: P&P G | J14: =B14+D14+F14+H14 -> 5225
A15: FG-R-2149LE25.M19 | D15: 5197 | E15: P&P G | J15: =B15+D15+F15+H15 -> 5197
A16: FG-R-2150LE25.M19 | D16: 9225 | E16: P&P G | F16: 68.7 | G16: TDS | J16: =B16+D16+F16+H16 -> 9293.7
A17: FG-R-2151LE25.M01 | D17: 4545 | E17: P&P G | J17: =B17+D17+F17+H17 -> 4545
A18: FG-R-2152LE25.M19 | B18: 1517.4212 | C18: DICEX S.A DE C.V. | D18: 6025 | E18: P&P G | F18: 37 | G18: TDS | J18: =B18+D18+F18+H18 -> 7579.4212
A19: FG-R-2152LE25.M19-1 | J19: =B19+D19+F19+H19 -> 0
A20: FG-R-2152LE25.M19-2 | J20: =B20+D20+F20+H20 -> 0
A21: FG-R-2153LE25.M19 | D21: 5197 | E21: P&P G | J21: =B21+D21+F21+H21 -> 5197
A22: FG-R-2154LE25.M01 | H22: 7651.51 | I22: BRABER | J22: =B22+D22+F22+H22 -> 7651.51
A23: FG-R-2154LE25.M01. | J23: =B23+D23+F23+H23 -> 0
A24: FG-R-2156LE25.M45 | B24: 187.49712 | C24: DICEX S.A DE C.V. | J24: =B24+D24+F24+H24 -> 187.49712
A25: FG-R-2158LE25.M45 | B25: 157.43023 | C25: DICEX S.A DE C.V. | J25: =B25+D25+F25+H25 -> 157.43023
A26: FG-R-2159LE25.M19 | D26: 5197 | E26: P&P G | J26: =B26+D26+F26+H26 -> 5197
A27: FG-R-2160LE25.M01 | D27: 5695 | E27: P&P G | J27: =B27+D27+F27+H27 -> 5695
A28: FG-R-2160LE25.M01-1 | J28: =B28+D28+F28+H28 -> 0
A29: FG-R-2161LE25.M19 | D29: 6025 | E29: P&P G | F29: 89.2 | G29: TDS | J29: =B29+D29+F29+H29 -> 6114.2
A30: FG-R-2161LE25.M19-1 | J30: =B30+D30+F30+H30 -> 0
A31: FG-R-2161LE25.M19-2 | J31: =B31+D31+F31+H31 -> 0
A32: FG-R-2162LE25.M01 | H32: 7535.98 | I32: BRABER | J32: =B32+D32+F32+H32 -> 7535.98
A33: FG-R-2162LE25.M01-2 | J33: =B33+D33+F33+H33 -> 0
A34: FG-R-2163LE25.M19 | F34: 91.5 | G34: TDS | H34: 7294.4 | I34: BRABER | J34: =B34+D34+F34+H34 -> 7385.9
A35: FG-R-2163LE25.M19-2 | F35: 32.5 | G35: TDS | J35: =B35+D35+F35+H35 -> 32.5
A36: FG-R-2164LE25.M19 | H36: 7519.58 | I36: BRABER | J36: =B36+D36+F36+H36 -> 7519.58
A37: FG-R-2173LE25.M | J37: =B37+D37+F37+H37 -> 0
A38: FG-R-2174LE25.M | J38: =B38+D38+F38+H38 -> 0
A39: FG-R-2175LE25.M | J39: =B39+D39+F39+H39 -> 0
A40: FG-R-2176LE25.M | J40: =B40+D40+F40+H40 -> 0
A41: FG-R-2177LE25.M | J41: =B41+D41+F41+H41 -> 0
A42: FG-R-2177LE25.M. | J42: =B42+D42+F42+H42 -> 0
A43: FG-R-2178LE25.M | J43: =B43+D43+F43+H43 -> 0
A44: FG-R-2178LE25.M-1 | J44: =B44+D44+F44+H44 -> 0
A45: FG-R-2178LE25.M-2 | J45: =B45+D45+F45+H45 -> 0
A46: FG-R-2179LE25.M45 | J46: =B46+D46+F46+H46 -> 0
J47: =SUM(J2:J46) -> 124189.83

Sheet Sheet3
A3: Sum of USD AMOUNT
A4: SUPPLIER | B4: REFERENCIA | C4: Total
